<Protocol Name="FloodingVehicleInCity">
    <CheckPoint Sim_Time="154.6" NumVehicleInCity="150" />
    <CheckPoint Sim_Time="158" NumVehicleInCity="151" />
    <CheckPoint Sim_Time="160.1" NumVehicleInCity="154" />
    <CheckPoint Sim_Time="173.1" NumVehicleInCity="164" />
    <CheckPoint Sim_Time="180" NumVehicleInCity="172" />
    <CheckPoint Sim_Time="188" NumVehicleInCity="178" />
    <CheckPoint Sim_Time="192" NumVehicleInCity="184" />
    <CheckPoint Sim_Time="195.2" NumVehicleInCity="187" />
    <CheckPoint Sim_Time="197.3" NumVehicleInCity="187" />
    <CheckPoint Sim_Time="200.4" NumVehicleInCity="189" />
    <CheckPoint Sim_Time="201.4" NumVehicleInCity="190" />
    <CheckPoint Sim_Time="201.8" NumVehicleInCity="189" />
    <CheckPoint Sim_Time="218.6" NumVehicleInCity="208" />
    <CheckPoint Sim_Time="218.7" NumVehicleInCity="207" />
    <CheckPoint Sim_Time="219" NumVehicleInCity="206" />
    <CheckPoint Sim_Time="219.2" NumVehicleInCity="206" />
    <CheckPoint Sim_Time="220.2" NumVehicleInCity="206" />
    <CheckPoint Sim_Time="220.5" NumVehicleInCity="206" />
    <CheckPoint Sim_Time="220.5" NumVehicleInCity="205" />
    <CheckPoint Sim_Time="220.9" NumVehicleInCity="204" />
    <CheckPoint Sim_Time="221.2" NumVehicleInCity="203" />
    <CheckPoint Sim_Time="222.6" NumVehicleInCity="203" />
    <CheckPoint Sim_Time="224.2" NumVehicleInCity="202" />
    <CheckPoint Sim_Time="226.8" NumVehicleInCity="205" />
    <CheckPoint Sim_Time="229" NumVehicleInCity="206" />
    <CheckPoint Sim_Time="230.2" NumVehicleInCity="207" />
    <CheckPoint Sim_Time="232.6" NumVehicleInCity="208" />
    <CheckPoint Sim_Time="239.3" NumVehicleInCity="213" />
    <CheckPoint Sim_Time="241.3" NumVehicleInCity="215" />
    <CheckPoint Sim_Time="244.2" NumVehicleInCity="216" />
    <CheckPoint Sim_Time="246.7" NumVehicleInCity="217" />
    <CheckPoint Sim_Time="254.7" NumVehicleInCity="227" />
    <CheckPoint Sim_Time="262.1" NumVehicleInCity="233" />
    <CheckPoint Sim_Time="264.2" NumVehicleInCity="235" />
    <CheckPoint Sim_Time="264.2" NumVehicleInCity="234" />
    <CheckPoint Sim_Time="264.5" NumVehicleInCity="233" />
    <CheckPoint Sim_Time="264.8" NumVehicleInCity="232" />
    <CheckPoint Sim_Time="266.1" NumVehicleInCity="233" />
    <CheckPoint Sim_Time="267.1" NumVehicleInCity="232" />
    <CheckPoint Sim_Time="268" NumVehicleInCity="233" />
    <CheckPoint Sim_Time="268.1" NumVehicleInCity="233" />
    <CheckPoint Sim_Time="271.5" NumVehicleInCity="235" />
    <CheckPoint Sim_Time="272.6" NumVehicleInCity="234" />
    <CheckPoint Sim_Time="273.3" NumVehicleInCity="233" />
    <CheckPoint Sim_Time="275.2" NumVehicleInCity="235" />
    <CheckPoint Sim_Time="275.8" NumVehicleInCity="234" />
    <CheckPoint Sim_Time="276.4" NumVehicleInCity="233" />
    <CheckPoint Sim_Time="277.8" NumVehicleInCity="234" />
    <CheckPoint Sim_Time="278.9" NumVehicleInCity="233" />
    <CheckPoint Sim_Time="280.1" NumVehicleInCity="235" />
    <CheckPoint Sim_Time="287" NumVehicleInCity="239" />
    <CheckPoint Sim_Time="291.6" NumVehicleInCity="242" />
    <CheckPoint Sim_Time="295.7" NumVehicleInCity="245" />
    <CheckPoint Sim_Time="307.4" NumVehicleInCity="256" />
    <CheckPoint Sim_Time="308.3" NumVehicleInCity="255" />
    <CheckPoint Sim_Time="308.4" NumVehicleInCity="254" />
    <CheckPoint Sim_Time="308.5" NumVehicleInCity="253" />
    <CheckPoint Sim_Time="308.7" NumVehicleInCity="252" />
    <CheckPoint Sim_Time="309.3" NumVehicleInCity="253" />
    <CheckPoint Sim_Time="309.4" NumVehicleInCity="252" />
    <CheckPoint Sim_Time="310.7" NumVehicleInCity="252" />
    <CheckPoint Sim_Time="311" NumVehicleInCity="252" />
    <CheckPoint Sim_Time="313.2" NumVehicleInCity="253" />
    <CheckPoint Sim_Time="313.2" NumVehicleInCity="252" />
    <CheckPoint Sim_Time="315.4" NumVehicleInCity="254" />
    <CheckPoint Sim_Time="315.4" NumVehicleInCity="253" />
    <CheckPoint Sim_Time="316.4" NumVehicleInCity="255" />
    <CheckPoint Sim_Time="317.5" NumVehicleInCity="258" />
    <CheckPoint Sim_Time="319.2" NumVehicleInCity="257" />
    <CheckPoint Sim_Time="320.1" NumVehicleInCity="257" />
    <CheckPoint Sim_Time="321.1" NumVehicleInCity="258" />
    <CheckPoint Sim_Time="322" NumVehicleInCity="258" />
    <CheckPoint Sim_Time="326.9" NumVehicleInCity="261" />
    <CheckPoint Sim_Time="328.9" NumVehicleInCity="264" />
    <CheckPoint Sim_Time="329.6" NumVehicleInCity="263" />
    <CheckPoint Sim_Time="330.6" NumVehicleInCity="262" />
    <CheckPoint Sim_Time="334.8" NumVehicleInCity="266" />
    <CheckPoint Sim_Time="335.1" NumVehicleInCity="265" />
    <CheckPoint Sim_Time="335.3" NumVehicleInCity="264" />
    <CheckPoint Sim_Time="336.3" NumVehicleInCity="265" />
    <CheckPoint Sim_Time="339.4" NumVehicleInCity="265" />
    <CheckPoint Sim_Time="339.9" NumVehicleInCity="265" />
    <CheckPoint Sim_Time="340.6" NumVehicleInCity="265" />
    <CheckPoint Sim_Time="353.4" NumVehicleInCity="278" />
    <CheckPoint Sim_Time="353.6" NumVehicleInCity="277" />
    <CheckPoint Sim_Time="353.7" NumVehicleInCity="276" />
    <CheckPoint Sim_Time="353.8" NumVehicleInCity="275" />
    <CheckPoint Sim_Time="354" NumVehicleInCity="274" />
    <CheckPoint Sim_Time="354.2" NumVehicleInCity="273" />
    <CheckPoint Sim_Time="354.6" NumVehicleInCity="272" />
    <CheckPoint Sim_Time="355.5" NumVehicleInCity="272" />
    <CheckPoint Sim_Time="355.7" NumVehicleInCity="271" />
    <CheckPoint Sim_Time="356.3" NumVehicleInCity="271" />
    <CheckPoint Sim_Time="356.8" NumVehicleInCity="270" />
    <CheckPoint Sim_Time="356.9" NumVehicleInCity="269" />
    <CheckPoint Sim_Time="358.4" NumVehicleInCity="271" />
    <CheckPoint Sim_Time="358.5" NumVehicleInCity="272" />
    <CheckPoint Sim_Time="359.8" NumVehicleInCity="271" />
    <CheckPoint Sim_Time="360.2" NumVehicleInCity="271" />
    <CheckPoint Sim_Time="361.7" NumVehicleInCity="270" />
    <CheckPoint Sim_Time="361.8" NumVehicleInCity="269" />
    <CheckPoint Sim_Time="362" NumVehicleInCity="269" />
    <CheckPoint Sim_Time="362.2" NumVehicleInCity="269" />
    <CheckPoint Sim_Time="364.1" NumVehicleInCity="271" />
    <CheckPoint Sim_Time="364.3" NumVehicleInCity="270" />
    <CheckPoint Sim_Time="365.1" NumVehicleInCity="271" />
    <CheckPoint Sim_Time="366.1" NumVehicleInCity="272" />
    <CheckPoint Sim_Time="366.4" NumVehicleInCity="271" />
    <CheckPoint Sim_Time="366.6" NumVehicleInCity="270" />
    <CheckPoint Sim_Time="366.6" NumVehicleInCity="269" />
    <CheckPoint Sim_Time="370.6" NumVehicleInCity="273" />
    <CheckPoint Sim_Time="371.1" NumVehicleInCity="273" />
    <CheckPoint Sim_Time="371.6" NumVehicleInCity="274" />
    <CheckPoint Sim_Time="375.6" NumVehicleInCity="277" />
    <CheckPoint Sim_Time="376.4" NumVehicleInCity="276" />
    <CheckPoint Sim_Time="376.9" NumVehicleInCity="275" />
    <CheckPoint Sim_Time="377.4" NumVehicleInCity="275" />
    <CheckPoint Sim_Time="379.3" NumVehicleInCity="278" />
    <CheckPoint Sim_Time="379.4" NumVehicleInCity="277" />
    <CheckPoint Sim_Time="382" NumVehicleInCity="278" />
    <CheckPoint Sim_Time="384" NumVehicleInCity="280" />
    <CheckPoint Sim_Time="397.5" NumVehicleInCity="295" />
    <CheckPoint Sim_Time="398" NumVehicleInCity="294" />
    <CheckPoint Sim_Time="398.6" NumVehicleInCity="294" />
    <CheckPoint Sim_Time="398.7" NumVehicleInCity="293" />
    <CheckPoint Sim_Time="399.2" NumVehicleInCity="293" />
    <CheckPoint Sim_Time="399.4" NumVehicleInCity="292" />
    <CheckPoint Sim_Time="400.2" NumVehicleInCity="293" />
    <CheckPoint Sim_Time="400.5" NumVehicleInCity="292" />
    <CheckPoint Sim_Time="400.8" NumVehicleInCity="291" />
    <CheckPoint Sim_Time="401.1" NumVehicleInCity="290" />
    <CheckPoint Sim_Time="401.3" NumVehicleInCity="290" />
    <CheckPoint Sim_Time="402" NumVehicleInCity="289" />
    <CheckPoint Sim_Time="402.3" NumVehicleInCity="288" />
    <CheckPoint Sim_Time="403" NumVehicleInCity="287" />
    <CheckPoint Sim_Time="403.2" NumVehicleInCity="287" />
    <CheckPoint Sim_Time="406.3" NumVehicleInCity="291" />
    <CheckPoint Sim_Time="406.5" NumVehicleInCity="290" />
    <CheckPoint Sim_Time="406.8" NumVehicleInCity="289" />
    <CheckPoint Sim_Time="408.4" NumVehicleInCity="289" />
    <CheckPoint Sim_Time="409.7" NumVehicleInCity="289" />
    <CheckPoint Sim_Time="410.9" NumVehicleInCity="291" />
    <CheckPoint Sim_Time="411.5" NumVehicleInCity="290" />
    <CheckPoint Sim_Time="416.2" NumVehicleInCity="293" />
    <CheckPoint Sim_Time="417.9" NumVehicleInCity="294" />
    <CheckPoint Sim_Time="420.3" NumVehicleInCity="297" />
    <CheckPoint Sim_Time="420.3" NumVehicleInCity="296" />
    <CheckPoint Sim_Time="420.4" NumVehicleInCity="295" />
    <CheckPoint Sim_Time="423.3" NumVehicleInCity="295" />
    <CheckPoint Sim_Time="423.5" NumVehicleInCity="294" />
    <CheckPoint Sim_Time="423.7" NumVehicleInCity="294" />
    <CheckPoint Sim_Time="425" NumVehicleInCity="294" />
    <CheckPoint Sim_Time="425.2" NumVehicleInCity="294" />
    <CheckPoint Sim_Time="427.8" NumVehicleInCity="296" />
    <CheckPoint Sim_Time="429.3" NumVehicleInCity="297" />
    <CheckPoint Sim_Time="430.6" NumVehicleInCity="297" />
    <CheckPoint Sim_Time="432.7" NumVehicleInCity="299" />
    <CheckPoint Sim_Time="443" NumVehicleInCity="310" />
    <CheckPoint Sim_Time="443.3" NumVehicleInCity="309" />
    <CheckPoint Sim_Time="443.4" NumVehicleInCity="308" />
    <CheckPoint Sim_Time="443.8" NumVehicleInCity="307" />
    <CheckPoint Sim_Time="444.1" NumVehicleInCity="306" />
    <CheckPoint Sim_Time="445.3" NumVehicleInCity="306" />
    <CheckPoint Sim_Time="445.7" NumVehicleInCity="306" />
    <CheckPoint Sim_Time="446" NumVehicleInCity="306" />
    <CheckPoint Sim_Time="446.3" NumVehicleInCity="306" />
    <CheckPoint Sim_Time="447.2" NumVehicleInCity="306" />
    <CheckPoint Sim_Time="447.5" NumVehicleInCity="305" />
    <CheckPoint Sim_Time="447.7" NumVehicleInCity="304" />
    <CheckPoint Sim_Time="448.3" NumVehicleInCity="303" />
    <CheckPoint Sim_Time="448.7" NumVehicleInCity="302" />
    <CheckPoint Sim_Time="448.8" NumVehicleInCity="301" />
    <CheckPoint Sim_Time="448.9" NumVehicleInCity="300" />
    <CheckPoint Sim_Time="449.4" NumVehicleInCity="299" />
    <CheckPoint Sim_Time="449.6" NumVehicleInCity="298" />
    <CheckPoint Sim_Time="450.1" NumVehicleInCity="298" />
    <CheckPoint Sim_Time="453.4" NumVehicleInCity="302" />
    <CheckPoint Sim_Time="456.8" NumVehicleInCity="302" />
    <CheckPoint Sim_Time="457.3" NumVehicleInCity="302" />
    <CheckPoint Sim_Time="457.5" NumVehicleInCity="303" />
    <CheckPoint Sim_Time="458.2" NumVehicleInCity="302" />
    <CheckPoint Sim_Time="460" NumVehicleInCity="303" />
    <CheckPoint Sim_Time="460.5" NumVehicleInCity="302" />
    <CheckPoint Sim_Time="461.7" NumVehicleInCity="301" />
    <CheckPoint Sim_Time="463" NumVehicleInCity="301" />
    <CheckPoint Sim_Time="466" NumVehicleInCity="304" />
    <CheckPoint Sim_Time="467.7" NumVehicleInCity="304" />
    <CheckPoint Sim_Time="467.8" NumVehicleInCity="303" />
    <CheckPoint Sim_Time="468.8" NumVehicleInCity="303" />
    <CheckPoint Sim_Time="470.8" NumVehicleInCity="306" />
    <CheckPoint Sim_Time="471.6" NumVehicleInCity="305" />
    <CheckPoint Sim_Time="472.7" NumVehicleInCity="304" />
    <CheckPoint Sim_Time="474.6" NumVehicleInCity="306" />
    <CheckPoint Sim_Time="474.7" NumVehicleInCity="305" />
    <CheckPoint Sim_Time="476.3" NumVehicleInCity="306" />
    <CheckPoint Sim_Time="476.6" NumVehicleInCity="305" />
    <CheckPoint Sim_Time="487.3" NumVehicleInCity="314" />
    <CheckPoint Sim_Time="488.3" NumVehicleInCity="314" />
    <CheckPoint Sim_Time="488.5" NumVehicleInCity="313" />
    <CheckPoint Sim_Time="489.3" NumVehicleInCity="313" />
    <CheckPoint Sim_Time="489.4" NumVehicleInCity="312" />
    <CheckPoint Sim_Time="490.4" NumVehicleInCity="312" />
    <CheckPoint Sim_Time="490.8" NumVehicleInCity="311" />
    <CheckPoint Sim_Time="491" NumVehicleInCity="310" />
    <CheckPoint Sim_Time="492.1" NumVehicleInCity="311" />
    <CheckPoint Sim_Time="492.3" NumVehicleInCity="310" />
    <CheckPoint Sim_Time="492.4" NumVehicleInCity="309" />
    <CheckPoint Sim_Time="492.7" NumVehicleInCity="308" />
    <CheckPoint Sim_Time="493.2" NumVehicleInCity="308" />
    <CheckPoint Sim_Time="493.7" NumVehicleInCity="307" />
    <CheckPoint Sim_Time="494.4" NumVehicleInCity="308" />
    <CheckPoint Sim_Time="494.7" NumVehicleInCity="308" />
    <CheckPoint Sim_Time="494.9" NumVehicleInCity="308" />
    <CheckPoint Sim_Time="497.2" NumVehicleInCity="312" />
    <CheckPoint Sim_Time="498" NumVehicleInCity="312" />
    <CheckPoint Sim_Time="499.7" NumVehicleInCity="312" />
    <CheckPoint Sim_Time="500.5" NumVehicleInCity="312" />
    <CheckPoint Sim_Time="500.9" NumVehicleInCity="311" />
    <CheckPoint Sim_Time="502.3" NumVehicleInCity="311" />
    <CheckPoint Sim_Time="503.1" NumVehicleInCity="311" />
    <CheckPoint Sim_Time="503.6" NumVehicleInCity="311" />
    <CheckPoint Sim_Time="505" NumVehicleInCity="310" />
    <CheckPoint Sim_Time="506.1" NumVehicleInCity="312" />
    <CheckPoint Sim_Time="508.1" NumVehicleInCity="312" />
    <CheckPoint Sim_Time="508.1" NumVehicleInCity="311" />
    <CheckPoint Sim_Time="509.9" NumVehicleInCity="312" />
    <CheckPoint Sim_Time="512.4" NumVehicleInCity="313" />
    <CheckPoint Sim_Time="512.8" NumVehicleInCity="312" />
    <CheckPoint Sim_Time="515.2" NumVehicleInCity="313" />
    <CheckPoint Sim_Time="516" NumVehicleInCity="313" />
    <CheckPoint Sim_Time="519.7" NumVehicleInCity="317" />
    <CheckPoint Sim_Time="520.1" NumVehicleInCity="317" />
    <CheckPoint Sim_Time="522.9" NumVehicleInCity="319" />
    <CheckPoint Sim_Time="532.7" NumVehicleInCity="331" />
    <CheckPoint Sim_Time="533.4" NumVehicleInCity="331" />
    <CheckPoint Sim_Time="533.4" NumVehicleInCity="330" />
    <CheckPoint Sim_Time="533.7" NumVehicleInCity="329" />
    <CheckPoint Sim_Time="534" NumVehicleInCity="328" />
    <CheckPoint Sim_Time="534.6" NumVehicleInCity="327" />
    <CheckPoint Sim_Time="535.6" NumVehicleInCity="328" />
    <CheckPoint Sim_Time="535.8" NumVehicleInCity="327" />
    <CheckPoint Sim_Time="535.8" NumVehicleInCity="326" />
    <CheckPoint Sim_Time="536" NumVehicleInCity="325" />
    <CheckPoint Sim_Time="536.1" NumVehicleInCity="325" />
    <CheckPoint Sim_Time="536.4" NumVehicleInCity="325" />
    <CheckPoint Sim_Time="537.8" NumVehicleInCity="325" />
    <CheckPoint Sim_Time="537.9" NumVehicleInCity="324" />
    <CheckPoint Sim_Time="538.1" NumVehicleInCity="324" />
    <CheckPoint Sim_Time="538.2" NumVehicleInCity="323" />
    <CheckPoint Sim_Time="539.3" NumVehicleInCity="323" />
    <CheckPoint Sim_Time="539.6" NumVehicleInCity="322" />
    <CheckPoint Sim_Time="539.8" NumVehicleInCity="321" />
    <CheckPoint Sim_Time="539.8" NumVehicleInCity="320" />
    <CheckPoint Sim_Time="540.1" NumVehicleInCity="319" />
    <CheckPoint Sim_Time="541.7" NumVehicleInCity="319" />
    <CheckPoint Sim_Time="543.8" NumVehicleInCity="320" />
    <CheckPoint Sim_Time="543.9" NumVehicleInCity="319" />
    <CheckPoint Sim_Time="545.5" NumVehicleInCity="321" />
    <CheckPoint Sim_Time="546.6" NumVehicleInCity="321" />
    <CheckPoint Sim_Time="547" NumVehicleInCity="320" />
    <CheckPoint Sim_Time="547.8" NumVehicleInCity="319" />
    <CheckPoint Sim_Time="548.5" NumVehicleInCity="319" />
    <CheckPoint Sim_Time="551.1" NumVehicleInCity="321" />
    <CheckPoint Sim_Time="551.3" NumVehicleInCity="320" />
    <CheckPoint Sim_Time="555.5" NumVehicleInCity="322" />
    <CheckPoint Sim_Time="556.5" NumVehicleInCity="322" />
    <CheckPoint Sim_Time="558.4" NumVehicleInCity="322" />
    <CheckPoint Sim_Time="560.5" NumVehicleInCity="325" />
    <CheckPoint Sim_Time="561.5" NumVehicleInCity="324" />
    <CheckPoint Sim_Time="562.7" NumVehicleInCity="324" />
    <CheckPoint Sim_Time="566.4" NumVehicleInCity="326" />
    <CheckPoint Sim_Time="577" NumVehicleInCity="337" />
    <CheckPoint Sim_Time="578.1" NumVehicleInCity="337" />
    <CheckPoint Sim_Time="578.3" NumVehicleInCity="336" />
    <CheckPoint Sim_Time="578.4" NumVehicleInCity="335" />
    <CheckPoint Sim_Time="578.9" NumVehicleInCity="335" />
    <CheckPoint Sim_Time="579.1" NumVehicleInCity="334" />
    <CheckPoint Sim_Time="579.1" NumVehicleInCity="333" />
    <CheckPoint Sim_Time="580.4" NumVehicleInCity="333" />
    <CheckPoint Sim_Time="580.5" NumVehicleInCity="332" />
    <CheckPoint Sim_Time="581.2" NumVehicleInCity="332" />
    <CheckPoint Sim_Time="582.7" NumVehicleInCity="333" />
    <CheckPoint Sim_Time="582.9" NumVehicleInCity="332" />
    <CheckPoint Sim_Time="582.9" NumVehicleInCity="331" />
    <CheckPoint Sim_Time="583.9" NumVehicleInCity="331" />
    <CheckPoint Sim_Time="584.5" NumVehicleInCity="331" />
    <CheckPoint Sim_Time="585" NumVehicleInCity="330" />
    <CheckPoint Sim_Time="586" NumVehicleInCity="330" />
    <CheckPoint Sim_Time="586.8" NumVehicleInCity="329" />
    <CheckPoint Sim_Time="586.9" NumVehicleInCity="328" />
    <CheckPoint Sim_Time="588.7" NumVehicleInCity="330" />
    <CheckPoint Sim_Time="590.2" NumVehicleInCity="331" />
    <CheckPoint Sim_Time="590.4" NumVehicleInCity="330" />
    <CheckPoint Sim_Time="591.4" NumVehicleInCity="329" />
    <CheckPoint Sim_Time="592.3" NumVehicleInCity="329" />
    <CheckPoint Sim_Time="594.7" NumVehicleInCity="332" />
    <CheckPoint Sim_Time="599" NumVehicleInCity="334" />
    <CheckPoint Sim_Time="602.2" NumVehicleInCity="337" />
    <CheckPoint Sim_Time="605" NumVehicleInCity="337" />
    <CheckPoint Sim_Time="609" NumVehicleInCity="340" />
    <CheckPoint Sim_Time="622.6" NumVehicleInCity="355" />
    <CheckPoint Sim_Time="622.7" NumVehicleInCity="354" />
    <CheckPoint Sim_Time="623.2" NumVehicleInCity="354" />
    <CheckPoint Sim_Time="623.3" NumVehicleInCity="353" />
    <CheckPoint Sim_Time="624.3" NumVehicleInCity="352" />
    <CheckPoint Sim_Time="624.3" NumVehicleInCity="351" />
    <CheckPoint Sim_Time="624.8" NumVehicleInCity="350" />
    <CheckPoint Sim_Time="625.4" NumVehicleInCity="350" />
    <CheckPoint Sim_Time="625.6" NumVehicleInCity="349" />
    <CheckPoint Sim_Time="625.8" NumVehicleInCity="348" />
    <CheckPoint Sim_Time="626.4" NumVehicleInCity="348" />
    <CheckPoint Sim_Time="627.3" NumVehicleInCity="348" />
    <CheckPoint Sim_Time="627.6" NumVehicleInCity="347" />
    <CheckPoint Sim_Time="627.7" NumVehicleInCity="346" />
    <CheckPoint Sim_Time="628.3" NumVehicleInCity="346" />
    <CheckPoint Sim_Time="628.8" NumVehicleInCity="347" />
    <CheckPoint Sim_Time="629.7" NumVehicleInCity="346" />
    <CheckPoint Sim_Time="629.8" NumVehicleInCity="345" />
    <CheckPoint Sim_Time="630.1" NumVehicleInCity="345" />
    <CheckPoint Sim_Time="630.9" NumVehicleInCity="344" />
    <CheckPoint Sim_Time="631.5" NumVehicleInCity="343" />
    <CheckPoint Sim_Time="631.9" NumVehicleInCity="342" />
    <CheckPoint Sim_Time="632" NumVehicleInCity="341" />
    <CheckPoint Sim_Time="632.6" NumVehicleInCity="341" />
    <CheckPoint Sim_Time="632.7" NumVehicleInCity="340" />
    <CheckPoint Sim_Time="633.5" NumVehicleInCity="340" />
    <CheckPoint Sim_Time="633.8" NumVehicleInCity="339" />
    <CheckPoint Sim_Time="634.4" NumVehicleInCity="339" />
    <CheckPoint Sim_Time="634.7" NumVehicleInCity="338" />
    <CheckPoint Sim_Time="635.4" NumVehicleInCity="340" />
    <CheckPoint Sim_Time="635.5" NumVehicleInCity="339" />
    <CheckPoint Sim_Time="636.1" NumVehicleInCity="338" />
    <CheckPoint Sim_Time="636.3" NumVehicleInCity="337" />
    <CheckPoint Sim_Time="637.3" NumVehicleInCity="337" />
    <CheckPoint Sim_Time="637.3" NumVehicleInCity="336" />
    <CheckPoint Sim_Time="637.5" NumVehicleInCity="335" />
    <CheckPoint Sim_Time="639.6" NumVehicleInCity="334" />
    <CheckPoint Sim_Time="641.6" NumVehicleInCity="338" />
    <CheckPoint Sim_Time="642.5" NumVehicleInCity="338" />
    <CheckPoint Sim_Time="643.4" NumVehicleInCity="338" />
    <CheckPoint Sim_Time="644.9" NumVehicleInCity="338" />
    <CheckPoint Sim_Time="647.9" NumVehicleInCity="340" />
    <CheckPoint Sim_Time="648.2" NumVehicleInCity="340" />
    <CheckPoint Sim_Time="648.3" NumVehicleInCity="339" />
    <CheckPoint Sim_Time="648.4" NumVehicleInCity="338" />
    <CheckPoint Sim_Time="651.5" NumVehicleInCity="340" />
    <CheckPoint Sim_Time="651.6" NumVehicleInCity="339" />
    <CheckPoint Sim_Time="651.8" NumVehicleInCity="338" />
    <CheckPoint Sim_Time="652.3" NumVehicleInCity="338" />
    <CheckPoint Sim_Time="653.2" NumVehicleInCity="337" />
    <CheckPoint Sim_Time="653.7" NumVehicleInCity="336" />
    <CheckPoint Sim_Time="653.9" NumVehicleInCity="335" />
    <CheckPoint Sim_Time="654.4" NumVehicleInCity="335" />
    <CheckPoint Sim_Time="654.8" NumVehicleInCity="334" />
    <CheckPoint Sim_Time="655.5" NumVehicleInCity="333" />
    <CheckPoint Sim_Time="655.9" NumVehicleInCity="333" />
    <CheckPoint Sim_Time="656.1" NumVehicleInCity="334" />
    <CheckPoint Sim_Time="656.8" NumVehicleInCity="333" />
    <CheckPoint Sim_Time="667.7" NumVehicleInCity="341" />
    <CheckPoint Sim_Time="667.8" NumVehicleInCity="340" />
    <CheckPoint Sim_Time="668" NumVehicleInCity="339" />
    <CheckPoint Sim_Time="668.2" NumVehicleInCity="339" />
    <CheckPoint Sim_Time="668.5" NumVehicleInCity="338" />
    <CheckPoint Sim_Time="668.6" NumVehicleInCity="337" />
    <CheckPoint Sim_Time="668.8" NumVehicleInCity="336" />
    <CheckPoint Sim_Time="669.3" NumVehicleInCity="337" />
    <CheckPoint Sim_Time="670" NumVehicleInCity="336" />
    <CheckPoint Sim_Time="670.1" NumVehicleInCity="336" />
    <CheckPoint Sim_Time="670.9" NumVehicleInCity="335" />
    <CheckPoint Sim_Time="671.1" NumVehicleInCity="334" />
    <CheckPoint Sim_Time="671.5" NumVehicleInCity="333" />
    <CheckPoint Sim_Time="671.7" NumVehicleInCity="333" />
    <CheckPoint Sim_Time="672.3" NumVehicleInCity="333" />
    <CheckPoint Sim_Time="672.6" NumVehicleInCity="332" />
    <CheckPoint Sim_Time="673.9" NumVehicleInCity="332" />
    <CheckPoint Sim_Time="674.7" NumVehicleInCity="331" />
    <CheckPoint Sim_Time="675" NumVehicleInCity="330" />
    <CheckPoint Sim_Time="675.1" NumVehicleInCity="330" />
    <CheckPoint Sim_Time="675.7" NumVehicleInCity="331" />
    <CheckPoint Sim_Time="676.2" NumVehicleInCity="330" />
    <CheckPoint Sim_Time="676.6" NumVehicleInCity="329" />
    <CheckPoint Sim_Time="676.6" NumVehicleInCity="328" />
    <CheckPoint Sim_Time="677.1" NumVehicleInCity="328" />
    <CheckPoint Sim_Time="678.8" NumVehicleInCity="328" />
    <CheckPoint Sim_Time="679.5" NumVehicleInCity="327" />
    <CheckPoint Sim_Time="681.2" NumVehicleInCity="326" />
    <CheckPoint Sim_Time="682.7" NumVehicleInCity="328" />
    <CheckPoint Sim_Time="683.8" NumVehicleInCity="328" />
    <CheckPoint Sim_Time="685" NumVehicleInCity="327" />
    <CheckPoint Sim_Time="685.1" NumVehicleInCity="326" />
    <CheckPoint Sim_Time="687.7" NumVehicleInCity="326" />
    <CheckPoint Sim_Time="690.3" NumVehicleInCity="328" />
    <CheckPoint Sim_Time="691.3" NumVehicleInCity="327" />
    <CheckPoint Sim_Time="692" NumVehicleInCity="326" />
    <CheckPoint Sim_Time="693.2" NumVehicleInCity="326" />
    <CheckPoint Sim_Time="696.3" NumVehicleInCity="330" />
    <CheckPoint Sim_Time="697.4" NumVehicleInCity="329" />
    <CheckPoint Sim_Time="697.7" NumVehicleInCity="328" />
    <CheckPoint Sim_Time="699.2" NumVehicleInCity="328" />
    <CheckPoint Sim_Time="699.7" NumVehicleInCity="327" />
    <CheckPoint Sim_Time="712.1" NumVehicleInCity="339" />
    <CheckPoint Sim_Time="713.3" NumVehicleInCity="340" />
    <CheckPoint Sim_Time="713.3" NumVehicleInCity="339" />
    <CheckPoint Sim_Time="713.6" NumVehicleInCity="339" />
    <CheckPoint Sim_Time="713.7" NumVehicleInCity="338" />
    <CheckPoint Sim_Time="713.7" NumVehicleInCity="337" />
    <CheckPoint Sim_Time="714.5" NumVehicleInCity="339" />
    <CheckPoint Sim_Time="715.3" NumVehicleInCity="338" />
    <CheckPoint Sim_Time="715.7" NumVehicleInCity="337" />
    <CheckPoint Sim_Time="715.9" NumVehicleInCity="337" />
    <CheckPoint Sim_Time="716" NumVehicleInCity="336" />
    <CheckPoint Sim_Time="716.3" NumVehicleInCity="335" />
    <CheckPoint Sim_Time="717.9" NumVehicleInCity="334" />
    <CheckPoint Sim_Time="718.2" NumVehicleInCity="334" />
    <CheckPoint Sim_Time="718.3" NumVehicleInCity="333" />
    <CheckPoint Sim_Time="719" NumVehicleInCity="333" />
    <CheckPoint Sim_Time="720.2" NumVehicleInCity="332" />
    <CheckPoint Sim_Time="720.4" NumVehicleInCity="332" />
    <CheckPoint Sim_Time="720.9" NumVehicleInCity="331" />
    <CheckPoint Sim_Time="722.5" NumVehicleInCity="332" />
    <CheckPoint Sim_Time="722.9" NumVehicleInCity="331" />
    <CheckPoint Sim_Time="723.2" NumVehicleInCity="330" />
    <CheckPoint Sim_Time="724.5" NumVehicleInCity="329" />
    <CheckPoint Sim_Time="724.9" NumVehicleInCity="328" />
    <CheckPoint Sim_Time="725.4" NumVehicleInCity="328" />
    <CheckPoint Sim_Time="725.5" NumVehicleInCity="327" />
    <CheckPoint Sim_Time="726.4" NumVehicleInCity="328" />
    <CheckPoint Sim_Time="726.6" NumVehicleInCity="327" />
    <CheckPoint Sim_Time="727.8" NumVehicleInCity="328" />
    <CheckPoint Sim_Time="728" NumVehicleInCity="327" />
    <CheckPoint Sim_Time="730.6" NumVehicleInCity="327" />
    <CheckPoint Sim_Time="731.5" NumVehicleInCity="326" />
    <CheckPoint Sim_Time="732.4" NumVehicleInCity="329" />
    <CheckPoint Sim_Time="732.9" NumVehicleInCity="328" />
    <CheckPoint Sim_Time="733.2" NumVehicleInCity="328" />
    <CheckPoint Sim_Time="736" NumVehicleInCity="327" />
    <CheckPoint Sim_Time="740" NumVehicleInCity="332" />
    <CheckPoint Sim_Time="740.5" NumVehicleInCity="331" />
    <CheckPoint Sim_Time="740.9" NumVehicleInCity="330" />
    <CheckPoint Sim_Time="742.6" NumVehicleInCity="330" />
    <CheckPoint Sim_Time="743.1" NumVehicleInCity="331" />
    <CheckPoint Sim_Time="743.3" NumVehicleInCity="330" />
    <CheckPoint Sim_Time="744" NumVehicleInCity="329" />
    <CheckPoint Sim_Time="744" NumVehicleInCity="328" />
    <CheckPoint Sim_Time="744.6" NumVehicleInCity="329" />
    <CheckPoint Sim_Time="745.5" NumVehicleInCity="329" />
    <CheckPoint Sim_Time="745.6" NumVehicleInCity="329" />
    <CheckPoint Sim_Time="747.8" NumVehicleInCity="329" />
    <CheckPoint Sim_Time="758.4" NumVehicleInCity="339" />
    <CheckPoint Sim_Time="758.4" NumVehicleInCity="338" />
    <CheckPoint Sim_Time="758.7" NumVehicleInCity="337" />
    <CheckPoint Sim_Time="758.7" NumVehicleInCity="336" />
    <CheckPoint Sim_Time="758.7" NumVehicleInCity="335" />
    <CheckPoint Sim_Time="759.4" NumVehicleInCity="335" />
    <CheckPoint Sim_Time="759.5" NumVehicleInCity="335" />
    <CheckPoint Sim_Time="760.6" NumVehicleInCity="335" />
    <CheckPoint Sim_Time="760.8" NumVehicleInCity="336" />
    <CheckPoint Sim_Time="761" NumVehicleInCity="335" />
    <CheckPoint Sim_Time="761.3" NumVehicleInCity="334" />
    <CheckPoint Sim_Time="761.6" NumVehicleInCity="333" />
    <CheckPoint Sim_Time="761.7" NumVehicleInCity="332" />
    <CheckPoint Sim_Time="762.9" NumVehicleInCity="331" />
    <CheckPoint Sim_Time="763" NumVehicleInCity="331" />
    <CheckPoint Sim_Time="763" NumVehicleInCity="330" />
    <CheckPoint Sim_Time="764.1" NumVehicleInCity="331" />
    <CheckPoint Sim_Time="764.2" NumVehicleInCity="330" />
    <CheckPoint Sim_Time="764.9" NumVehicleInCity="329" />
    <CheckPoint Sim_Time="764.9" NumVehicleInCity="328" />
    <CheckPoint Sim_Time="765.4" NumVehicleInCity="329" />
    <CheckPoint Sim_Time="767.5" NumVehicleInCity="335" />
    <CheckPoint Sim_Time="768.9" NumVehicleInCity="334" />
    <CheckPoint Sim_Time="769.8" NumVehicleInCity="333" />
    <CheckPoint Sim_Time="771.8" NumVehicleInCity="336" />
    <CheckPoint Sim_Time="772.4" NumVehicleInCity="338" />
    <CheckPoint Sim_Time="773.2" NumVehicleInCity="337" />
    <CheckPoint Sim_Time="774.7" NumVehicleInCity="336" />
    <CheckPoint Sim_Time="775" NumVehicleInCity="336" />
    <CheckPoint Sim_Time="775.1" NumVehicleInCity="335" />
    <CheckPoint Sim_Time="775.4" NumVehicleInCity="334" />
    <CheckPoint Sim_Time="777.1" NumVehicleInCity="335" />
    <CheckPoint Sim_Time="782.6" NumVehicleInCity="341" />
    <CheckPoint Sim_Time="782.6" NumVehicleInCity="340" />
    <CheckPoint Sim_Time="784.8" NumVehicleInCity="342" />
    <CheckPoint Sim_Time="785.2" NumVehicleInCity="341" />
    <CheckPoint Sim_Time="787.8" NumVehicleInCity="341" />
    <CheckPoint Sim_Time="788" NumVehicleInCity="340" />
    <CheckPoint Sim_Time="789" NumVehicleInCity="341" />
    <CheckPoint Sim_Time="789.4" NumVehicleInCity="340" />
    <CheckPoint Sim_Time="790" NumVehicleInCity="339" />
    <CheckPoint Sim_Time="790.2" NumVehicleInCity="339" />
    <CheckPoint Sim_Time="792.6" NumVehicleInCity="338" />
    <CheckPoint Sim_Time="802.3" NumVehicleInCity="349" />
    <CheckPoint Sim_Time="802.6" NumVehicleInCity="348" />
    <CheckPoint Sim_Time="803.1" NumVehicleInCity="348" />
    <CheckPoint Sim_Time="803.3" NumVehicleInCity="348" />
    <CheckPoint Sim_Time="803.9" NumVehicleInCity="348" />
    <CheckPoint Sim_Time="805" NumVehicleInCity="348" />
    <CheckPoint Sim_Time="805.1" NumVehicleInCity="347" />
    <CheckPoint Sim_Time="805.3" NumVehicleInCity="346" />
    <CheckPoint Sim_Time="806" NumVehicleInCity="345" />
    <CheckPoint Sim_Time="806.1" NumVehicleInCity="345" />
    <CheckPoint Sim_Time="806.5" NumVehicleInCity="344" />
    <CheckPoint Sim_Time="806.7" NumVehicleInCity="343" />
    <CheckPoint Sim_Time="807" NumVehicleInCity="342" />
    <CheckPoint Sim_Time="807.1" NumVehicleInCity="341" />
    <CheckPoint Sim_Time="807.6" NumVehicleInCity="340" />
    <CheckPoint Sim_Time="807.9" NumVehicleInCity="340" />
    <CheckPoint Sim_Time="809.1" NumVehicleInCity="340" />
    <CheckPoint Sim_Time="809.5" NumVehicleInCity="340" />
    <CheckPoint Sim_Time="809.9" NumVehicleInCity="340" />
    <CheckPoint Sim_Time="810.3" NumVehicleInCity="339" />
    <CheckPoint Sim_Time="810.8" NumVehicleInCity="339" />
    <CheckPoint Sim_Time="811.4" NumVehicleInCity="340" />
    <CheckPoint Sim_Time="812" NumVehicleInCity="339" />
    <CheckPoint Sim_Time="814.3" NumVehicleInCity="339" />
    <CheckPoint Sim_Time="816" NumVehicleInCity="340" />
    <CheckPoint Sim_Time="817.2" NumVehicleInCity="340" />
    <CheckPoint Sim_Time="817.6" NumVehicleInCity="340" />
    <CheckPoint Sim_Time="818.7" NumVehicleInCity="340" />
    <CheckPoint Sim_Time="819" NumVehicleInCity="339" />
    <CheckPoint Sim_Time="820.3" NumVehicleInCity="339" />
    <CheckPoint Sim_Time="820.3" NumVehicleInCity="338" />
    <CheckPoint Sim_Time="820.5" NumVehicleInCity="337" />
    <CheckPoint Sim_Time="821.1" NumVehicleInCity="337" />
    <CheckPoint Sim_Time="821.4" NumVehicleInCity="336" />
    <CheckPoint Sim_Time="824.7" NumVehicleInCity="341" />
    <CheckPoint Sim_Time="827.6" NumVehicleInCity="340" />
    <CheckPoint Sim_Time="832.4" NumVehicleInCity="346" />
    <CheckPoint Sim_Time="833.1" NumVehicleInCity="345" />
    <CheckPoint Sim_Time="834.8" NumVehicleInCity="346" />
    <CheckPoint Sim_Time="835.3" NumVehicleInCity="347" />
    <CheckPoint Sim_Time="836.3" NumVehicleInCity="347" />
    <CheckPoint Sim_Time="838.2" NumVehicleInCity="348" />
    <CheckPoint Sim_Time="842.7" NumVehicleInCity="351" />
    <CheckPoint Sim_Time="847.7" NumVehicleInCity="355" />
    <CheckPoint Sim_Time="847.9" NumVehicleInCity="355" />
    <CheckPoint Sim_Time="848.4" NumVehicleInCity="354" />
    <CheckPoint Sim_Time="848.5" NumVehicleInCity="353" />
    <CheckPoint Sim_Time="849.3" NumVehicleInCity="352" />
    <CheckPoint Sim_Time="849.8" NumVehicleInCity="351" />
    <CheckPoint Sim_Time="850.1" NumVehicleInCity="350" />
    <CheckPoint Sim_Time="850.3" NumVehicleInCity="349" />
    <CheckPoint Sim_Time="851" NumVehicleInCity="348" />
    <CheckPoint Sim_Time="851.8" NumVehicleInCity="349" />
    <CheckPoint Sim_Time="852.8" NumVehicleInCity="349" />
    <CheckPoint Sim_Time="853.1" NumVehicleInCity="348" />
    <CheckPoint Sim_Time="854.9" NumVehicleInCity="348" />
    <CheckPoint Sim_Time="855" NumVehicleInCity="347" />
    <CheckPoint Sim_Time="856" NumVehicleInCity="347" />
    <CheckPoint Sim_Time="857.6" NumVehicleInCity="348" />
    <CheckPoint Sim_Time="858.4" NumVehicleInCity="351" />
    <CheckPoint Sim_Time="859.5" NumVehicleInCity="350" />
    <CheckPoint Sim_Time="859.8" NumVehicleInCity="349" />
    <CheckPoint Sim_Time="860.3" NumVehicleInCity="348" />
    <CheckPoint Sim_Time="861.1" NumVehicleInCity="347" />
    <CheckPoint Sim_Time="861.2" NumVehicleInCity="346" />
    <CheckPoint Sim_Time="861.5" NumVehicleInCity="345" />
    <CheckPoint Sim_Time="863" NumVehicleInCity="344" />
    <CheckPoint Sim_Time="864.2" NumVehicleInCity="346" />
    <CheckPoint Sim_Time="864.6" NumVehicleInCity="346" />
    <CheckPoint Sim_Time="867.6" NumVehicleInCity="346" />
    <CheckPoint Sim_Time="868" NumVehicleInCity="346" />
    <CheckPoint Sim_Time="868.4" NumVehicleInCity="345" />
    <CheckPoint Sim_Time="868.7" NumVehicleInCity="344" />
    <CheckPoint Sim_Time="870.9" NumVehicleInCity="348" />
    <CheckPoint Sim_Time="871.9" NumVehicleInCity="348" />
    <CheckPoint Sim_Time="872.1" NumVehicleInCity="348" />
    <CheckPoint Sim_Time="873.9" NumVehicleInCity="348" />
    <CheckPoint Sim_Time="876.7" NumVehicleInCity="351" />
    <CheckPoint Sim_Time="876.8" NumVehicleInCity="350" />
    <CheckPoint Sim_Time="878.6" NumVehicleInCity="351" />
    <CheckPoint Sim_Time="878.8" NumVehicleInCity="350" />
    <CheckPoint Sim_Time="879.5" NumVehicleInCity="349" />
    <CheckPoint Sim_Time="880.1" NumVehicleInCity="348" />
    <CheckPoint Sim_Time="881.9" NumVehicleInCity="350" />
    <CheckPoint Sim_Time="893.6" NumVehicleInCity="362" />
    <CheckPoint Sim_Time="893.7" NumVehicleInCity="361" />
    <CheckPoint Sim_Time="894" NumVehicleInCity="360" />
    <CheckPoint Sim_Time="894.3" NumVehicleInCity="359" />
    <CheckPoint Sim_Time="894.5" NumVehicleInCity="358" />
    <CheckPoint Sim_Time="895.7" NumVehicleInCity="357" />
    <CheckPoint Sim_Time="895.9" NumVehicleInCity="357" />
    <CheckPoint Sim_Time="896" NumVehicleInCity="357" />
    <CheckPoint Sim_Time="896.4" NumVehicleInCity="356" />
    <CheckPoint Sim_Time="896.6" NumVehicleInCity="355" />
    <CheckPoint Sim_Time="896.9" NumVehicleInCity="355" />
    <CheckPoint Sim_Time="897.2" NumVehicleInCity="355" />
    <CheckPoint Sim_Time="897.7" NumVehicleInCity="354" />
    <CheckPoint Sim_Time="897.9" NumVehicleInCity="353" />
    <CheckPoint Sim_Time="898.9" NumVehicleInCity="353" />
    <CheckPoint Sim_Time="899.6" NumVehicleInCity="353" />
    <CheckPoint Sim_Time="900" NumVehicleInCity="352" />
    <CheckPoint Sim_Time="901.7" NumVehicleInCity="351" />
    <CheckPoint Sim_Time="902.1" NumVehicleInCity="350" />
    <CheckPoint Sim_Time="902.4" NumVehicleInCity="350" />
    <CheckPoint Sim_Time="903.8" NumVehicleInCity="351" />
    <CheckPoint Sim_Time="904" NumVehicleInCity="350" />
    <CheckPoint Sim_Time="907.6" NumVehicleInCity="350" />
    <CheckPoint Sim_Time="907.8" NumVehicleInCity="349" />
    <CheckPoint Sim_Time="912.3" NumVehicleInCity="350" />
    <CheckPoint Sim_Time="912.5" NumVehicleInCity="349" />
    <CheckPoint Sim_Time="912.7" NumVehicleInCity="348" />
    <CheckPoint Sim_Time="913" NumVehicleInCity="347" />
    <CheckPoint Sim_Time="914.4" NumVehicleInCity="346" />
    <CheckPoint Sim_Time="914.9" NumVehicleInCity="345" />
    <CheckPoint Sim_Time="915.8" NumVehicleInCity="344" />
    <CheckPoint Sim_Time="919.7" NumVehicleInCity="343" />
    <CheckPoint Sim_Time="920.1" NumVehicleInCity="342" />
    <CheckPoint Sim_Time="921.5" NumVehicleInCity="341" />
    <CheckPoint Sim_Time="922.3" NumVehicleInCity="340" />
    <CheckPoint Sim_Time="922.3" NumVehicleInCity="339" />
    <CheckPoint Sim_Time="924.3" NumVehicleInCity="340" />
    <CheckPoint Sim_Time="924.5" NumVehicleInCity="339" />
    <CheckPoint Sim_Time="927.2" NumVehicleInCity="341" />
    <CheckPoint Sim_Time="938.4" NumVehicleInCity="351" />
    <CheckPoint Sim_Time="938.5" NumVehicleInCity="350" />
    <CheckPoint Sim_Time="938.6" NumVehicleInCity="349" />
    <CheckPoint Sim_Time="938.6" NumVehicleInCity="348" />
    <CheckPoint Sim_Time="939.2" NumVehicleInCity="348" />
    <CheckPoint Sim_Time="940.4" NumVehicleInCity="348" />
    <CheckPoint Sim_Time="940.7" NumVehicleInCity="347" />
    <CheckPoint Sim_Time="940.8" NumVehicleInCity="346" />
    <CheckPoint Sim_Time="941" NumVehicleInCity="346" />
    <CheckPoint Sim_Time="941" NumVehicleInCity="345" />
    <CheckPoint Sim_Time="942.4" NumVehicleInCity="345" />
    <CheckPoint Sim_Time="943.1" NumVehicleInCity="345" />
    <CheckPoint Sim_Time="943.1" NumVehicleInCity="344" />
    <CheckPoint Sim_Time="943.3" NumVehicleInCity="343" />
    <CheckPoint Sim_Time="945.3" NumVehicleInCity="344" />
    <CheckPoint Sim_Time="946.6" NumVehicleInCity="344" />
    <CheckPoint Sim_Time="947.4" NumVehicleInCity="344" />
    <CheckPoint Sim_Time="948.4" NumVehicleInCity="344" />
    <CheckPoint Sim_Time="948.8" NumVehicleInCity="343" />
    <CheckPoint Sim_Time="950.4" NumVehicleInCity="344" />
    <CheckPoint Sim_Time="951.7" NumVehicleInCity="344" />
    <CheckPoint Sim_Time="952.4" NumVehicleInCity="344" />
    <CheckPoint Sim_Time="954.8" NumVehicleInCity="345" />
    <CheckPoint Sim_Time="957" NumVehicleInCity="347" />
    <CheckPoint Sim_Time="957.4" NumVehicleInCity="346" />
    <CheckPoint Sim_Time="958.7" NumVehicleInCity="346" />
    <CheckPoint Sim_Time="960.8" NumVehicleInCity="347" />
    <CheckPoint Sim_Time="961.1" NumVehicleInCity="347" />
    <CheckPoint Sim_Time="963.5" NumVehicleInCity="348" />
    <CheckPoint Sim_Time="963.6" NumVehicleInCity="347" />
    <CheckPoint Sim_Time="964.6" NumVehicleInCity="347" />
    <CheckPoint Sim_Time="966.3" NumVehicleInCity="348" />
    <CheckPoint Sim_Time="967.6" NumVehicleInCity="348" />
    <CheckPoint Sim_Time="970.5" NumVehicleInCity="350" />
    <CheckPoint Sim_Time="971.4" NumVehicleInCity="350" />
    <CheckPoint Sim_Time="982" NumVehicleInCity="360" />
    <CheckPoint Sim_Time="983.3" NumVehicleInCity="360" />
    <CheckPoint Sim_Time="983.4" NumVehicleInCity="359" />
    <CheckPoint Sim_Time="984.1" NumVehicleInCity="359" />
    <CheckPoint Sim_Time="985.1" NumVehicleInCity="359" />
    <CheckPoint Sim_Time="985.9" NumVehicleInCity="358" />
    <CheckPoint Sim_Time="987" NumVehicleInCity="359" />
    <CheckPoint Sim_Time="987.6" NumVehicleInCity="358" />
    <CheckPoint Sim_Time="987.6" NumVehicleInCity="357" />
    <CheckPoint Sim_Time="989.6" NumVehicleInCity="358" />
    <CheckPoint Sim_Time="989.7" NumVehicleInCity="357" />
    <CheckPoint Sim_Time="990.3" NumVehicleInCity="357" />
    <CheckPoint Sim_Time="990.5" NumVehicleInCity="356" />
    <CheckPoint Sim_Time="990.8" NumVehicleInCity="355" />
    <CheckPoint Sim_Time="991.7" NumVehicleInCity="355" />
    <CheckPoint Sim_Time="993.2" NumVehicleInCity="356" />
    <CheckPoint Sim_Time="993.8" NumVehicleInCity="355" />
    <CheckPoint Sim_Time="994.3" NumVehicleInCity="355" />
    <CheckPoint Sim_Time="994.8" NumVehicleInCity="354" />
    <CheckPoint Sim_Time="996.3" NumVehicleInCity="355" />
    <CheckPoint Sim_Time="999.1" NumVehicleInCity="357" />
    <CheckPoint Sim_Time="1000.5" NumVehicleInCity="357" />
    <CheckPoint Sim_Time="1002.8" NumVehicleInCity="358" />
    <CheckPoint Sim_Time="1002.8" NumVehicleInCity="357" />
    <CheckPoint Sim_Time="1003.5" NumVehicleInCity="357" />
    <CheckPoint Sim_Time="1005.6" NumVehicleInCity="358" />
    <CheckPoint Sim_Time="1006.4" NumVehicleInCity="358" />
    <CheckPoint Sim_Time="1007.1" NumVehicleInCity="358" />
    <CheckPoint Sim_Time="1010.2" NumVehicleInCity="360" />
    <CheckPoint Sim_Time="1010.5" NumVehicleInCity="359" />
    <CheckPoint Sim_Time="1010.6" NumVehicleInCity="358" />
    <CheckPoint Sim_Time="1012.7" NumVehicleInCity="359" />
    <CheckPoint Sim_Time="1014.8" NumVehicleInCity="360" />
    <CheckPoint Sim_Time="1014.9" NumVehicleInCity="359" />
    <CheckPoint Sim_Time="1016" NumVehicleInCity="360" />
    <CheckPoint Sim_Time="1016.1" NumVehicleInCity="359" />
    <CheckPoint Sim_Time="1017.3" NumVehicleInCity="359" />
    <CheckPoint Sim_Time="1024.4" NumVehicleInCity="365" />
    <CheckPoint Sim_Time="1027.4" NumVehicleInCity="367" />
    <CheckPoint Sim_Time="1028.4" NumVehicleInCity="367" />
    <CheckPoint Sim_Time="1029.2" NumVehicleInCity="367" />
    <CheckPoint Sim_Time="1029.5" NumVehicleInCity="366" />
    <CheckPoint Sim_Time="1029.6" NumVehicleInCity="365" />
    <CheckPoint Sim_Time="1029.7" NumVehicleInCity="364" />
    <CheckPoint Sim_Time="1030.5" NumVehicleInCity="364" />
    <CheckPoint Sim_Time="1031.6" NumVehicleInCity="364" />
    <CheckPoint Sim_Time="1031.7" NumVehicleInCity="363" />
    <CheckPoint Sim_Time="1031.9" NumVehicleInCity="362" />
    <CheckPoint Sim_Time="1033.1" NumVehicleInCity="362" />
    <CheckPoint Sim_Time="1033.9" NumVehicleInCity="361" />
    <CheckPoint Sim_Time="1034.6" NumVehicleInCity="361" />
    <CheckPoint Sim_Time="1035.2" NumVehicleInCity="361" />
    <CheckPoint Sim_Time="1035.9" NumVehicleInCity="360" />
    <CheckPoint Sim_Time="1036.5" NumVehicleInCity="360" />
    <CheckPoint Sim_Time="1038.4" NumVehicleInCity="361" />
    <CheckPoint Sim_Time="1039" NumVehicleInCity="361" />
    <CheckPoint Sim_Time="1040.2" NumVehicleInCity="361" />
    <CheckPoint Sim_Time="1040.6" NumVehicleInCity="360" />
    <CheckPoint Sim_Time="1041.1" NumVehicleInCity="360" />
    <CheckPoint Sim_Time="1041.2" NumVehicleInCity="359" />
    <CheckPoint Sim_Time="1043.6" NumVehicleInCity="360" />
    <CheckPoint Sim_Time="1044.1" NumVehicleInCity="360" />
    <CheckPoint Sim_Time="1046" NumVehicleInCity="361" />
    <CheckPoint Sim_Time="1048.5" NumVehicleInCity="362" />
    <CheckPoint Sim_Time="1049.9" NumVehicleInCity="362" />
    <CheckPoint Sim_Time="1052.1" NumVehicleInCity="364" />
    <CheckPoint Sim_Time="1053.3" NumVehicleInCity="364" />
    <CheckPoint Sim_Time="1054.9" NumVehicleInCity="364" />
    <CheckPoint Sim_Time="1056.1" NumVehicleInCity="365" />
    <CheckPoint Sim_Time="1059" NumVehicleInCity="367" />
    <CheckPoint Sim_Time="1060.2" NumVehicleInCity="367" />
    <CheckPoint Sim_Time="1073.2" NumVehicleInCity="379" />
    <CheckPoint Sim_Time="1073.2" NumVehicleInCity="378" />
    <CheckPoint Sim_Time="1073.4" NumVehicleInCity="377" />
    <CheckPoint Sim_Time="1074.1" NumVehicleInCity="377" />
    <CheckPoint Sim_Time="1074.2" NumVehicleInCity="376" />
    <CheckPoint Sim_Time="1074.3" NumVehicleInCity="375" />
    <CheckPoint Sim_Time="1074.4" NumVehicleInCity="374" />
    <CheckPoint Sim_Time="1074.9" NumVehicleInCity="373" />
    <CheckPoint Sim_Time="1075.2" NumVehicleInCity="372" />
    <CheckPoint Sim_Time="1075.5" NumVehicleInCity="371" />
    <CheckPoint Sim_Time="1075.9" NumVehicleInCity="370" />
    <CheckPoint Sim_Time="1076.8" NumVehicleInCity="370" />
    <CheckPoint Sim_Time="1077.1" NumVehicleInCity="370" />
    <CheckPoint Sim_Time="1077.7" NumVehicleInCity="369" />
    <CheckPoint Sim_Time="1078.5" NumVehicleInCity="369" />
    <CheckPoint Sim_Time="1078.5" NumVehicleInCity="368" />
    <CheckPoint Sim_Time="1078.6" NumVehicleInCity="367" />
    <CheckPoint Sim_Time="1079.6" NumVehicleInCity="367" />
    <CheckPoint Sim_Time="1079.8" NumVehicleInCity="366" />
    <CheckPoint Sim_Time="1080.2" NumVehicleInCity="366" />
    <CheckPoint Sim_Time="1080.8" NumVehicleInCity="365" />
    <CheckPoint Sim_Time="1082" NumVehicleInCity="366" />
    <CheckPoint Sim_Time="1082.4" NumVehicleInCity="365" />
    <CheckPoint Sim_Time="1083.6" NumVehicleInCity="365" />
    <CheckPoint Sim_Time="1084.6" NumVehicleInCity="365" />
    <CheckPoint Sim_Time="1084.9" NumVehicleInCity="364" />
    <CheckPoint Sim_Time="1086.3" NumVehicleInCity="365" />
    <CheckPoint Sim_Time="1086.3" NumVehicleInCity="364" />
    <CheckPoint Sim_Time="1086.5" NumVehicleInCity="363" />
    <CheckPoint Sim_Time="1087.2" NumVehicleInCity="363" />
    <CheckPoint Sim_Time="1087.9" NumVehicleInCity="362" />
    <CheckPoint Sim_Time="1088.6" NumVehicleInCity="362" />
    <CheckPoint Sim_Time="1089.3" NumVehicleInCity="362" />
    <CheckPoint Sim_Time="1092.3" NumVehicleInCity="364" />
    <CheckPoint Sim_Time="1092.5" NumVehicleInCity="363" />
    <CheckPoint Sim_Time="1093.2" NumVehicleInCity="363" />
    <CheckPoint Sim_Time="1095.1" NumVehicleInCity="364" />
    <CheckPoint Sim_Time="1095.9" NumVehicleInCity="363" />
    <CheckPoint Sim_Time="1096.9" NumVehicleInCity="363" />
    <CheckPoint Sim_Time="1098.7" NumVehicleInCity="364" />
    <CheckPoint Sim_Time="1099.5" NumVehicleInCity="364" />
    <CheckPoint Sim_Time="1099.6" NumVehicleInCity="363" />
    <CheckPoint Sim_Time="1100.6" NumVehicleInCity="363" />
    <CheckPoint Sim_Time="1101.5" NumVehicleInCity="363" />
    <CheckPoint Sim_Time="1101.6" NumVehicleInCity="362" />
    <CheckPoint Sim_Time="1102.5" NumVehicleInCity="362" />
    <CheckPoint Sim_Time="1102.8" NumVehicleInCity="361" />
    <CheckPoint Sim_Time="1106.1" NumVehicleInCity="364" />
    <CheckPoint Sim_Time="1106.1" NumVehicleInCity="363" />
    <CheckPoint Sim_Time="1107.9" NumVehicleInCity="363" />
    <CheckPoint Sim_Time="1117.3" NumVehicleInCity="372" />
    <CheckPoint Sim_Time="1118.1" NumVehicleInCity="372" />
    <CheckPoint Sim_Time="1118.4" NumVehicleInCity="371" />
    <CheckPoint Sim_Time="1118.5" NumVehicleInCity="370" />
    <CheckPoint Sim_Time="1118.5" NumVehicleInCity="369" />
    <CheckPoint Sim_Time="1118.5" NumVehicleInCity="368" />
    <CheckPoint Sim_Time="1118.6" NumVehicleInCity="367" />
    <CheckPoint Sim_Time="1119.5" NumVehicleInCity="367" />
    <CheckPoint Sim_Time="1120.4" NumVehicleInCity="367" />
    <CheckPoint Sim_Time="1120.7" NumVehicleInCity="366" />
    <CheckPoint Sim_Time="1121.1" NumVehicleInCity="366" />
    <CheckPoint Sim_Time="1122.7" NumVehicleInCity="366" />
    <CheckPoint Sim_Time="1123.2" NumVehicleInCity="366" />
    <CheckPoint Sim_Time="1123.5" NumVehicleInCity="365" />
    <CheckPoint Sim_Time="1124.6" NumVehicleInCity="365" />
    <CheckPoint Sim_Time="1125.2" NumVehicleInCity="365" />
    <CheckPoint Sim_Time="1125.6" NumVehicleInCity="364" />
    <CheckPoint Sim_Time="1125.9" NumVehicleInCity="363" />
    <CheckPoint Sim_Time="1126" NumVehicleInCity="362" />
    <CheckPoint Sim_Time="1126.1" NumVehicleInCity="361" />
    <CheckPoint Sim_Time="1127.4" NumVehicleInCity="361" />
    <CheckPoint Sim_Time="1127.6" NumVehicleInCity="360" />
    <CheckPoint Sim_Time="1130.3" NumVehicleInCity="362" />
    <CheckPoint Sim_Time="1130.4" NumVehicleInCity="361" />
    <CheckPoint Sim_Time="1132" NumVehicleInCity="362" />
    <CheckPoint Sim_Time="1133.1" NumVehicleInCity="362" />
    <CheckPoint Sim_Time="1133.1" NumVehicleInCity="361" />
    <CheckPoint Sim_Time="1134.8" NumVehicleInCity="361" />
    <CheckPoint Sim_Time="1135.3" NumVehicleInCity="361" />
    <CheckPoint Sim_Time="1136.3" NumVehicleInCity="361" />
    <CheckPoint Sim_Time="1137.4" NumVehicleInCity="361" />
    <CheckPoint Sim_Time="1139.7" NumVehicleInCity="362" />
    <CheckPoint Sim_Time="1140.5" NumVehicleInCity="362" />
    <CheckPoint Sim_Time="1141" NumVehicleInCity="362" />
    <CheckPoint Sim_Time="1145" NumVehicleInCity="365" />
    <CheckPoint Sim_Time="1147.8" NumVehicleInCity="366" />
    <CheckPoint Sim_Time="1148" NumVehicleInCity="366" />
    <CheckPoint Sim_Time="1148.4" NumVehicleInCity="365" />
    <CheckPoint Sim_Time="1150.2" NumVehicleInCity="366" />
    <CheckPoint Sim_Time="1150.4" NumVehicleInCity="365" />
    <CheckPoint Sim_Time="1150.4" NumVehicleInCity="364" />
    <CheckPoint Sim_Time="1152.5" NumVehicleInCity="365" />
    <CheckPoint Sim_Time="1152.6" NumVehicleInCity="364" />
    <CheckPoint Sim_Time="1162.2" NumVehicleInCity="373" />
    <CheckPoint Sim_Time="1162.3" NumVehicleInCity="372" />
    <CheckPoint Sim_Time="1163.5" NumVehicleInCity="372" />
    <CheckPoint Sim_Time="1164.1" NumVehicleInCity="372" />
    <CheckPoint Sim_Time="1164.4" NumVehicleInCity="371" />
    <CheckPoint Sim_Time="1165" NumVehicleInCity="371" />
    <CheckPoint Sim_Time="1165.2" NumVehicleInCity="370" />
    <CheckPoint Sim_Time="1165.5" NumVehicleInCity="369" />
    <CheckPoint Sim_Time="1165.8" NumVehicleInCity="368" />
    <CheckPoint Sim_Time="1166" NumVehicleInCity="368" />
    <CheckPoint Sim_Time="1167.3" NumVehicleInCity="368" />
    <CheckPoint Sim_Time="1167.9" NumVehicleInCity="367" />
    <CheckPoint Sim_Time="1169.2" NumVehicleInCity="368" />
    <CheckPoint Sim_Time="1169.9" NumVehicleInCity="367" />
    <CheckPoint Sim_Time="1170" NumVehicleInCity="367" />
    <CheckPoint Sim_Time="1171" NumVehicleInCity="367" />
    <CheckPoint Sim_Time="1171.3" NumVehicleInCity="366" />
    <CheckPoint Sim_Time="1172.1" NumVehicleInCity="366" />
    <CheckPoint Sim_Time="1172.2" NumVehicleInCity="365" />
    <CheckPoint Sim_Time="1173.1" NumVehicleInCity="365" />
    <CheckPoint Sim_Time="1173.8" NumVehicleInCity="364" />
    <CheckPoint Sim_Time="1175.1" NumVehicleInCity="365" />
    <CheckPoint Sim_Time="1175.5" NumVehicleInCity="364" />
    <CheckPoint Sim_Time="1177.8" NumVehicleInCity="365" />
    <CheckPoint Sim_Time="1182.3" NumVehicleInCity="369" />
    <CheckPoint Sim_Time="1182.6" NumVehicleInCity="368" />
    <CheckPoint Sim_Time="1184.1" NumVehicleInCity="369" />
    <CheckPoint Sim_Time="1184.6" NumVehicleInCity="368" />
    <CheckPoint Sim_Time="1186.5" NumVehicleInCity="369" />
    <CheckPoint Sim_Time="1186.5" NumVehicleInCity="368" />
    <CheckPoint Sim_Time="1187.7" NumVehicleInCity="368" />
    <CheckPoint Sim_Time="1188.7" NumVehicleInCity="368" />
    <CheckPoint Sim_Time="1190.8" NumVehicleInCity="369" />
    <CheckPoint Sim_Time="1191" NumVehicleInCity="369" />
    <CheckPoint Sim_Time="1191.1" NumVehicleInCity="368" />
    <CheckPoint Sim_Time="1194.5" NumVehicleInCity="370" />
    <CheckPoint Sim_Time="1195.3" NumVehicleInCity="370" />
    <CheckPoint Sim_Time="1196.5" NumVehicleInCity="370" />
    <CheckPoint Sim_Time="1200.9" NumVehicleInCity="373" />
    <CheckPoint Sim_Time="1202.6" NumVehicleInCity="374" />
    <CheckPoint Sim_Time="1207.1" NumVehicleInCity="378" />
    <CheckPoint Sim_Time="1208.5" NumVehicleInCity="378" />
    <CheckPoint Sim_Time="1209.2" NumVehicleInCity="378" />
    <CheckPoint Sim_Time="1209.4" NumVehicleInCity="377" />
    <CheckPoint Sim_Time="1210.1" NumVehicleInCity="377" />
    <CheckPoint Sim_Time="1211" NumVehicleInCity="377" />
    <CheckPoint Sim_Time="1211.7" NumVehicleInCity="376" />
    <CheckPoint Sim_Time="1211.9" NumVehicleInCity="375" />
    <CheckPoint Sim_Time="1213" NumVehicleInCity="376" />
    <CheckPoint Sim_Time="1213.8" NumVehicleInCity="375" />
    <CheckPoint Sim_Time="1214.8" NumVehicleInCity="375" />
    <CheckPoint Sim_Time="1215" NumVehicleInCity="375" />
    <CheckPoint Sim_Time="1215.6" NumVehicleInCity="374" />
    <CheckPoint Sim_Time="1216.6" NumVehicleInCity="374" />
    <CheckPoint Sim_Time="1217.6" NumVehicleInCity="374" />
    <CheckPoint Sim_Time="1217.6" NumVehicleInCity="373" />
    <CheckPoint Sim_Time="1217.8" NumVehicleInCity="372" />
    <CheckPoint Sim_Time="1218.6" NumVehicleInCity="372" />
    <CheckPoint Sim_Time="1219.7" NumVehicleInCity="372" />
    <CheckPoint Sim_Time="1220.4" NumVehicleInCity="372" />
    <CheckPoint Sim_Time="1220.5" NumVehicleInCity="371" />
    <CheckPoint Sim_Time="1221" NumVehicleInCity="371" />
    <CheckPoint Sim_Time="1225.7" NumVehicleInCity="374" />
    <CheckPoint Sim_Time="1227.2" NumVehicleInCity="375" />
    <CheckPoint Sim_Time="1228.1" NumVehicleInCity="375" />
    <CheckPoint Sim_Time="1228.6" NumVehicleInCity="374" />
    <CheckPoint Sim_Time="1229.7" NumVehicleInCity="374" />
    <CheckPoint Sim_Time="1231.7" NumVehicleInCity="375" />
    <CheckPoint Sim_Time="1237.3" NumVehicleInCity="380" />
    <CheckPoint Sim_Time="1237.8" NumVehicleInCity="379" />
    <CheckPoint Sim_Time="1239.3" NumVehicleInCity="380" />
    <CheckPoint Sim_Time="1239.4" NumVehicleInCity="379" />
    <CheckPoint Sim_Time="1240" NumVehicleInCity="379" />
    <CheckPoint Sim_Time="1240.6" NumVehicleInCity="378" />
    <CheckPoint Sim_Time="1252.7" NumVehicleInCity="389" />
    <CheckPoint Sim_Time="1253.3" NumVehicleInCity="389" />
    <CheckPoint Sim_Time="1253.6" NumVehicleInCity="388" />
    <CheckPoint Sim_Time="1254.2" NumVehicleInCity="388" />
    <CheckPoint Sim_Time="1254.4" NumVehicleInCity="387" />
    <CheckPoint Sim_Time="1255.1" NumVehicleInCity="387" />
    <CheckPoint Sim_Time="1255.4" NumVehicleInCity="386" />
    <CheckPoint Sim_Time="1255.5" NumVehicleInCity="385" />
    <CheckPoint Sim_Time="1256" NumVehicleInCity="385" />
    <CheckPoint Sim_Time="1257.4" NumVehicleInCity="385" />
    <CheckPoint Sim_Time="1257.9" NumVehicleInCity="384" />
    <CheckPoint Sim_Time="1258.4" NumVehicleInCity="384" />
    <CheckPoint Sim_Time="1259" NumVehicleInCity="384" />
    <CheckPoint Sim_Time="1260.2" NumVehicleInCity="384" />
    <CheckPoint Sim_Time="1260.6" NumVehicleInCity="383" />
    <CheckPoint Sim_Time="1260.7" NumVehicleInCity="382" />
    <CheckPoint Sim_Time="1260.7" NumVehicleInCity="381" />
    <CheckPoint Sim_Time="1261.1" NumVehicleInCity="381" />
    <CheckPoint Sim_Time="1261.6" NumVehicleInCity="380" />
    <CheckPoint Sim_Time="1262.3" NumVehicleInCity="380" />
    <CheckPoint Sim_Time="1262.8" NumVehicleInCity="379" />
    <CheckPoint Sim_Time="1263.1" NumVehicleInCity="379" />
    <CheckPoint Sim_Time="1263.7" NumVehicleInCity="378" />
    <CheckPoint Sim_Time="1264.3" NumVehicleInCity="378" />
    <CheckPoint Sim_Time="1264.5" NumVehicleInCity="377" />
    <CheckPoint Sim_Time="1266" NumVehicleInCity="378" />
    <CheckPoint Sim_Time="1267.5" NumVehicleInCity="378" />
    <CheckPoint Sim_Time="1268" NumVehicleInCity="378" />
    <CheckPoint Sim_Time="1268.3" NumVehicleInCity="377" />
    <CheckPoint Sim_Time="1269.3" NumVehicleInCity="377" />
    <CheckPoint Sim_Time="1270.1" NumVehicleInCity="377" />
    <CheckPoint Sim_Time="1271.9" NumVehicleInCity="377" />
    <CheckPoint Sim_Time="1272.8" NumVehicleInCity="377" />
    <CheckPoint Sim_Time="1272.9" NumVehicleInCity="376" />
    <CheckPoint Sim_Time="1275.4" NumVehicleInCity="378" />
    <CheckPoint Sim_Time="1275.9" NumVehicleInCity="377" />
    <CheckPoint Sim_Time="1277.7" NumVehicleInCity="378" />
    <CheckPoint Sim_Time="1278.7" NumVehicleInCity="378" />
    <CheckPoint Sim_Time="1279.9" NumVehicleInCity="378" />
    <CheckPoint Sim_Time="1280.1" NumVehicleInCity="378" />
    <CheckPoint Sim_Time="1280.5" NumVehicleInCity="377" />
    <CheckPoint Sim_Time="1280.8" NumVehicleInCity="376" />
    <CheckPoint Sim_Time="1281.1" NumVehicleInCity="376" />
    <CheckPoint Sim_Time="1282.5" NumVehicleInCity="376" />
    <CheckPoint Sim_Time="1283" NumVehicleInCity="376" />
    <CheckPoint Sim_Time="1283.2" NumVehicleInCity="375" />
    <CheckPoint Sim_Time="1283.7" NumVehicleInCity="374" />
    <CheckPoint Sim_Time="1285" NumVehicleInCity="375" />
    <CheckPoint Sim_Time="1285.2" NumVehicleInCity="374" />
    <CheckPoint Sim_Time="1285.9" NumVehicleInCity="373" />
    <CheckPoint Sim_Time="1287.7" NumVehicleInCity="374" />
    <CheckPoint Sim_Time="1297.4" NumVehicleInCity="383" />
    <CheckPoint Sim_Time="1297.5" NumVehicleInCity="382" />
    <CheckPoint Sim_Time="1298.1" NumVehicleInCity="382" />
    <CheckPoint Sim_Time="1298.3" NumVehicleInCity="381" />
    <CheckPoint Sim_Time="1298.4" NumVehicleInCity="380" />
    <CheckPoint Sim_Time="1298.5" NumVehicleInCity="379" />
    <CheckPoint Sim_Time="1299.1" NumVehicleInCity="379" />
    <CheckPoint Sim_Time="1300.1" NumVehicleInCity="379" />
    <CheckPoint Sim_Time="1300.2" NumVehicleInCity="378" />
    <CheckPoint Sim_Time="1300.6" NumVehicleInCity="377" />
    <CheckPoint Sim_Time="1300.6" NumVehicleInCity="376" />
    <CheckPoint Sim_Time="1301.7" NumVehicleInCity="376" />
    <CheckPoint Sim_Time="1301.9" NumVehicleInCity="375" />
    <CheckPoint Sim_Time="1302" NumVehicleInCity="375" />
    <CheckPoint Sim_Time="1302.3" NumVehicleInCity="374" />
    <CheckPoint Sim_Time="1302.6" NumVehicleInCity="373" />
    <CheckPoint Sim_Time="1302.8" NumVehicleInCity="372" />
    <CheckPoint Sim_Time="1304.5" NumVehicleInCity="373" />
    <CheckPoint Sim_Time="1304.7" NumVehicleInCity="372" />
    <CheckPoint Sim_Time="1306" NumVehicleInCity="373" />
    <CheckPoint Sim_Time="1307.8" NumVehicleInCity="373" />
    <CheckPoint Sim_Time="1309.3" NumVehicleInCity="374" />
    <CheckPoint Sim_Time="1312.4" NumVehicleInCity="376" />
    <CheckPoint Sim_Time="1314.4" NumVehicleInCity="377" />
    <CheckPoint Sim_Time="1316.5" NumVehicleInCity="378" />
    <CheckPoint Sim_Time="1318" NumVehicleInCity="379" />
    <CheckPoint Sim_Time="1318.1" NumVehicleInCity="378" />
    <CheckPoint Sim_Time="1319" NumVehicleInCity="378" />
    <CheckPoint Sim_Time="1320" NumVehicleInCity="378" />
    <CheckPoint Sim_Time="1321.4" NumVehicleInCity="378" />
    <CheckPoint Sim_Time="1324.5" NumVehicleInCity="380" />
    <CheckPoint Sim_Time="1324.8" NumVehicleInCity="379" />
    <CheckPoint Sim_Time="1327.5" NumVehicleInCity="381" />
    <CheckPoint Sim_Time="1329" NumVehicleInCity="382" />
    <CheckPoint Sim_Time="1330" NumVehicleInCity="382" />
    <CheckPoint Sim_Time="1332.6" NumVehicleInCity="383" />
    <CheckPoint Sim_Time="1343.3" NumVehicleInCity="392" />
    <CheckPoint Sim_Time="1344.2" NumVehicleInCity="392" />
    <CheckPoint Sim_Time="1344.4" NumVehicleInCity="391" />
    <CheckPoint Sim_Time="1345.4" NumVehicleInCity="391" />
    <CheckPoint Sim_Time="1345.7" NumVehicleInCity="390" />
    <CheckPoint Sim_Time="1346.1" NumVehicleInCity="390" />
    <CheckPoint Sim_Time="1346.2" NumVehicleInCity="389" />
    <CheckPoint Sim_Time="1346.8" NumVehicleInCity="388" />
    <CheckPoint Sim_Time="1347.9" NumVehicleInCity="388" />
    <CheckPoint Sim_Time="1348.2" NumVehicleInCity="388" />
    <CheckPoint Sim_Time="1349" NumVehicleInCity="388" />
    <CheckPoint Sim_Time="1349.4" NumVehicleInCity="387" />
    <CheckPoint Sim_Time="1349.9" NumVehicleInCity="386" />
    <CheckPoint Sim_Time="1351.4" NumVehicleInCity="387" />
    <CheckPoint Sim_Time="1351.6" NumVehicleInCity="386" />
    <CheckPoint Sim_Time="1351.9" NumVehicleInCity="385" />
    <CheckPoint Sim_Time="1352.9" NumVehicleInCity="385" />
    <CheckPoint Sim_Time="1353.9" NumVehicleInCity="385" />
    <CheckPoint Sim_Time="1354.4" NumVehicleInCity="385" />
    <CheckPoint Sim_Time="1354.9" NumVehicleInCity="384" />
    <CheckPoint Sim_Time="1355.5" NumVehicleInCity="384" />
    <CheckPoint Sim_Time="1356" NumVehicleInCity="384" />
    <CheckPoint Sim_Time="1356.2" NumVehicleInCity="383" />
    <CheckPoint Sim_Time="1358.2" NumVehicleInCity="384" />
    <CheckPoint Sim_Time="1358.4" NumVehicleInCity="383" />
    <CheckPoint Sim_Time="1358.5" NumVehicleInCity="382" />
    <CheckPoint Sim_Time="1359" NumVehicleInCity="382" />
    <CheckPoint Sim_Time="1360.5" NumVehicleInCity="382" />
    <CheckPoint Sim_Time="1363.3" NumVehicleInCity="384" />
    <CheckPoint Sim_Time="1364.9" NumVehicleInCity="384" />
    <CheckPoint Sim_Time="1365.9" NumVehicleInCity="384" />
    <CheckPoint Sim_Time="1367.9" NumVehicleInCity="385" />
    <CheckPoint Sim_Time="1368.5" NumVehicleInCity="385" />
    <CheckPoint Sim_Time="1368.8" NumVehicleInCity="384" />
    <CheckPoint Sim_Time="1370.3" NumVehicleInCity="385" />
    <CheckPoint Sim_Time="1371.3" NumVehicleInCity="385" />
    <CheckPoint Sim_Time="1373.2" NumVehicleInCity="386" />
    <CheckPoint Sim_Time="1373.3" NumVehicleInCity="385" />
    <CheckPoint Sim_Time="1387.4" NumVehicleInCity="398" />
    <CheckPoint Sim_Time="1387.4" NumVehicleInCity="397" />
    <CheckPoint Sim_Time="1388.5" NumVehicleInCity="397" />
    <CheckPoint Sim_Time="1388.6" NumVehicleInCity="396" />
    <CheckPoint Sim_Time="1388.7" NumVehicleInCity="395" />
    <CheckPoint Sim_Time="1389.9" NumVehicleInCity="395" />
    <CheckPoint Sim_Time="1390.4" NumVehicleInCity="395" />
    <CheckPoint Sim_Time="1390.9" NumVehicleInCity="394" />
    <CheckPoint Sim_Time="1390.9" NumVehicleInCity="393" />
    <CheckPoint Sim_Time="1391" NumVehicleInCity="393" />
    <CheckPoint Sim_Time="1391" NumVehicleInCity="392" />
    <CheckPoint Sim_Time="1392.3" NumVehicleInCity="392" />
    <CheckPoint Sim_Time="1394" NumVehicleInCity="393" />
    <CheckPoint Sim_Time="1394.3" NumVehicleInCity="392" />
    <CheckPoint Sim_Time="1398.2" NumVehicleInCity="395" />
    <CheckPoint Sim_Time="1399.8" NumVehicleInCity="395" />
    <CheckPoint Sim_Time="1402" NumVehicleInCity="397" />
    <CheckPoint Sim_Time="1402.1" NumVehicleInCity="396" />
    <CheckPoint Sim_Time="1404.1" NumVehicleInCity="397" />
    <CheckPoint Sim_Time="1404.4" NumVehicleInCity="396" />
    <CheckPoint Sim_Time="1405.2" NumVehicleInCity="396" />
    <CheckPoint Sim_Time="1407.3" NumVehicleInCity="397" />
    <CheckPoint Sim_Time="1407.8" NumVehicleInCity="396" />
    <CheckPoint Sim_Time="1413.9" NumVehicleInCity="401" />
    <CheckPoint Sim_Time="1414.3" NumVehicleInCity="401" />
    <CheckPoint Sim_Time="1415.6" NumVehicleInCity="401" />
    <CheckPoint Sim_Time="1417.2" NumVehicleInCity="402" />
    <CheckPoint Sim_Time="1419" NumVehicleInCity="403" />
    <CheckPoint Sim_Time="1419.2" NumVehicleInCity="402" />
    <CheckPoint Sim_Time="1419.5" NumVehicleInCity="401" />
    <CheckPoint Sim_Time="1432.4" NumVehicleInCity="413" />
    <CheckPoint Sim_Time="1432.5" NumVehicleInCity="412" />
    <CheckPoint Sim_Time="1432.8" NumVehicleInCity="411" />
    <CheckPoint Sim_Time="1433.3" NumVehicleInCity="411" />
    <CheckPoint Sim_Time="1433.5" NumVehicleInCity="410" />
    <CheckPoint Sim_Time="1433.6" NumVehicleInCity="409" />
    <CheckPoint Sim_Time="1434.4" NumVehicleInCity="409" />
    <CheckPoint Sim_Time="1435.3" NumVehicleInCity="409" />
    <CheckPoint Sim_Time="1435.4" NumVehicleInCity="408" />
    <CheckPoint Sim_Time="1436.7" NumVehicleInCity="408" />
    <CheckPoint Sim_Time="1436.8" NumVehicleInCity="407" />
    <CheckPoint Sim_Time="1437.6" NumVehicleInCity="407" />
    <CheckPoint Sim_Time="1438" NumVehicleInCity="407" />
    <CheckPoint Sim_Time="1438.2" NumVehicleInCity="406" />
    <CheckPoint Sim_Time="1438.2" NumVehicleInCity="405" />
    <CheckPoint Sim_Time="1438.3" NumVehicleInCity="404" />
    <CheckPoint Sim_Time="1439.3" NumVehicleInCity="404" />
    <CheckPoint Sim_Time="1440.1" NumVehicleInCity="404" />
    <CheckPoint Sim_Time="1440.6" NumVehicleInCity="403" />
    <CheckPoint Sim_Time="1440.6" NumVehicleInCity="402" />
    <CheckPoint Sim_Time="1441.7" NumVehicleInCity="402" />
    <CheckPoint Sim_Time="1442.4" NumVehicleInCity="402" />
    <CheckPoint Sim_Time="1443.4" NumVehicleInCity="402" />
    <CheckPoint Sim_Time="1443.4" NumVehicleInCity="401" />
    <CheckPoint Sim_Time="1443.9" NumVehicleInCity="400" />
    <CheckPoint Sim_Time="1444.5" NumVehicleInCity="400" />
    <CheckPoint Sim_Time="1445.1" NumVehicleInCity="400" />
    <CheckPoint Sim_Time="1446.2" NumVehicleInCity="400" />
    <CheckPoint Sim_Time="1447.1" NumVehicleInCity="400" />
    <CheckPoint Sim_Time="1447.8" NumVehicleInCity="399" />
    <CheckPoint Sim_Time="1449.7" NumVehicleInCity="400" />
    <CheckPoint Sim_Time="1451.6" NumVehicleInCity="401" />
    <CheckPoint Sim_Time="1453.3" NumVehicleInCity="402" />
    <CheckPoint Sim_Time="1453.6" NumVehicleInCity="401" />
    <CheckPoint Sim_Time="1455" NumVehicleInCity="402" />
    <CheckPoint Sim_Time="1455.1" NumVehicleInCity="401" />
    <CheckPoint Sim_Time="1457.1" NumVehicleInCity="402" />
    <CheckPoint Sim_Time="1458.1" NumVehicleInCity="402" />
    <CheckPoint Sim_Time="1459.6" NumVehicleInCity="402" />
    <CheckPoint Sim_Time="1461.5" NumVehicleInCity="403" />
    <CheckPoint Sim_Time="1463.1" NumVehicleInCity="404" />
    <CheckPoint Sim_Time="1463.2" NumVehicleInCity="403" />
    <CheckPoint Sim_Time="1463.6" NumVehicleInCity="402" />
    <CheckPoint Sim_Time="1463.6" NumVehicleInCity="401" />
    <CheckPoint Sim_Time="1465.1" NumVehicleInCity="402" />
    <CheckPoint Sim_Time="1465.7" NumVehicleInCity="401" />
    <CheckPoint Sim_Time="1466.5" NumVehicleInCity="401" />
    <CheckPoint Sim_Time="1467.2" NumVehicleInCity="401" />
    <CheckPoint Sim_Time="1476.1" NumVehicleInCity="409" />
    <CheckPoint Sim_Time="1477.9" NumVehicleInCity="409" />
    <CheckPoint Sim_Time="1478.5" NumVehicleInCity="409" />
    <CheckPoint Sim_Time="1478.6" NumVehicleInCity="408" />
    <CheckPoint Sim_Time="1479.3" NumVehicleInCity="408" />
    <CheckPoint Sim_Time="1479.4" NumVehicleInCity="407" />
    <CheckPoint Sim_Time="1480.5" NumVehicleInCity="407" />
    <CheckPoint Sim_Time="1480.5" NumVehicleInCity="406" />
    <CheckPoint Sim_Time="1480.9" NumVehicleInCity="405" />
    <CheckPoint Sim_Time="1481.2" NumVehicleInCity="405" />
    <CheckPoint Sim_Time="1482.8" NumVehicleInCity="405" />
    <CheckPoint Sim_Time="1483" NumVehicleInCity="405" />
    <CheckPoint Sim_Time="1483.5" NumVehicleInCity="404" />
    <CheckPoint Sim_Time="1484.4" NumVehicleInCity="403" />
    <CheckPoint Sim_Time="1484.8" NumVehicleInCity="402" />
    <CheckPoint Sim_Time="1485.1" NumVehicleInCity="402" />
    <CheckPoint Sim_Time="1488.5" NumVehicleInCity="404" />
    <CheckPoint Sim_Time="1489.6" NumVehicleInCity="404" />
    <CheckPoint Sim_Time="1490.4" NumVehicleInCity="404" />
    <CheckPoint Sim_Time="1491.7" NumVehicleInCity="404" />
    <CheckPoint Sim_Time="1492.3" NumVehicleInCity="404" />
    <CheckPoint Sim_Time="1492.8" NumVehicleInCity="403" />
    <CheckPoint Sim_Time="1493.8" NumVehicleInCity="403" />
    <CheckPoint Sim_Time="1497.3" NumVehicleInCity="406" />
    <CheckPoint Sim_Time="1498.8" NumVehicleInCity="406" />
    <CheckPoint Sim_Time="1499.3" NumVehicleInCity="406" />
    <CheckPoint Sim_Time="1500.7" NumVehicleInCity="406" />
    <CheckPoint Sim_Time="1501.1" NumVehicleInCity="406" />
    <CheckPoint Sim_Time="1506.3" NumVehicleInCity="410" />
    <CheckPoint Sim_Time="1508.9" NumVehicleInCity="411" />
    <CheckPoint Sim_Time="1509.8" NumVehicleInCity="411" />
    <CheckPoint Sim_Time="1510.1" NumVehicleInCity="411" />
    <CheckPoint Sim_Time="1510.1" NumVehicleInCity="410" />
    <CheckPoint Sim_Time="1510.8" NumVehicleInCity="409" />
    <CheckPoint Sim_Time="1511.5" NumVehicleInCity="409" />
    <CheckPoint Sim_Time="1512.5" NumVehicleInCity="409" />
    <CheckPoint Sim_Time="1523.5" NumVehicleInCity="419" />
    <CheckPoint Sim_Time="1523.5" NumVehicleInCity="418" />
    <CheckPoint Sim_Time="1523.6" NumVehicleInCity="417" />
    <CheckPoint Sim_Time="1523.6" NumVehicleInCity="416" />
    <CheckPoint Sim_Time="1523.7" NumVehicleInCity="415" />
    <CheckPoint Sim_Time="1524.3" NumVehicleInCity="415" />
    <CheckPoint Sim_Time="1524.6" NumVehicleInCity="414" />
    <CheckPoint Sim_Time="1525.2" NumVehicleInCity="414" />
    <CheckPoint Sim_Time="1525.7" NumVehicleInCity="413" />
    <CheckPoint Sim_Time="1526.1" NumVehicleInCity="413" />
    <CheckPoint Sim_Time="1527.5" NumVehicleInCity="413" />
    <CheckPoint Sim_Time="1527.8" NumVehicleInCity="412" />
    <CheckPoint Sim_Time="1527.9" NumVehicleInCity="411" />
    <CheckPoint Sim_Time="1528.4" NumVehicleInCity="411" />
    <CheckPoint Sim_Time="1529.8" NumVehicleInCity="411" />
    <CheckPoint Sim_Time="1530.7" NumVehicleInCity="411" />
    <CheckPoint Sim_Time="1531.4" NumVehicleInCity="411" />
    <CheckPoint Sim_Time="1531.6" NumVehicleInCity="410" />
    <CheckPoint Sim_Time="1531.8" NumVehicleInCity="409" />
    <CheckPoint Sim_Time="1532.2" NumVehicleInCity="409" />
    <CheckPoint Sim_Time="1532.9" NumVehicleInCity="408" />
    <CheckPoint Sim_Time="1533.2" NumVehicleInCity="407" />
    <CheckPoint Sim_Time="1533.7" NumVehicleInCity="406" />
    <CheckPoint Sim_Time="1533.8" NumVehicleInCity="405" />
    <CheckPoint Sim_Time="1534.1" NumVehicleInCity="405" />
    <CheckPoint Sim_Time="1534.2" NumVehicleInCity="404" />
    <CheckPoint Sim_Time="1535.1" NumVehicleInCity="404" />
    <CheckPoint Sim_Time="1537" NumVehicleInCity="405" />
    <CheckPoint Sim_Time="1539.2" NumVehicleInCity="406" />
    <CheckPoint Sim_Time="1539.3" NumVehicleInCity="405" />
    <CheckPoint Sim_Time="1542.5" NumVehicleInCity="407" />
    <CheckPoint Sim_Time="1546" NumVehicleInCity="410" />
    <CheckPoint Sim_Time="1548.2" NumVehicleInCity="411" />
    <CheckPoint Sim_Time="1549.5" NumVehicleInCity="411" />
    <CheckPoint Sim_Time="1549.7" NumVehicleInCity="410" />
    <CheckPoint Sim_Time="1550" NumVehicleInCity="410" />
    <CheckPoint Sim_Time="1551.3" NumVehicleInCity="410" />
    <CheckPoint Sim_Time="1552.9" NumVehicleInCity="410" />
    <CheckPoint Sim_Time="1553.6" NumVehicleInCity="410" />
    <CheckPoint Sim_Time="1554.3" NumVehicleInCity="410" />
    <CheckPoint Sim_Time="1555" NumVehicleInCity="410" />
    <CheckPoint Sim_Time="1555.3" NumVehicleInCity="409" />
    <CheckPoint Sim_Time="1556.2" NumVehicleInCity="409" />
    <CheckPoint Sim_Time="1556.7" NumVehicleInCity="408" />
    <CheckPoint Sim_Time="1567.4" NumVehicleInCity="418" />
    <CheckPoint Sim_Time="1568" NumVehicleInCity="418" />
    <CheckPoint Sim_Time="1568.3" NumVehicleInCity="417" />
    <CheckPoint Sim_Time="1568.4" NumVehicleInCity="416" />
    <CheckPoint Sim_Time="1568.4" NumVehicleInCity="415" />
    <CheckPoint Sim_Time="1568.5" NumVehicleInCity="414" />
    <CheckPoint Sim_Time="1569.4" NumVehicleInCity="414" />
    <CheckPoint Sim_Time="1570" NumVehicleInCity="414" />
    <CheckPoint Sim_Time="1570.3" NumVehicleInCity="413" />
    <CheckPoint Sim_Time="1570.4" NumVehicleInCity="412" />
    <CheckPoint Sim_Time="1570.4" NumVehicleInCity="411" />
    <CheckPoint Sim_Time="1570.8" NumVehicleInCity="410" />
    <CheckPoint Sim_Time="1571.4" NumVehicleInCity="410" />
    <CheckPoint Sim_Time="1571.6" NumVehicleInCity="409" />
    <CheckPoint Sim_Time="1572.3" NumVehicleInCity="409" />
    <CheckPoint Sim_Time="1572.3" NumVehicleInCity="408" />
    <CheckPoint Sim_Time="1572.9" NumVehicleInCity="407" />
    <CheckPoint Sim_Time="1573" NumVehicleInCity="407" />
    <CheckPoint Sim_Time="1573.6" NumVehicleInCity="406" />
    <CheckPoint Sim_Time="1574.6" NumVehicleInCity="406" />
    <CheckPoint Sim_Time="1575.7" NumVehicleInCity="406" />
    <CheckPoint Sim_Time="1576.6" NumVehicleInCity="406" />
    <CheckPoint Sim_Time="1576.6" NumVehicleInCity="405" />
    <CheckPoint Sim_Time="1580.1" NumVehicleInCity="408" />
    <CheckPoint Sim_Time="1582.3" NumVehicleInCity="409" />
    <CheckPoint Sim_Time="1582.5" NumVehicleInCity="408" />
    <CheckPoint Sim_Time="1584.4" NumVehicleInCity="409" />
    <CheckPoint Sim_Time="1585.5" NumVehicleInCity="409" />
    <CheckPoint Sim_Time="1586.2" NumVehicleInCity="409" />
    <CheckPoint Sim_Time="1586.4" NumVehicleInCity="408" />
    <CheckPoint Sim_Time="1590.8" NumVehicleInCity="411" />
    <CheckPoint Sim_Time="1591" NumVehicleInCity="411" />
    <CheckPoint Sim_Time="1591.5" NumVehicleInCity="410" />
    <CheckPoint Sim_Time="1593.3" NumVehicleInCity="411" />
    <CheckPoint Sim_Time="1593.4" NumVehicleInCity="410" />
    <CheckPoint Sim_Time="1594.2" NumVehicleInCity="410" />
    <CheckPoint Sim_Time="1613.4" NumVehicleInCity="428" />
    <CheckPoint Sim_Time="1613.4" NumVehicleInCity="427" />
    <CheckPoint Sim_Time="1613.4" NumVehicleInCity="426" />
    <CheckPoint Sim_Time="1613.7" NumVehicleInCity="425" />
    <CheckPoint Sim_Time="1614.2" NumVehicleInCity="424" />
    <CheckPoint Sim_Time="1614.5" NumVehicleInCity="423" />
    <CheckPoint Sim_Time="1614.5" NumVehicleInCity="422" />
    <CheckPoint Sim_Time="1615.5" NumVehicleInCity="422" />
    <CheckPoint Sim_Time="1615.8" NumVehicleInCity="421" />
    <CheckPoint Sim_Time="1615.9" NumVehicleInCity="420" />
    <CheckPoint Sim_Time="1616.1" NumVehicleInCity="420" />
    <CheckPoint Sim_Time="1616.2" NumVehicleInCity="419" />
    <CheckPoint Sim_Time="1618.1" NumVehicleInCity="420" />
    <CheckPoint Sim_Time="1618.2" NumVehicleInCity="419" />
    <CheckPoint Sim_Time="1618.3" NumVehicleInCity="418" />
    <CheckPoint Sim_Time="1620.5" NumVehicleInCity="419" />
    <CheckPoint Sim_Time="1620.5" NumVehicleInCity="418" />
    <CheckPoint Sim_Time="1621.4" NumVehicleInCity="418" />
    <CheckPoint Sim_Time="1622.2" NumVehicleInCity="418" />
    <CheckPoint Sim_Time="1622.9" NumVehicleInCity="417" />
    <CheckPoint Sim_Time="1624.1" NumVehicleInCity="418" />
    <CheckPoint Sim_Time="1624.2" NumVehicleInCity="417" />
    <CheckPoint Sim_Time="1624.3" NumVehicleInCity="416" />
    <CheckPoint Sim_Time="1624.8" NumVehicleInCity="415" />
    <CheckPoint Sim_Time="1625.2" NumVehicleInCity="415" />
    <CheckPoint Sim_Time="1625.6" NumVehicleInCity="414" />
    <CheckPoint Sim_Time="1626.3" NumVehicleInCity="414" />
    <CheckPoint Sim_Time="1627.2" NumVehicleInCity="414" />
    <CheckPoint Sim_Time="1628.5" NumVehicleInCity="414" />
    <CheckPoint Sim_Time="1635.9" NumVehicleInCity="420" />
    <CheckPoint Sim_Time="1636.3" NumVehicleInCity="420" />
    <CheckPoint Sim_Time="1636.5" NumVehicleInCity="419" />
    <CheckPoint Sim_Time="1636.6" NumVehicleInCity="418" />
    <CheckPoint Sim_Time="1637.6" NumVehicleInCity="418" />
    <CheckPoint Sim_Time="1637.6" NumVehicleInCity="417" />
    <CheckPoint Sim_Time="1639.4" NumVehicleInCity="418" />
    <CheckPoint Sim_Time="1639.4" NumVehicleInCity="417" />
    <CheckPoint Sim_Time="1641.4" NumVehicleInCity="418" />
    <CheckPoint Sim_Time="1641.7" NumVehicleInCity="417" />
    <CheckPoint Sim_Time="1643" NumVehicleInCity="418" />
    <CheckPoint Sim_Time="1644.1" NumVehicleInCity="418" />
    <CheckPoint Sim_Time="1645.4" NumVehicleInCity="418" />
    <CheckPoint Sim_Time="1647" NumVehicleInCity="419" />
    <CheckPoint Sim_Time="1658.2" NumVehicleInCity="429" />
    <CheckPoint Sim_Time="1658.2" NumVehicleInCity="428" />
    <CheckPoint Sim_Time="1658.2" NumVehicleInCity="427" />
    <CheckPoint Sim_Time="1658.5" NumVehicleInCity="426" />
    <CheckPoint Sim_Time="1659.1" NumVehicleInCity="425" />
    <CheckPoint Sim_Time="1659.2" NumVehicleInCity="424" />
    <CheckPoint Sim_Time="1659.3" NumVehicleInCity="423" />
    <CheckPoint Sim_Time="1659.4" NumVehicleInCity="422" />
    <CheckPoint Sim_Time="1659.8" NumVehicleInCity="421" />
    <CheckPoint Sim_Time="1660.4" NumVehicleInCity="421" />
    <CheckPoint Sim_Time="1660.7" NumVehicleInCity="420" />
    <CheckPoint Sim_Time="1660.9" NumVehicleInCity="419" />
    <CheckPoint Sim_Time="1661.4" NumVehicleInCity="419" />
    <CheckPoint Sim_Time="1661.4" NumVehicleInCity="418" />
    <CheckPoint Sim_Time="1662.3" NumVehicleInCity="418" />
    <CheckPoint Sim_Time="1662.9" NumVehicleInCity="417" />
    <CheckPoint Sim_Time="1663.5" NumVehicleInCity="417" />
    <CheckPoint Sim_Time="1664.9" NumVehicleInCity="417" />
    <CheckPoint Sim_Time="1665.6" NumVehicleInCity="417" />
    <CheckPoint Sim_Time="1666.8" NumVehicleInCity="417" />
    <CheckPoint Sim_Time="1667.2" NumVehicleInCity="417" />
    <CheckPoint Sim_Time="1667.9" NumVehicleInCity="416" />
    <CheckPoint Sim_Time="1669.3" NumVehicleInCity="417" />
    <CheckPoint Sim_Time="1670" NumVehicleInCity="417" />
    <CheckPoint Sim_Time="1670.1" NumVehicleInCity="416" />
    <CheckPoint Sim_Time="1670.3" NumVehicleInCity="415" />
    <CheckPoint Sim_Time="1671.5" NumVehicleInCity="415" />
    <CheckPoint Sim_Time="1671.7" NumVehicleInCity="414" />
    <CheckPoint Sim_Time="1671.9" NumVehicleInCity="413" />
    <CheckPoint Sim_Time="1674" NumVehicleInCity="415" />
    <CheckPoint Sim_Time="1675.1" NumVehicleInCity="415" />
    <CheckPoint Sim_Time="1676.5" NumVehicleInCity="415" />
    <CheckPoint Sim_Time="1678.6" NumVehicleInCity="416" />
    <CheckPoint Sim_Time="1678.6" NumVehicleInCity="415" />
    <CheckPoint Sim_Time="1679.3" NumVehicleInCity="415" />
    <CheckPoint Sim_Time="1679.3" NumVehicleInCity="414" />
    <CheckPoint Sim_Time="1681" NumVehicleInCity="415" />
    <CheckPoint Sim_Time="1682.5" NumVehicleInCity="415" />
    <CheckPoint Sim_Time="1684" NumVehicleInCity="416" />
    <CheckPoint Sim_Time="1687.1" NumVehicleInCity="418" />
    <CheckPoint Sim_Time="1687.2" NumVehicleInCity="417" />
    <CheckPoint Sim_Time="1687.5" NumVehicleInCity="416" />
    <CheckPoint Sim_Time="1688.9" NumVehicleInCity="416" />
    <CheckPoint Sim_Time="1689.2" NumVehicleInCity="416" />
    <CheckPoint Sim_Time="1690" NumVehicleInCity="416" />
    <CheckPoint Sim_Time="1699" NumVehicleInCity="424" />
    <CheckPoint Sim_Time="1703.6" NumVehicleInCity="427" />
    <CheckPoint Sim_Time="1703.6" NumVehicleInCity="426" />
    <CheckPoint Sim_Time="1704.3" NumVehicleInCity="426" />
    <CheckPoint Sim_Time="1705.7" NumVehicleInCity="426" />
    <CheckPoint Sim_Time="1705.8" NumVehicleInCity="425" />
    <CheckPoint Sim_Time="1708.3" NumVehicleInCity="427" />
    <CheckPoint Sim_Time="1709.1" NumVehicleInCity="427" />
    <CheckPoint Sim_Time="1709.5" NumVehicleInCity="426" />
    <CheckPoint Sim_Time="1710.2" NumVehicleInCity="426" />
    <CheckPoint Sim_Time="1711.7" NumVehicleInCity="426" />
    <CheckPoint Sim_Time="1712.7" NumVehicleInCity="426" />
    <CheckPoint Sim_Time="1713.5" NumVehicleInCity="426" />
    <CheckPoint Sim_Time="1713.8" NumVehicleInCity="425" />
    <CheckPoint Sim_Time="1714.3" NumVehicleInCity="425" />
    <CheckPoint Sim_Time="1714.4" NumVehicleInCity="424" />
    <CheckPoint Sim_Time="1714.6" NumVehicleInCity="423" />
    <CheckPoint Sim_Time="1714.6" NumVehicleInCity="422" />
    <CheckPoint Sim_Time="1715.2" NumVehicleInCity="422" />
    <CheckPoint Sim_Time="1716.1" NumVehicleInCity="422" />
    <CheckPoint Sim_Time="1716.4" NumVehicleInCity="421" />
    <CheckPoint Sim_Time="1718.6" NumVehicleInCity="422" />
    <CheckPoint Sim_Time="1718.7" NumVehicleInCity="421" />
    <CheckPoint Sim_Time="1721" NumVehicleInCity="423" />
    <CheckPoint Sim_Time="1721.3" NumVehicleInCity="422" />
    <CheckPoint Sim_Time="1723" NumVehicleInCity="423" />
    <CheckPoint Sim_Time="1724.1" NumVehicleInCity="423" />
    <CheckPoint Sim_Time="1725" NumVehicleInCity="423" />
    <CheckPoint Sim_Time="1727.3" NumVehicleInCity="424" />
    <CheckPoint Sim_Time="1729.9" NumVehicleInCity="425" />
    <CheckPoint Sim_Time="1730.6" NumVehicleInCity="425" />
    <CheckPoint Sim_Time="1731.4" NumVehicleInCity="425" />
    <CheckPoint Sim_Time="1734" NumVehicleInCity="427" />
    <CheckPoint Sim_Time="1734.1" NumVehicleInCity="426" />
    <CheckPoint Sim_Time="1747.7" NumVehicleInCity="437" />
    <CheckPoint Sim_Time="1748.4" NumVehicleInCity="437" />
    <CheckPoint Sim_Time="1748.6" NumVehicleInCity="436" />
    <CheckPoint Sim_Time="1748.7" NumVehicleInCity="435" />
    <CheckPoint Sim_Time="1749.2" NumVehicleInCity="435" />
    <CheckPoint Sim_Time="1749.3" NumVehicleInCity="434" />
    <CheckPoint Sim_Time="1749.3" NumVehicleInCity="433" />
    <CheckPoint Sim_Time="1750.4" NumVehicleInCity="433" />
    <CheckPoint Sim_Time="1751" NumVehicleInCity="433" />
    <CheckPoint Sim_Time="1751.2" NumVehicleInCity="432" />
    <CheckPoint Sim_Time="1751.6" NumVehicleInCity="431" />
    <CheckPoint Sim_Time="1751.6" NumVehicleInCity="430" />
    <CheckPoint Sim_Time="1752.3" NumVehicleInCity="430" />
    <CheckPoint Sim_Time="1753.1" NumVehicleInCity="430" />
    <CheckPoint Sim_Time="1754" NumVehicleInCity="430" />
    <CheckPoint Sim_Time="1755" NumVehicleInCity="430" />
    <CheckPoint Sim_Time="1755.7" NumVehicleInCity="429" />
    <CheckPoint Sim_Time="1755.7" NumVehicleInCity="428" />
    <CheckPoint Sim_Time="1757.1" NumVehicleInCity="429" />
    <CheckPoint Sim_Time="1757.3" NumVehicleInCity="428" />
    <CheckPoint Sim_Time="1758.4" NumVehicleInCity="428" />
    <CheckPoint Sim_Time="1758.5" NumVehicleInCity="427" />
    <CheckPoint Sim_Time="1759.8" NumVehicleInCity="427" />
    <CheckPoint Sim_Time="1763.5" NumVehicleInCity="430" />
    <CheckPoint Sim_Time="1765.2" NumVehicleInCity="431" />
    <CheckPoint Sim_Time="1765.3" NumVehicleInCity="430" />
    <CheckPoint Sim_Time="1765.9" NumVehicleInCity="429" />
    <CheckPoint Sim_Time="1766.8" NumVehicleInCity="429" />
    <CheckPoint Sim_Time="1770.6" NumVehicleInCity="432" />
    <CheckPoint Sim_Time="1773.3" NumVehicleInCity="434" />
    <CheckPoint Sim_Time="1774.9" NumVehicleInCity="434" />
    <CheckPoint Sim_Time="1776.6" NumVehicleInCity="435" />
    <CheckPoint Sim_Time="1776.9" NumVehicleInCity="434" />
    <CheckPoint Sim_Time="1777.8" NumVehicleInCity="434" />
    <CheckPoint Sim_Time="1782.3" NumVehicleInCity="438" />
    <CheckPoint Sim_Time="1784.9" NumVehicleInCity="439" />
    <CheckPoint Sim_Time="1791.5" NumVehicleInCity="445" />
    <CheckPoint Sim_Time="1793.4" NumVehicleInCity="446" />
    <CheckPoint Sim_Time="1794.7" NumVehicleInCity="446" />
    <CheckPoint Sim_Time="1795" NumVehicleInCity="446" />
    <CheckPoint Sim_Time="1795.2" NumVehicleInCity="445" />
    <CheckPoint Sim_Time="1795.9" NumVehicleInCity="444" />
    <CheckPoint Sim_Time="1796.1" NumVehicleInCity="444" />
    <CheckPoint Sim_Time="1796.6" NumVehicleInCity="443" />
    <CheckPoint Sim_Time="1797.3" NumVehicleInCity="443" />
    <CheckPoint Sim_Time="1797.6" NumVehicleInCity="442" />
    <CheckPoint Sim_Time="1798" NumVehicleInCity="442" />
    <CheckPoint Sim_Time="1798.1" NumVehicleInCity="441" />
    <CheckPoint Sim_Time="1799.6" NumVehicleInCity="441" />
    <CheckPoint Sim_Time="1799.9" NumVehicleInCity="440" />
    <CheckPoint Sim_Time="1800.1" NumVehicleInCity="440" />
    <CheckPoint Sim_Time="1800.9" NumVehicleInCity="439" />
    <CheckPoint Sim_Time="1801.8" NumVehicleInCity="439" />
    <CheckPoint Sim_Time="1802.5" NumVehicleInCity="439" />
    <CheckPoint Sim_Time="1803" NumVehicleInCity="439" />
    <CheckPoint Sim_Time="1803.6" NumVehicleInCity="438" />
    <CheckPoint Sim_Time="1803.7" NumVehicleInCity="437" />
    <CheckPoint Sim_Time="1804.9" NumVehicleInCity="437" />
    <CheckPoint Sim_Time="1806" NumVehicleInCity="438" />
    <CheckPoint Sim_Time="1806.7" NumVehicleInCity="437" />
    <CheckPoint Sim_Time="1812.3" NumVehicleInCity="442" />
    <CheckPoint Sim_Time="1813.2" NumVehicleInCity="442" />
    <CheckPoint Sim_Time="1814.4" NumVehicleInCity="442" />
    <CheckPoint Sim_Time="1815.9" NumVehicleInCity="442" />
    <CheckPoint Sim_Time="1815.9" NumVehicleInCity="441" />
    <CheckPoint Sim_Time="1816.4" NumVehicleInCity="441" />
    <CheckPoint Sim_Time="1817.6" NumVehicleInCity="441" />
    <CheckPoint Sim_Time="1817.8" NumVehicleInCity="440" />
    <CheckPoint Sim_Time="1817.9" NumVehicleInCity="439" />
    <CheckPoint Sim_Time="1819.7" NumVehicleInCity="440" />
    <CheckPoint Sim_Time="1820.4" NumVehicleInCity="440" />
    <CheckPoint Sim_Time="1820.5" NumVehicleInCity="439" />
    <CheckPoint Sim_Time="1820.6" NumVehicleInCity="438" />
    <CheckPoint Sim_Time="1821.4" NumVehicleInCity="438" />
    <CheckPoint Sim_Time="1822.5" NumVehicleInCity="438" />
    <CheckPoint Sim_Time="1823" NumVehicleInCity="438" />
    <CheckPoint Sim_Time="1824.3" NumVehicleInCity="438" />
    <CheckPoint Sim_Time="1824.9" NumVehicleInCity="437" />
    <CheckPoint Sim_Time="1824.9" NumVehicleInCity="436" />
    <CheckPoint Sim_Time="1825.8" NumVehicleInCity="436" />
    <CheckPoint Sim_Time="1827" NumVehicleInCity="437" />
    <CheckPoint Sim_Time="1838.1" NumVehicleInCity="447" />
    <CheckPoint Sim_Time="1838.3" NumVehicleInCity="446" />
    <CheckPoint Sim_Time="1838.3" NumVehicleInCity="445" />
    <CheckPoint Sim_Time="1838.4" NumVehicleInCity="444" />
    <CheckPoint Sim_Time="1838.6" NumVehicleInCity="443" />
    <CheckPoint Sim_Time="1838.6" NumVehicleInCity="442" />
    <CheckPoint Sim_Time="1839.3" NumVehicleInCity="442" />
    <CheckPoint Sim_Time="1840.2" NumVehicleInCity="442" />
    <CheckPoint Sim_Time="1840.4" NumVehicleInCity="441" />
    <CheckPoint Sim_Time="1840.8" NumVehicleInCity="440" />
    <CheckPoint Sim_Time="1840.9" NumVehicleInCity="439" />
    <CheckPoint Sim_Time="1841.3" NumVehicleInCity="439" />
    <CheckPoint Sim_Time="1842.5" NumVehicleInCity="439" />
    <CheckPoint Sim_Time="1842.8" NumVehicleInCity="438" />
    <CheckPoint Sim_Time="1843.3" NumVehicleInCity="438" />
    <CheckPoint Sim_Time="1844.9" NumVehicleInCity="438" />
    <CheckPoint Sim_Time="1845" NumVehicleInCity="438" />
    <CheckPoint Sim_Time="1846.9" NumVehicleInCity="438" />
    <CheckPoint Sim_Time="1848.8" NumVehicleInCity="439" />
    <CheckPoint Sim_Time="1849.5" NumVehicleInCity="439" />
    <CheckPoint Sim_Time="1849.8" NumVehicleInCity="438" />
    <CheckPoint Sim_Time="1850.3" NumVehicleInCity="438" />
    <CheckPoint Sim_Time="1852.5" NumVehicleInCity="439" />
    <CheckPoint Sim_Time="1853.2" NumVehicleInCity="439" />
    <CheckPoint Sim_Time="1855.3" NumVehicleInCity="440" />
    <CheckPoint Sim_Time="1855.6" NumVehicleInCity="439" />
    <CheckPoint Sim_Time="1855.9" NumVehicleInCity="438" />
    <CheckPoint Sim_Time="1857.3" NumVehicleInCity="439" />
    <CheckPoint Sim_Time="1858.2" NumVehicleInCity="439" />
    <CheckPoint Sim_Time="1858.5" NumVehicleInCity="438" />
    <CheckPoint Sim_Time="1859.4" NumVehicleInCity="438" />
    <CheckPoint Sim_Time="1859.5" NumVehicleInCity="437" />
    <CheckPoint Sim_Time="1860.2" NumVehicleInCity="437" />
    <CheckPoint Sim_Time="1861.9" NumVehicleInCity="437" />
    <CheckPoint Sim_Time="1862.2" NumVehicleInCity="437" />
    <CheckPoint Sim_Time="1863.7" NumVehicleInCity="437" />
    <CheckPoint Sim_Time="1865.2" NumVehicleInCity="438" />
    <CheckPoint Sim_Time="1865.2" NumVehicleInCity="437" />
    <CheckPoint Sim_Time="1866" NumVehicleInCity="437" />
    <CheckPoint Sim_Time="1867.8" NumVehicleInCity="437" />
    <CheckPoint Sim_Time="1868.4" NumVehicleInCity="437" />
    <CheckPoint Sim_Time="1868.6" NumVehicleInCity="436" />
    <CheckPoint Sim_Time="1869.7" NumVehicleInCity="436" />
    <CheckPoint Sim_Time="1870.6" NumVehicleInCity="436" />
    <CheckPoint Sim_Time="1871.1" NumVehicleInCity="436" />
    <CheckPoint Sim_Time="1872.9" NumVehicleInCity="436" />
    <CheckPoint Sim_Time="1881.2" NumVehicleInCity="444" />
    <CheckPoint Sim_Time="1883.4" NumVehicleInCity="445" />
    <CheckPoint Sim_Time="1883.6" NumVehicleInCity="444" />
    <CheckPoint Sim_Time="1884.2" NumVehicleInCity="444" />
    <CheckPoint Sim_Time="1884.6" NumVehicleInCity="443" />
    <CheckPoint Sim_Time="1885.6" NumVehicleInCity="443" />
    <CheckPoint Sim_Time="1886.1" NumVehicleInCity="443" />
    <CheckPoint Sim_Time="1887" NumVehicleInCity="443" />
    <CheckPoint Sim_Time="1887.3" NumVehicleInCity="442" />
    <CheckPoint Sim_Time="1887.4" NumVehicleInCity="441" />
    <CheckPoint Sim_Time="1887.9" NumVehicleInCity="440" />
    <CheckPoint Sim_Time="1888.5" NumVehicleInCity="440" />
    <CheckPoint Sim_Time="1889.1" NumVehicleInCity="440" />
    <CheckPoint Sim_Time="1889.5" NumVehicleInCity="439" />
    <CheckPoint Sim_Time="1889.8" NumVehicleInCity="438" />
    <CheckPoint Sim_Time="1891.6" NumVehicleInCity="439" />
    <CheckPoint Sim_Time="1891.8" NumVehicleInCity="438" />
    <CheckPoint Sim_Time="1892.3" NumVehicleInCity="438" />
    <CheckPoint Sim_Time="1894.2" NumVehicleInCity="439" />
    <CheckPoint Sim_Time="1894.5" NumVehicleInCity="438" />
    <CheckPoint Sim_Time="1894.7" NumVehicleInCity="437" />
    <CheckPoint Sim_Time="1894.9" NumVehicleInCity="436" />
    <CheckPoint Sim_Time="1896.9" NumVehicleInCity="437" />
    <CheckPoint Sim_Time="1897" NumVehicleInCity="437" />
    <CheckPoint Sim_Time="1897" NumVehicleInCity="436" />
    <CheckPoint Sim_Time="1897.3" NumVehicleInCity="435" />
    <CheckPoint Sim_Time="1898.5" NumVehicleInCity="435" />
    <CheckPoint Sim_Time="1899.1" NumVehicleInCity="435" />
    <CheckPoint Sim_Time="1899.3" NumVehicleInCity="434" />
    <CheckPoint Sim_Time="1899.5" NumVehicleInCity="433" />
    <CheckPoint Sim_Time="1899.7" NumVehicleInCity="432" />
    <CheckPoint Sim_Time="1900.2" NumVehicleInCity="432" />
    <CheckPoint Sim_Time="1901.3" NumVehicleInCity="432" />
    <CheckPoint Sim_Time="1903.4" NumVehicleInCity="433" />
    <CheckPoint Sim_Time="1904.8" NumVehicleInCity="433" />
    <CheckPoint Sim_Time="1905.8" NumVehicleInCity="433" />
    <CheckPoint Sim_Time="1906.1" NumVehicleInCity="433" />
    <CheckPoint Sim_Time="1908.5" NumVehicleInCity="434" />
    <CheckPoint Sim_Time="1908.6" NumVehicleInCity="433" />
    <CheckPoint Sim_Time="1910.4" NumVehicleInCity="434" />
    <CheckPoint Sim_Time="1910.7" NumVehicleInCity="433" />
    <CheckPoint Sim_Time="1912.6" NumVehicleInCity="434" />
    <CheckPoint Sim_Time="1912.8" NumVehicleInCity="433" />
    <CheckPoint Sim_Time="1914.6" NumVehicleInCity="434" />
    <CheckPoint Sim_Time="1915" NumVehicleInCity="434" />
    <CheckPoint Sim_Time="1916.8" NumVehicleInCity="434" />
    <CheckPoint Sim_Time="1927" NumVehicleInCity="444" />
    <CheckPoint Sim_Time="1927.5" NumVehicleInCity="443" />
    <CheckPoint Sim_Time="1927.6" NumVehicleInCity="442" />
    <CheckPoint Sim_Time="1928.5" NumVehicleInCity="442" />
    <CheckPoint Sim_Time="1929" NumVehicleInCity="442" />
    <CheckPoint Sim_Time="1929.3" NumVehicleInCity="441" />
    <CheckPoint Sim_Time="1930.1" NumVehicleInCity="441" />
    <CheckPoint Sim_Time="1930.2" NumVehicleInCity="440" />
    <CheckPoint Sim_Time="1930.2" NumVehicleInCity="439" />
    <CheckPoint Sim_Time="1930.6" NumVehicleInCity="438" />
    <CheckPoint Sim_Time="1932.3" NumVehicleInCity="439" />
    <CheckPoint Sim_Time="1932.3" NumVehicleInCity="438" />
    <CheckPoint Sim_Time="1933" NumVehicleInCity="438" />
    <CheckPoint Sim_Time="1934.3" NumVehicleInCity="438" />
    <CheckPoint Sim_Time="1936.3" NumVehicleInCity="439" />
    <CheckPoint Sim_Time="1936.3" NumVehicleInCity="438" />
    <CheckPoint Sim_Time="1936.5" NumVehicleInCity="437" />
    <CheckPoint Sim_Time="1936.6" NumVehicleInCity="436" />
    <CheckPoint Sim_Time="1938.4" NumVehicleInCity="437" />
    <CheckPoint Sim_Time="1939" NumVehicleInCity="437" />
    <CheckPoint Sim_Time="1939" NumVehicleInCity="436" />
    <CheckPoint Sim_Time="1939.3" NumVehicleInCity="435" />
    <CheckPoint Sim_Time="1939.7" NumVehicleInCity="434" />
    <CheckPoint Sim_Time="1943" NumVehicleInCity="436" />
    <CheckPoint Sim_Time="1943.1" NumVehicleInCity="435" />
    <CheckPoint Sim_Time="1943.5" NumVehicleInCity="434" />
    <CheckPoint Sim_Time="1946.9" NumVehicleInCity="436" />
    <CheckPoint Sim_Time="1947.4" NumVehicleInCity="436" />
    <CheckPoint Sim_Time="1947.6" NumVehicleInCity="435" />
    <CheckPoint Sim_Time="1951.3" NumVehicleInCity="438" />
    <CheckPoint Sim_Time="1953" NumVehicleInCity="439" />
    <CheckPoint Sim_Time="1953.2" NumVehicleInCity="438" />
    <CheckPoint Sim_Time="1955.4" NumVehicleInCity="439" />
    <CheckPoint Sim_Time="1958.1" NumVehicleInCity="441" />
    <CheckPoint Sim_Time="1958.2" NumVehicleInCity="440" />
    <CheckPoint Sim_Time="1958.2" NumVehicleInCity="439" />
    <CheckPoint Sim_Time="1960" NumVehicleInCity="440" />
    <CheckPoint Sim_Time="1960.2" NumVehicleInCity="439" />
    <CheckPoint Sim_Time="1972.5" NumVehicleInCity="450" />
    <CheckPoint Sim_Time="1973.2" NumVehicleInCity="450" />
    <CheckPoint Sim_Time="1973.3" NumVehicleInCity="449" />
    <CheckPoint Sim_Time="1973.8" NumVehicleInCity="448" />
    <CheckPoint Sim_Time="1974" NumVehicleInCity="448" />
    <CheckPoint Sim_Time="1974.3" NumVehicleInCity="447" />
    <CheckPoint Sim_Time="1975.1" NumVehicleInCity="447" />
    <CheckPoint Sim_Time="1975.3" NumVehicleInCity="446" />
    <CheckPoint Sim_Time="1975.4" NumVehicleInCity="445" />
    <CheckPoint Sim_Time="1975.5" NumVehicleInCity="444" />
    <CheckPoint Sim_Time="1975.9" NumVehicleInCity="443" />
    <CheckPoint Sim_Time="1976.6" NumVehicleInCity="443" />
    <CheckPoint Sim_Time="1977" NumVehicleInCity="443" />
    <CheckPoint Sim_Time="1977.3" NumVehicleInCity="442" />
    <CheckPoint Sim_Time="1977.5" NumVehicleInCity="441" />
    <CheckPoint Sim_Time="1977.8" NumVehicleInCity="440" />
    <CheckPoint Sim_Time="1978.4" NumVehicleInCity="440" />
    <CheckPoint Sim_Time="1979.4" NumVehicleInCity="440" />
    <CheckPoint Sim_Time="1979.5" NumVehicleInCity="439" />
    <CheckPoint Sim_Time="1979.9" NumVehicleInCity="438" />
    <CheckPoint Sim_Time="1980.2" NumVehicleInCity="438" />
    <CheckPoint Sim_Time="1980.6" NumVehicleInCity="437" />
    <CheckPoint Sim_Time="1981.5" NumVehicleInCity="437" />
    <CheckPoint Sim_Time="1982.4" NumVehicleInCity="437" />
    <CheckPoint Sim_Time="1983.9" NumVehicleInCity="437" />
    <CheckPoint Sim_Time="1984.2" NumVehicleInCity="437" />
    <CheckPoint Sim_Time="1984.3" NumVehicleInCity="436" />
    <CheckPoint Sim_Time="1984.7" NumVehicleInCity="435" />
    <CheckPoint Sim_Time="1985" NumVehicleInCity="435" />
    <CheckPoint Sim_Time="1987.5" NumVehicleInCity="436" />
    <CheckPoint Sim_Time="1988.3" NumVehicleInCity="436" />
    <CheckPoint Sim_Time="1989.4" NumVehicleInCity="436" />
    <CheckPoint Sim_Time="1989.6" NumVehicleInCity="435" />
    <CheckPoint Sim_Time="1992.7" NumVehicleInCity="436" />
    <CheckPoint Sim_Time="1993.6" NumVehicleInCity="436" />
    <CheckPoint Sim_Time="1996.6" NumVehicleInCity="438" />
    <CheckPoint Sim_Time="2000" NumVehicleInCity="441" />
    <CheckPoint Sim_Time="2002.9" NumVehicleInCity="442" />
    <CheckPoint Sim_Time="2003.3" NumVehicleInCity="442" />
    <CheckPoint Sim_Time="2004.3" NumVehicleInCity="442" />
    <CheckPoint Sim_Time="2004.9" NumVehicleInCity="441" />
    <CheckPoint Sim_Time="2006.3" NumVehicleInCity="442" />
    <CheckPoint Sim_Time="2006.7" NumVehicleInCity="441" />
    <CheckPoint Sim_Time="2016.2" NumVehicleInCity="450" />
    <CheckPoint Sim_Time="2018.4" NumVehicleInCity="451" />
    <CheckPoint Sim_Time="2018.5" NumVehicleInCity="450" />
    <CheckPoint Sim_Time="2018.6" NumVehicleInCity="449" />
    <CheckPoint Sim_Time="2019.2" NumVehicleInCity="449" />
    <CheckPoint Sim_Time="2019.3" NumVehicleInCity="448" />
    <CheckPoint Sim_Time="2020.7" NumVehicleInCity="448" />
    <CheckPoint Sim_Time="2021.1" NumVehicleInCity="448" />
    <CheckPoint Sim_Time="2021.7" NumVehicleInCity="447" />
    <CheckPoint Sim_Time="2022.8" NumVehicleInCity="447" />
    <CheckPoint Sim_Time="2023.8" NumVehicleInCity="447" />
    <CheckPoint Sim_Time="2025" NumVehicleInCity="448" />
    <CheckPoint Sim_Time="2025.2" NumVehicleInCity="447" />
    <CheckPoint Sim_Time="2026.5" NumVehicleInCity="447" />
    <CheckPoint Sim_Time="2026.9" NumVehicleInCity="446" />
    <CheckPoint Sim_Time="2027.2" NumVehicleInCity="446" />
    <CheckPoint Sim_Time="2027.3" NumVehicleInCity="445" />
    <CheckPoint Sim_Time="2029.1" NumVehicleInCity="446" />
    <CheckPoint Sim_Time="2029.6" NumVehicleInCity="445" />
    <CheckPoint Sim_Time="2031.4" NumVehicleInCity="446" />
    <CheckPoint Sim_Time="2032.9" NumVehicleInCity="446" />
    <CheckPoint Sim_Time="2036.4" NumVehicleInCity="448" />
    <CheckPoint Sim_Time="2038" NumVehicleInCity="449" />
    <CheckPoint Sim_Time="2039.5" NumVehicleInCity="449" />
    <CheckPoint Sim_Time="2040.4" NumVehicleInCity="449" />
    <CheckPoint Sim_Time="2040.5" NumVehicleInCity="448" />
    <CheckPoint Sim_Time="2042.7" NumVehicleInCity="449" />
    <CheckPoint Sim_Time="2044.4" NumVehicleInCity="450" />
    <CheckPoint Sim_Time="2045.5" NumVehicleInCity="450" />
    <CheckPoint Sim_Time="2048.2" NumVehicleInCity="452" />
    <CheckPoint Sim_Time="2049.1" NumVehicleInCity="452" />
    <CheckPoint Sim_Time="2050" NumVehicleInCity="452" />
    <CheckPoint Sim_Time="2050.2" NumVehicleInCity="451" />
    <CheckPoint Sim_Time="2052.3" NumVehicleInCity="452" />
    <CheckPoint Sim_Time="2062.6" NumVehicleInCity="461" />
    <CheckPoint Sim_Time="2063.3" NumVehicleInCity="461" />
    <CheckPoint Sim_Time="2063.5" NumVehicleInCity="460" />
    <CheckPoint Sim_Time="2063.7" NumVehicleInCity="459" />
    <CheckPoint Sim_Time="2063.8" NumVehicleInCity="458" />
    <CheckPoint Sim_Time="2064.8" NumVehicleInCity="458" />
    <CheckPoint Sim_Time="2065.1" NumVehicleInCity="458" />
    <CheckPoint Sim_Time="2065.6" NumVehicleInCity="457" />
    <CheckPoint Sim_Time="2065.9" NumVehicleInCity="456" />
    <CheckPoint Sim_Time="2065.9" NumVehicleInCity="455" />
    <CheckPoint Sim_Time="2066.1" NumVehicleInCity="455" />
    <CheckPoint Sim_Time="2066.3" NumVehicleInCity="454" />
    <CheckPoint Sim_Time="2066.8" NumVehicleInCity="453" />
    <CheckPoint Sim_Time="2067.2" NumVehicleInCity="453" />
    <CheckPoint Sim_Time="2067.6" NumVehicleInCity="452" />
    <CheckPoint Sim_Time="2067.7" NumVehicleInCity="451" />
    <CheckPoint Sim_Time="2068" NumVehicleInCity="451" />
    <CheckPoint Sim_Time="2068.1" NumVehicleInCity="450" />
    <CheckPoint Sim_Time="2068.9" NumVehicleInCity="449" />
    <CheckPoint Sim_Time="2070" NumVehicleInCity="450" />
    <CheckPoint Sim_Time="2070.2" NumVehicleInCity="449" />
    <CheckPoint Sim_Time="2070.4" NumVehicleInCity="448" />
    <CheckPoint Sim_Time="2071.2" NumVehicleInCity="448" />
    <CheckPoint Sim_Time="2071.7" NumVehicleInCity="447" />
    <CheckPoint Sim_Time="2072.6" NumVehicleInCity="447" />
    <CheckPoint Sim_Time="2074.5" NumVehicleInCity="448" />
    <CheckPoint Sim_Time="2076.6" NumVehicleInCity="449" />
    <CheckPoint Sim_Time="2077.3" NumVehicleInCity="449" />
    <CheckPoint Sim_Time="2078.9" NumVehicleInCity="449" />
    <CheckPoint Sim_Time="2079" NumVehicleInCity="449" />
    <CheckPoint Sim_Time="2080.3" NumVehicleInCity="449" />
    <CheckPoint Sim_Time="2082.1" NumVehicleInCity="450" />
    <CheckPoint Sim_Time="2083.7" NumVehicleInCity="450" />
    <CheckPoint Sim_Time="2084.9" NumVehicleInCity="450" />
    <CheckPoint Sim_Time="2086.3" NumVehicleInCity="451" />
    <CheckPoint Sim_Time="2087.6" NumVehicleInCity="451" />
    <CheckPoint Sim_Time="2087.6" NumVehicleInCity="450" />
    <CheckPoint Sim_Time="2089.6" NumVehicleInCity="451" />
    <CheckPoint Sim_Time="2090.3" NumVehicleInCity="451" />
    <CheckPoint Sim_Time="2092.3" NumVehicleInCity="452" />
    <CheckPoint Sim_Time="2093.5" NumVehicleInCity="452" />
    <CheckPoint Sim_Time="2094.5" NumVehicleInCity="452" />
    <CheckPoint Sim_Time="2095.6" NumVehicleInCity="452" />
    <CheckPoint Sim_Time="2095.6" NumVehicleInCity="451" />
    <CheckPoint Sim_Time="2096.2" NumVehicleInCity="451" />
</Protocol>
