<Protocol Name="FloodingVehicleInCity">
    <CheckPoint Sim_Time="157.9" NumVehicleInCity="153" />
    <CheckPoint Sim_Time="171.6" NumVehicleInCity="165" />
    <CheckPoint Sim_Time="172.9" NumVehicleInCity="166" />
    <CheckPoint Sim_Time="174.6" NumVehicleInCity="167" />
    <CheckPoint Sim_Time="174.7" NumVehicleInCity="166" />
    <CheckPoint Sim_Time="175.4" NumVehicleInCity="165" />
    <CheckPoint Sim_Time="177.4" NumVehicleInCity="166" />
    <CheckPoint Sim_Time="178.6" NumVehicleInCity="167" />
    <CheckPoint Sim_Time="185.1" NumVehicleInCity="171" />
    <CheckPoint Sim_Time="194.5" NumVehicleInCity="179" />
    <CheckPoint Sim_Time="199.3" NumVehicleInCity="181" />
    <CheckPoint Sim_Time="202.6" NumVehicleInCity="184" />
    <CheckPoint Sim_Time="211.6" NumVehicleInCity="191" />
    <CheckPoint Sim_Time="218.2" NumVehicleInCity="196" />
    <CheckPoint Sim_Time="218.7" NumVehicleInCity="195" />
    <CheckPoint Sim_Time="219.4" NumVehicleInCity="196" />
    <CheckPoint Sim_Time="221" NumVehicleInCity="197" />
    <CheckPoint Sim_Time="224.4" NumVehicleInCity="197" />
    <CheckPoint Sim_Time="224.9" NumVehicleInCity="196" />
    <CheckPoint Sim_Time="226.6" NumVehicleInCity="199" />
    <CheckPoint Sim_Time="229.1" NumVehicleInCity="198" />
    <CheckPoint Sim_Time="230.9" NumVehicleInCity="199" />
    <CheckPoint Sim_Time="231.7" NumVehicleInCity="199" />
    <CheckPoint Sim_Time="235.8" NumVehicleInCity="202" />
    <CheckPoint Sim_Time="236.2" NumVehicleInCity="201" />
    <CheckPoint Sim_Time="237.9" NumVehicleInCity="204" />
    <CheckPoint Sim_Time="243.1" NumVehicleInCity="207" />
    <CheckPoint Sim_Time="248.4" NumVehicleInCity="209" />
    <CheckPoint Sim_Time="258.4" NumVehicleInCity="221" />
    <CheckPoint Sim_Time="263.3" NumVehicleInCity="226" />
    <CheckPoint Sim_Time="263.4" NumVehicleInCity="225" />
    <CheckPoint Sim_Time="263.6" NumVehicleInCity="224" />
    <CheckPoint Sim_Time="264.4" NumVehicleInCity="224" />
    <CheckPoint Sim_Time="265.3" NumVehicleInCity="223" />
    <CheckPoint Sim_Time="265.7" NumVehicleInCity="222" />
    <CheckPoint Sim_Time="266.6" NumVehicleInCity="221" />
    <CheckPoint Sim_Time="268.5" NumVehicleInCity="224" />
    <CheckPoint Sim_Time="272.7" NumVehicleInCity="226" />
    <CheckPoint Sim_Time="275" NumVehicleInCity="229" />
    <CheckPoint Sim_Time="278.9" NumVehicleInCity="230" />
    <CheckPoint Sim_Time="282" NumVehicleInCity="233" />
    <CheckPoint Sim_Time="282.3" NumVehicleInCity="233" />
    <CheckPoint Sim_Time="286.8" NumVehicleInCity="237" />
    <CheckPoint Sim_Time="290.8" NumVehicleInCity="241" />
    <CheckPoint Sim_Time="291" NumVehicleInCity="240" />
    <CheckPoint Sim_Time="293.7" NumVehicleInCity="243" />
    <CheckPoint Sim_Time="294.7" NumVehicleInCity="242" />
    <CheckPoint Sim_Time="304.8" NumVehicleInCity="249" />
    <CheckPoint Sim_Time="306.7" NumVehicleInCity="250" />
    <CheckPoint Sim_Time="307" NumVehicleInCity="250" />
    <CheckPoint Sim_Time="307.3" NumVehicleInCity="249" />
    <CheckPoint Sim_Time="307.7" NumVehicleInCity="248" />
    <CheckPoint Sim_Time="308.3" NumVehicleInCity="248" />
    <CheckPoint Sim_Time="309.9" NumVehicleInCity="248" />
    <CheckPoint Sim_Time="314.6" NumVehicleInCity="251" />
    <CheckPoint Sim_Time="315.6" NumVehicleInCity="251" />
    <CheckPoint Sim_Time="317.3" NumVehicleInCity="252" />
    <CheckPoint Sim_Time="318.9" NumVehicleInCity="253" />
    <CheckPoint Sim_Time="319.4" NumVehicleInCity="253" />
    <CheckPoint Sim_Time="319.8" NumVehicleInCity="253" />
    <CheckPoint Sim_Time="323.2" NumVehicleInCity="255" />
    <CheckPoint Sim_Time="327.3" NumVehicleInCity="259" />
    <CheckPoint Sim_Time="327.6" NumVehicleInCity="259" />
    <CheckPoint Sim_Time="328.5" NumVehicleInCity="259" />
    <CheckPoint Sim_Time="330.6" NumVehicleInCity="261" />
    <CheckPoint Sim_Time="331" NumVehicleInCity="260" />
    <CheckPoint Sim_Time="332" NumVehicleInCity="259" />
    <CheckPoint Sim_Time="334.5" NumVehicleInCity="262" />
    <CheckPoint Sim_Time="334.8" NumVehicleInCity="262" />
    <CheckPoint Sim_Time="353.3" NumVehicleInCity="277" />
    <CheckPoint Sim_Time="353.3" NumVehicleInCity="276" />
    <CheckPoint Sim_Time="353.3" NumVehicleInCity="275" />
    <CheckPoint Sim_Time="353.5" NumVehicleInCity="274" />
    <CheckPoint Sim_Time="354.2" NumVehicleInCity="274" />
    <CheckPoint Sim_Time="355.5" NumVehicleInCity="275" />
    <CheckPoint Sim_Time="355.8" NumVehicleInCity="274" />
    <CheckPoint Sim_Time="355.9" NumVehicleInCity="273" />
    <CheckPoint Sim_Time="356.3" NumVehicleInCity="272" />
    <CheckPoint Sim_Time="357.4" NumVehicleInCity="272" />
    <CheckPoint Sim_Time="357.5" NumVehicleInCity="271" />
    <CheckPoint Sim_Time="357.9" NumVehicleInCity="270" />
    <CheckPoint Sim_Time="358.2" NumVehicleInCity="270" />
    <CheckPoint Sim_Time="358.8" NumVehicleInCity="270" />
    <CheckPoint Sim_Time="359.8" NumVehicleInCity="272" />
    <CheckPoint Sim_Time="360.5" NumVehicleInCity="272" />
    <CheckPoint Sim_Time="362.3" NumVehicleInCity="271" />
    <CheckPoint Sim_Time="364.2" NumVehicleInCity="272" />
    <CheckPoint Sim_Time="367.1" NumVehicleInCity="275" />
    <CheckPoint Sim_Time="368.1" NumVehicleInCity="274" />
    <CheckPoint Sim_Time="368.3" NumVehicleInCity="273" />
    <CheckPoint Sim_Time="368.6" NumVehicleInCity="272" />
    <CheckPoint Sim_Time="370.4" NumVehicleInCity="273" />
    <CheckPoint Sim_Time="370.7" NumVehicleInCity="272" />
    <CheckPoint Sim_Time="373.2" NumVehicleInCity="275" />
    <CheckPoint Sim_Time="373.9" NumVehicleInCity="274" />
    <CheckPoint Sim_Time="374.1" NumVehicleInCity="273" />
    <CheckPoint Sim_Time="376.8" NumVehicleInCity="274" />
    <CheckPoint Sim_Time="380.6" NumVehicleInCity="276" />
    <CheckPoint Sim_Time="382.6" NumVehicleInCity="276" />
    <CheckPoint Sim_Time="383.1" NumVehicleInCity="275" />
    <CheckPoint Sim_Time="385.4" NumVehicleInCity="278" />
    <CheckPoint Sim_Time="398.5" NumVehicleInCity="290" />
    <CheckPoint Sim_Time="398.6" NumVehicleInCity="289" />
    <CheckPoint Sim_Time="398.6" NumVehicleInCity="288" />
    <CheckPoint Sim_Time="398.7" NumVehicleInCity="287" />
    <CheckPoint Sim_Time="400.7" NumVehicleInCity="287" />
    <CheckPoint Sim_Time="401" NumVehicleInCity="286" />
    <CheckPoint Sim_Time="401.2" NumVehicleInCity="285" />
    <CheckPoint Sim_Time="402.5" NumVehicleInCity="286" />
    <CheckPoint Sim_Time="402.9" NumVehicleInCity="286" />
    <CheckPoint Sim_Time="402.9" NumVehicleInCity="285" />
    <CheckPoint Sim_Time="403.3" NumVehicleInCity="284" />
    <CheckPoint Sim_Time="404.2" NumVehicleInCity="284" />
    <CheckPoint Sim_Time="405.7" NumVehicleInCity="284" />
    <CheckPoint Sim_Time="406.9" NumVehicleInCity="283" />
    <CheckPoint Sim_Time="408.3" NumVehicleInCity="286" />
    <CheckPoint Sim_Time="408.4" NumVehicleInCity="286" />
    <CheckPoint Sim_Time="408.7" NumVehicleInCity="285" />
    <CheckPoint Sim_Time="409.2" NumVehicleInCity="284" />
    <CheckPoint Sim_Time="410.1" NumVehicleInCity="284" />
    <CheckPoint Sim_Time="411.5" NumVehicleInCity="284" />
    <CheckPoint Sim_Time="411.8" NumVehicleInCity="283" />
    <CheckPoint Sim_Time="412.2" NumVehicleInCity="283" />
    <CheckPoint Sim_Time="413.1" NumVehicleInCity="283" />
    <CheckPoint Sim_Time="415.2" NumVehicleInCity="284" />
    <CheckPoint Sim_Time="415.5" NumVehicleInCity="284" />
    <CheckPoint Sim_Time="417.1" NumVehicleInCity="284" />
    <CheckPoint Sim_Time="417.7" NumVehicleInCity="283" />
    <CheckPoint Sim_Time="419.7" NumVehicleInCity="285" />
    <CheckPoint Sim_Time="422.3" NumVehicleInCity="287" />
    <CheckPoint Sim_Time="423.1" NumVehicleInCity="287" />
    <CheckPoint Sim_Time="425.8" NumVehicleInCity="289" />
    <CheckPoint Sim_Time="426.2" NumVehicleInCity="289" />
    <CheckPoint Sim_Time="428.8" NumVehicleInCity="289" />
    <CheckPoint Sim_Time="429.2" NumVehicleInCity="289" />
    <CheckPoint Sim_Time="431.3" NumVehicleInCity="291" />
    <CheckPoint Sim_Time="443.4" NumVehicleInCity="301" />
    <CheckPoint Sim_Time="443.4" NumVehicleInCity="300" />
    <CheckPoint Sim_Time="443.4" NumVehicleInCity="299" />
    <CheckPoint Sim_Time="443.8" NumVehicleInCity="298" />
    <CheckPoint Sim_Time="444.2" NumVehicleInCity="297" />
    <CheckPoint Sim_Time="444.3" NumVehicleInCity="296" />
    <CheckPoint Sim_Time="444.9" NumVehicleInCity="295" />
    <CheckPoint Sim_Time="444.9" NumVehicleInCity="294" />
    <CheckPoint Sim_Time="445.2" NumVehicleInCity="293" />
    <CheckPoint Sim_Time="445.2" NumVehicleInCity="292" />
    <CheckPoint Sim_Time="445.8" NumVehicleInCity="292" />
    <CheckPoint Sim_Time="445.9" NumVehicleInCity="291" />
    <CheckPoint Sim_Time="445.9" NumVehicleInCity="290" />
    <CheckPoint Sim_Time="447.8" NumVehicleInCity="292" />
    <CheckPoint Sim_Time="450.5" NumVehicleInCity="294" />
    <CheckPoint Sim_Time="451.6" NumVehicleInCity="294" />
    <CheckPoint Sim_Time="454.2" NumVehicleInCity="296" />
    <CheckPoint Sim_Time="455.5" NumVehicleInCity="296" />
    <CheckPoint Sim_Time="455.9" NumVehicleInCity="295" />
    <CheckPoint Sim_Time="456.1" NumVehicleInCity="294" />
    <CheckPoint Sim_Time="456.4" NumVehicleInCity="293" />
    <CheckPoint Sim_Time="456.7" NumVehicleInCity="292" />
    <CheckPoint Sim_Time="456.9" NumVehicleInCity="291" />
    <CheckPoint Sim_Time="458.4" NumVehicleInCity="293" />
    <CheckPoint Sim_Time="459.4" NumVehicleInCity="292" />
    <CheckPoint Sim_Time="459.5" NumVehicleInCity="291" />
    <CheckPoint Sim_Time="460.4" NumVehicleInCity="292" />
    <CheckPoint Sim_Time="461.5" NumVehicleInCity="293" />
    <CheckPoint Sim_Time="463.5" NumVehicleInCity="296" />
    <CheckPoint Sim_Time="463.9" NumVehicleInCity="295" />
    <CheckPoint Sim_Time="466.7" NumVehicleInCity="295" />
    <CheckPoint Sim_Time="467.4" NumVehicleInCity="294" />
    <CheckPoint Sim_Time="467.5" NumVehicleInCity="293" />
    <CheckPoint Sim_Time="467.9" NumVehicleInCity="292" />
    <CheckPoint Sim_Time="470" NumVehicleInCity="294" />
    <CheckPoint Sim_Time="470.2" NumVehicleInCity="294" />
    <CheckPoint Sim_Time="472" NumVehicleInCity="295" />
    <CheckPoint Sim_Time="473.6" NumVehicleInCity="296" />
    <CheckPoint Sim_Time="474.2" NumVehicleInCity="295" />
    <CheckPoint Sim_Time="476.1" NumVehicleInCity="296" />
    <CheckPoint Sim_Time="488.3" NumVehicleInCity="308" />
    <CheckPoint Sim_Time="488.4" NumVehicleInCity="307" />
    <CheckPoint Sim_Time="488.6" NumVehicleInCity="306" />
    <CheckPoint Sim_Time="489.2" NumVehicleInCity="305" />
    <CheckPoint Sim_Time="489.3" NumVehicleInCity="305" />
    <CheckPoint Sim_Time="489.4" NumVehicleInCity="306" />
    <CheckPoint Sim_Time="490.2" NumVehicleInCity="305" />
    <CheckPoint Sim_Time="490.9" NumVehicleInCity="305" />
    <CheckPoint Sim_Time="491" NumVehicleInCity="304" />
    <CheckPoint Sim_Time="492.4" NumVehicleInCity="304" />
    <CheckPoint Sim_Time="492.9" NumVehicleInCity="303" />
    <CheckPoint Sim_Time="493.1" NumVehicleInCity="302" />
    <CheckPoint Sim_Time="494.3" NumVehicleInCity="303" />
    <CheckPoint Sim_Time="494.5" NumVehicleInCity="302" />
    <CheckPoint Sim_Time="494.7" NumVehicleInCity="301" />
    <CheckPoint Sim_Time="495.7" NumVehicleInCity="301" />
    <CheckPoint Sim_Time="497.8" NumVehicleInCity="303" />
    <CheckPoint Sim_Time="497.8" NumVehicleInCity="302" />
    <CheckPoint Sim_Time="500.9" NumVehicleInCity="303" />
    <CheckPoint Sim_Time="501" NumVehicleInCity="302" />
    <CheckPoint Sim_Time="501.8" NumVehicleInCity="302" />
    <CheckPoint Sim_Time="503.4" NumVehicleInCity="301" />
    <CheckPoint Sim_Time="503.5" NumVehicleInCity="300" />
    <CheckPoint Sim_Time="504.7" NumVehicleInCity="300" />
    <CheckPoint Sim_Time="505.4" NumVehicleInCity="299" />
    <CheckPoint Sim_Time="506.7" NumVehicleInCity="299" />
    <CheckPoint Sim_Time="511.4" NumVehicleInCity="303" />
    <CheckPoint Sim_Time="511.7" NumVehicleInCity="303" />
    <CheckPoint Sim_Time="513.4" NumVehicleInCity="305" />
    <CheckPoint Sim_Time="516.8" NumVehicleInCity="305" />
    <CheckPoint Sim_Time="517.2" NumVehicleInCity="305" />
    <CheckPoint Sim_Time="519.8" NumVehicleInCity="307" />
    <CheckPoint Sim_Time="519.9" NumVehicleInCity="306" />
    <CheckPoint Sim_Time="521.9" NumVehicleInCity="306" />
    <CheckPoint Sim_Time="522.5" NumVehicleInCity="305" />
    <CheckPoint Sim_Time="533.1" NumVehicleInCity="315" />
    <CheckPoint Sim_Time="533.6" NumVehicleInCity="315" />
    <CheckPoint Sim_Time="533.6" NumVehicleInCity="314" />
    <CheckPoint Sim_Time="533.8" NumVehicleInCity="313" />
    <CheckPoint Sim_Time="534.5" NumVehicleInCity="312" />
    <CheckPoint Sim_Time="535.8" NumVehicleInCity="312" />
    <CheckPoint Sim_Time="536.4" NumVehicleInCity="313" />
    <CheckPoint Sim_Time="536.6" NumVehicleInCity="312" />
    <CheckPoint Sim_Time="536.7" NumVehicleInCity="312" />
    <CheckPoint Sim_Time="536.7" NumVehicleInCity="311" />
    <CheckPoint Sim_Time="537.6" NumVehicleInCity="310" />
    <CheckPoint Sim_Time="538.2" NumVehicleInCity="310" />
    <CheckPoint Sim_Time="539.5" NumVehicleInCity="309" />
    <CheckPoint Sim_Time="539.8" NumVehicleInCity="309" />
    <CheckPoint Sim_Time="539.9" NumVehicleInCity="308" />
    <CheckPoint Sim_Time="540.1" NumVehicleInCity="307" />
    <CheckPoint Sim_Time="541.8" NumVehicleInCity="308" />
    <CheckPoint Sim_Time="544.1" NumVehicleInCity="309" />
    <CheckPoint Sim_Time="544.9" NumVehicleInCity="309" />
    <CheckPoint Sim_Time="545.7" NumVehicleInCity="309" />
    <CheckPoint Sim_Time="547.1" NumVehicleInCity="310" />
    <CheckPoint Sim_Time="549.8" NumVehicleInCity="312" />
    <CheckPoint Sim_Time="550" NumVehicleInCity="311" />
    <CheckPoint Sim_Time="551.9" NumVehicleInCity="313" />
    <CheckPoint Sim_Time="554.3" NumVehicleInCity="315" />
    <CheckPoint Sim_Time="556.7" NumVehicleInCity="316" />
    <CheckPoint Sim_Time="558" NumVehicleInCity="316" />
    <CheckPoint Sim_Time="561.7" NumVehicleInCity="320" />
    <CheckPoint Sim_Time="561.8" NumVehicleInCity="319" />
    <CheckPoint Sim_Time="563.8" NumVehicleInCity="319" />
    <CheckPoint Sim_Time="564.5" NumVehicleInCity="320" />
    <CheckPoint Sim_Time="566.1" NumVehicleInCity="320" />
    <CheckPoint Sim_Time="566.4" NumVehicleInCity="319" />
    <CheckPoint Sim_Time="570.5" NumVehicleInCity="321" />
    <CheckPoint Sim_Time="578.3" NumVehicleInCity="327" />
    <CheckPoint Sim_Time="578.5" NumVehicleInCity="326" />
    <CheckPoint Sim_Time="578.5" NumVehicleInCity="325" />
    <CheckPoint Sim_Time="579" NumVehicleInCity="325" />
    <CheckPoint Sim_Time="579.3" NumVehicleInCity="326" />
    <CheckPoint Sim_Time="579.5" NumVehicleInCity="325" />
    <CheckPoint Sim_Time="579.5" NumVehicleInCity="324" />
    <CheckPoint Sim_Time="580.5" NumVehicleInCity="324" />
    <CheckPoint Sim_Time="580.9" NumVehicleInCity="323" />
    <CheckPoint Sim_Time="582.7" NumVehicleInCity="324" />
    <CheckPoint Sim_Time="583.3" NumVehicleInCity="324" />
    <CheckPoint Sim_Time="585" NumVehicleInCity="323" />
    <CheckPoint Sim_Time="585.1" NumVehicleInCity="322" />
    <CheckPoint Sim_Time="585.2" NumVehicleInCity="321" />
    <CheckPoint Sim_Time="585.3" NumVehicleInCity="320" />
    <CheckPoint Sim_Time="586.4" NumVehicleInCity="321" />
    <CheckPoint Sim_Time="586.4" NumVehicleInCity="320" />
    <CheckPoint Sim_Time="588.7" NumVehicleInCity="323" />
    <CheckPoint Sim_Time="589.2" NumVehicleInCity="322" />
    <CheckPoint Sim_Time="590.3" NumVehicleInCity="321" />
    <CheckPoint Sim_Time="594.4" NumVehicleInCity="325" />
    <CheckPoint Sim_Time="594.4" NumVehicleInCity="324" />
    <CheckPoint Sim_Time="594.4" NumVehicleInCity="323" />
    <CheckPoint Sim_Time="598.7" NumVehicleInCity="325" />
    <CheckPoint Sim_Time="598.9" NumVehicleInCity="325" />
    <CheckPoint Sim_Time="601.9" NumVehicleInCity="326" />
    <CheckPoint Sim_Time="607.1" NumVehicleInCity="332" />
    <CheckPoint Sim_Time="609" NumVehicleInCity="331" />
    <CheckPoint Sim_Time="610" NumVehicleInCity="331" />
    <CheckPoint Sim_Time="610.3" NumVehicleInCity="330" />
    <CheckPoint Sim_Time="611.3" NumVehicleInCity="329" />
    <CheckPoint Sim_Time="612.2" NumVehicleInCity="330" />
    <CheckPoint Sim_Time="622.4" NumVehicleInCity="338" />
    <CheckPoint Sim_Time="622.9" NumVehicleInCity="338" />
    <CheckPoint Sim_Time="623.1" NumVehicleInCity="337" />
    <CheckPoint Sim_Time="623.2" NumVehicleInCity="336" />
    <CheckPoint Sim_Time="624.4" NumVehicleInCity="336" />
    <CheckPoint Sim_Time="624.5" NumVehicleInCity="336" />
    <CheckPoint Sim_Time="624.6" NumVehicleInCity="335" />
    <CheckPoint Sim_Time="624.6" NumVehicleInCity="334" />
    <CheckPoint Sim_Time="625.5" NumVehicleInCity="334" />
    <CheckPoint Sim_Time="626.4" NumVehicleInCity="334" />
    <CheckPoint Sim_Time="627.2" NumVehicleInCity="333" />
    <CheckPoint Sim_Time="627.2" NumVehicleInCity="332" />
    <CheckPoint Sim_Time="628.5" NumVehicleInCity="333" />
    <CheckPoint Sim_Time="628.6" NumVehicleInCity="332" />
    <CheckPoint Sim_Time="628.9" NumVehicleInCity="331" />
    <CheckPoint Sim_Time="629.7" NumVehicleInCity="331" />
    <CheckPoint Sim_Time="630.7" NumVehicleInCity="332" />
    <CheckPoint Sim_Time="631.4" NumVehicleInCity="332" />
    <CheckPoint Sim_Time="632" NumVehicleInCity="331" />
    <CheckPoint Sim_Time="633.4" NumVehicleInCity="332" />
    <CheckPoint Sim_Time="634.1" NumVehicleInCity="332" />
    <CheckPoint Sim_Time="636.6" NumVehicleInCity="335" />
    <CheckPoint Sim_Time="639.2" NumVehicleInCity="335" />
    <CheckPoint Sim_Time="640.5" NumVehicleInCity="336" />
    <CheckPoint Sim_Time="640.6" NumVehicleInCity="335" />
    <CheckPoint Sim_Time="642.6" NumVehicleInCity="335" />
    <CheckPoint Sim_Time="642.9" NumVehicleInCity="335" />
    <CheckPoint Sim_Time="644" NumVehicleInCity="335" />
    <CheckPoint Sim_Time="646.4" NumVehicleInCity="335" />
    <CheckPoint Sim_Time="648" NumVehicleInCity="336" />
    <CheckPoint Sim_Time="651.5" NumVehicleInCity="338" />
    <CheckPoint Sim_Time="651.7" NumVehicleInCity="337" />
    <CheckPoint Sim_Time="653.2" NumVehicleInCity="338" />
    <CheckPoint Sim_Time="653.6" NumVehicleInCity="337" />
    <CheckPoint Sim_Time="654.1" NumVehicleInCity="336" />
    <CheckPoint Sim_Time="654.4" NumVehicleInCity="335" />
    <CheckPoint Sim_Time="655.8" NumVehicleInCity="336" />
    <CheckPoint Sim_Time="658.7" NumVehicleInCity="337" />
    <CheckPoint Sim_Time="663.2" NumVehicleInCity="343" />
    <CheckPoint Sim_Time="668.5" NumVehicleInCity="345" />
    <CheckPoint Sim_Time="668.5" NumVehicleInCity="344" />
    <CheckPoint Sim_Time="668.5" NumVehicleInCity="343" />
    <CheckPoint Sim_Time="668.7" NumVehicleInCity="343" />
    <CheckPoint Sim_Time="668.7" NumVehicleInCity="342" />
    <CheckPoint Sim_Time="669" NumVehicleInCity="342" />
    <CheckPoint Sim_Time="670.2" NumVehicleInCity="342" />
    <CheckPoint Sim_Time="670.3" NumVehicleInCity="341" />
    <CheckPoint Sim_Time="670.7" NumVehicleInCity="340" />
    <CheckPoint Sim_Time="670.8" NumVehicleInCity="339" />
    <CheckPoint Sim_Time="671.1" NumVehicleInCity="339" />
    <CheckPoint Sim_Time="671.7" NumVehicleInCity="339" />
    <CheckPoint Sim_Time="672.7" NumVehicleInCity="340" />
    <CheckPoint Sim_Time="672.8" NumVehicleInCity="339" />
    <CheckPoint Sim_Time="672.9" NumVehicleInCity="338" />
    <CheckPoint Sim_Time="674" NumVehicleInCity="337" />
    <CheckPoint Sim_Time="674.7" NumVehicleInCity="336" />
    <CheckPoint Sim_Time="676.4" NumVehicleInCity="338" />
    <CheckPoint Sim_Time="677.2" NumVehicleInCity="339" />
    <CheckPoint Sim_Time="682.4" NumVehicleInCity="342" />
    <CheckPoint Sim_Time="683.6" NumVehicleInCity="341" />
    <CheckPoint Sim_Time="684.8" NumVehicleInCity="341" />
    <CheckPoint Sim_Time="686.4" NumVehicleInCity="341" />
    <CheckPoint Sim_Time="688.9" NumVehicleInCity="342" />
    <CheckPoint Sim_Time="693.4" NumVehicleInCity="345" />
    <CheckPoint Sim_Time="698" NumVehicleInCity="349" />
    <CheckPoint Sim_Time="699.1" NumVehicleInCity="350" />
    <CheckPoint Sim_Time="700.7" NumVehicleInCity="350" />
    <CheckPoint Sim_Time="701.6" NumVehicleInCity="351" />
    <CheckPoint Sim_Time="712.6" NumVehicleInCity="361" />
    <CheckPoint Sim_Time="713.2" NumVehicleInCity="362" />
    <CheckPoint Sim_Time="713.3" NumVehicleInCity="361" />
    <CheckPoint Sim_Time="713.4" NumVehicleInCity="360" />
    <CheckPoint Sim_Time="714.1" NumVehicleInCity="361" />
    <CheckPoint Sim_Time="715.1" NumVehicleInCity="361" />
    <CheckPoint Sim_Time="715.2" NumVehicleInCity="360" />
    <CheckPoint Sim_Time="715.7" NumVehicleInCity="359" />
    <CheckPoint Sim_Time="715.8" NumVehicleInCity="358" />
    <CheckPoint Sim_Time="717.2" NumVehicleInCity="357" />
    <CheckPoint Sim_Time="718.4" NumVehicleInCity="359" />
    <CheckPoint Sim_Time="719" NumVehicleInCity="359" />
    <CheckPoint Sim_Time="719.2" NumVehicleInCity="360" />
    <CheckPoint Sim_Time="719.7" NumVehicleInCity="359" />
    <CheckPoint Sim_Time="720.9" NumVehicleInCity="358" />
    <CheckPoint Sim_Time="721.4" NumVehicleInCity="357" />
    <CheckPoint Sim_Time="721.5" NumVehicleInCity="356" />
    <CheckPoint Sim_Time="721.6" NumVehicleInCity="355" />
    <CheckPoint Sim_Time="721.8" NumVehicleInCity="354" />
    <CheckPoint Sim_Time="723.4" NumVehicleInCity="354" />
    <CheckPoint Sim_Time="727" NumVehicleInCity="356" />
    <CheckPoint Sim_Time="727.1" NumVehicleInCity="355" />
    <CheckPoint Sim_Time="727.5" NumVehicleInCity="354" />
    <CheckPoint Sim_Time="728.3" NumVehicleInCity="354" />
    <CheckPoint Sim_Time="728.6" NumVehicleInCity="353" />
    <CheckPoint Sim_Time="729.1" NumVehicleInCity="354" />
    <CheckPoint Sim_Time="730.1" NumVehicleInCity="353" />
    <CheckPoint Sim_Time="733" NumVehicleInCity="353" />
    <CheckPoint Sim_Time="733.6" NumVehicleInCity="353" />
    <CheckPoint Sim_Time="733.7" NumVehicleInCity="352" />
    <CheckPoint Sim_Time="735.1" NumVehicleInCity="353" />
    <CheckPoint Sim_Time="735.6" NumVehicleInCity="353" />
    <CheckPoint Sim_Time="737.8" NumVehicleInCity="353" />
    <CheckPoint Sim_Time="738.1" NumVehicleInCity="352" />
    <CheckPoint Sim_Time="739" NumVehicleInCity="352" />
    <CheckPoint Sim_Time="741" NumVehicleInCity="354" />
    <CheckPoint Sim_Time="743.1" NumVehicleInCity="355" />
    <CheckPoint Sim_Time="743.3" NumVehicleInCity="354" />
    <CheckPoint Sim_Time="743.8" NumVehicleInCity="353" />
    <CheckPoint Sim_Time="744" NumVehicleInCity="352" />
    <CheckPoint Sim_Time="746.4" NumVehicleInCity="355" />
    <CheckPoint Sim_Time="758.2" NumVehicleInCity="366" />
    <CheckPoint Sim_Time="758.2" NumVehicleInCity="365" />
    <CheckPoint Sim_Time="758.3" NumVehicleInCity="364" />
    <CheckPoint Sim_Time="758.3" NumVehicleInCity="363" />
    <CheckPoint Sim_Time="758.4" NumVehicleInCity="363" />
    <CheckPoint Sim_Time="759.1" NumVehicleInCity="362" />
    <CheckPoint Sim_Time="759.3" NumVehicleInCity="361" />
    <CheckPoint Sim_Time="760.4" NumVehicleInCity="361" />
    <CheckPoint Sim_Time="760.5" NumVehicleInCity="360" />
    <CheckPoint Sim_Time="760.9" NumVehicleInCity="359" />
    <CheckPoint Sim_Time="761.1" NumVehicleInCity="359" />
    <CheckPoint Sim_Time="761.2" NumVehicleInCity="358" />
    <CheckPoint Sim_Time="761.5" NumVehicleInCity="357" />
    <CheckPoint Sim_Time="762.3" NumVehicleInCity="357" />
    <CheckPoint Sim_Time="763.3" NumVehicleInCity="358" />
    <CheckPoint Sim_Time="764.8" NumVehicleInCity="360" />
    <CheckPoint Sim_Time="765.1" NumVehicleInCity="360" />
    <CheckPoint Sim_Time="767.1" NumVehicleInCity="360" />
    <CheckPoint Sim_Time="767.3" NumVehicleInCity="359" />
    <CheckPoint Sim_Time="769" NumVehicleInCity="360" />
    <CheckPoint Sim_Time="771.7" NumVehicleInCity="363" />
    <CheckPoint Sim_Time="775.2" NumVehicleInCity="363" />
    <CheckPoint Sim_Time="776.1" NumVehicleInCity="363" />
    <CheckPoint Sim_Time="776.7" NumVehicleInCity="364" />
    <CheckPoint Sim_Time="777.3" NumVehicleInCity="365" />
    <CheckPoint Sim_Time="777.6" NumVehicleInCity="364" />
    <CheckPoint Sim_Time="779" NumVehicleInCity="363" />
    <CheckPoint Sim_Time="780.9" NumVehicleInCity="363" />
    <CheckPoint Sim_Time="788.9" NumVehicleInCity="371" />
    <CheckPoint Sim_Time="789.5" NumVehicleInCity="370" />
    <CheckPoint Sim_Time="791.4" NumVehicleInCity="371" />
    <CheckPoint Sim_Time="802.8" NumVehicleInCity="382" />
    <CheckPoint Sim_Time="802.8" NumVehicleInCity="381" />
    <CheckPoint Sim_Time="802.8" NumVehicleInCity="380" />
    <CheckPoint Sim_Time="802.9" NumVehicleInCity="379" />
    <CheckPoint Sim_Time="803.3" NumVehicleInCity="379" />
    <CheckPoint Sim_Time="803.3" NumVehicleInCity="378" />
    <CheckPoint Sim_Time="803.4" NumVehicleInCity="377" />
    <CheckPoint Sim_Time="804.2" NumVehicleInCity="377" />
    <CheckPoint Sim_Time="804.8" NumVehicleInCity="376" />
    <CheckPoint Sim_Time="805.2" NumVehicleInCity="375" />
    <CheckPoint Sim_Time="805.5" NumVehicleInCity="375" />
    <CheckPoint Sim_Time="805.9" NumVehicleInCity="374" />
    <CheckPoint Sim_Time="806.1" NumVehicleInCity="374" />
    <CheckPoint Sim_Time="807.1" NumVehicleInCity="374" />
    <CheckPoint Sim_Time="808.4" NumVehicleInCity="374" />
    <CheckPoint Sim_Time="809.9" NumVehicleInCity="374" />
    <CheckPoint Sim_Time="810.4" NumVehicleInCity="373" />
    <CheckPoint Sim_Time="810.7" NumVehicleInCity="372" />
    <CheckPoint Sim_Time="812.4" NumVehicleInCity="372" />
    <CheckPoint Sim_Time="813" NumVehicleInCity="372" />
    <CheckPoint Sim_Time="813.2" NumVehicleInCity="372" />
    <CheckPoint Sim_Time="814.8" NumVehicleInCity="374" />
    <CheckPoint Sim_Time="815.3" NumVehicleInCity="373" />
    <CheckPoint Sim_Time="815.3" NumVehicleInCity="372" />
    <CheckPoint Sim_Time="816.1" NumVehicleInCity="371" />
    <CheckPoint Sim_Time="816.6" NumVehicleInCity="370" />
    <CheckPoint Sim_Time="817.4" NumVehicleInCity="371" />
    <CheckPoint Sim_Time="819.8" NumVehicleInCity="371" />
    <CheckPoint Sim_Time="821" NumVehicleInCity="372" />
    <CheckPoint Sim_Time="823.1" NumVehicleInCity="373" />
    <CheckPoint Sim_Time="823.1" NumVehicleInCity="372" />
    <CheckPoint Sim_Time="825.3" NumVehicleInCity="373" />
    <CheckPoint Sim_Time="827" NumVehicleInCity="374" />
    <CheckPoint Sim_Time="827.4" NumVehicleInCity="374" />
    <CheckPoint Sim_Time="827.7" NumVehicleInCity="373" />
    <CheckPoint Sim_Time="828" NumVehicleInCity="372" />
    <CheckPoint Sim_Time="829.8" NumVehicleInCity="373" />
    <CheckPoint Sim_Time="830.3" NumVehicleInCity="373" />
    <CheckPoint Sim_Time="831.1" NumVehicleInCity="373" />
    <CheckPoint Sim_Time="832.8" NumVehicleInCity="373" />
    <CheckPoint Sim_Time="832.9" NumVehicleInCity="372" />
    <CheckPoint Sim_Time="834.1" NumVehicleInCity="372" />
    <CheckPoint Sim_Time="836.7" NumVehicleInCity="373" />
    <CheckPoint Sim_Time="848.1" NumVehicleInCity="381" />
    <CheckPoint Sim_Time="848.1" NumVehicleInCity="380" />
    <CheckPoint Sim_Time="848.6" NumVehicleInCity="380" />
    <CheckPoint Sim_Time="848.7" NumVehicleInCity="379" />
    <CheckPoint Sim_Time="849.4" NumVehicleInCity="379" />
    <CheckPoint Sim_Time="849.4" NumVehicleInCity="378" />
    <CheckPoint Sim_Time="850.8" NumVehicleInCity="379" />
    <CheckPoint Sim_Time="850.8" NumVehicleInCity="378" />
    <CheckPoint Sim_Time="851.1" NumVehicleInCity="377" />
    <CheckPoint Sim_Time="851.9" NumVehicleInCity="376" />
    <CheckPoint Sim_Time="853.1" NumVehicleInCity="375" />
    <CheckPoint Sim_Time="853.2" NumVehicleInCity="374" />
    <CheckPoint Sim_Time="853.8" NumVehicleInCity="375" />
    <CheckPoint Sim_Time="854" NumVehicleInCity="374" />
    <CheckPoint Sim_Time="855.5" NumVehicleInCity="376" />
    <CheckPoint Sim_Time="856" NumVehicleInCity="375" />
    <CheckPoint Sim_Time="857.7" NumVehicleInCity="376" />
    <CheckPoint Sim_Time="857.8" NumVehicleInCity="375" />
    <CheckPoint Sim_Time="859.3" NumVehicleInCity="374" />
    <CheckPoint Sim_Time="859.6" NumVehicleInCity="373" />
    <CheckPoint Sim_Time="862.1" NumVehicleInCity="376" />
    <CheckPoint Sim_Time="862.3" NumVehicleInCity="375" />
    <CheckPoint Sim_Time="863.5" NumVehicleInCity="375" />
    <CheckPoint Sim_Time="864.8" NumVehicleInCity="374" />
    <CheckPoint Sim_Time="865.6" NumVehicleInCity="374" />
    <CheckPoint Sim_Time="866.8" NumVehicleInCity="376" />
    <CheckPoint Sim_Time="868.5" NumVehicleInCity="376" />
    <CheckPoint Sim_Time="869.2" NumVehicleInCity="375" />
    <CheckPoint Sim_Time="871.5" NumVehicleInCity="376" />
    <CheckPoint Sim_Time="873.9" NumVehicleInCity="378" />
    <CheckPoint Sim_Time="874.6" NumVehicleInCity="378" />
    <CheckPoint Sim_Time="876" NumVehicleInCity="378" />
    <CheckPoint Sim_Time="877.1" NumVehicleInCity="378" />
    <CheckPoint Sim_Time="877.8" NumVehicleInCity="377" />
    <CheckPoint Sim_Time="878.4" NumVehicleInCity="378" />
    <CheckPoint Sim_Time="878.6" NumVehicleInCity="377" />
    <CheckPoint Sim_Time="879" NumVehicleInCity="376" />
    <CheckPoint Sim_Time="879.6" NumVehicleInCity="376" />
    <CheckPoint Sim_Time="880.3" NumVehicleInCity="376" />
    <CheckPoint Sim_Time="880.5" NumVehicleInCity="375" />
    <CheckPoint Sim_Time="893.5" NumVehicleInCity="389" />
    <CheckPoint Sim_Time="894.1" NumVehicleInCity="388" />
    <CheckPoint Sim_Time="894.2" NumVehicleInCity="387" />
    <CheckPoint Sim_Time="894.2" NumVehicleInCity="386" />
    <CheckPoint Sim_Time="894.3" NumVehicleInCity="385" />
    <CheckPoint Sim_Time="894.4" NumVehicleInCity="385" />
    <CheckPoint Sim_Time="894.6" NumVehicleInCity="384" />
    <CheckPoint Sim_Time="895.9" NumVehicleInCity="385" />
    <CheckPoint Sim_Time="895.9" NumVehicleInCity="384" />
    <CheckPoint Sim_Time="897" NumVehicleInCity="383" />
    <CheckPoint Sim_Time="897.9" NumVehicleInCity="382" />
    <CheckPoint Sim_Time="897.9" NumVehicleInCity="381" />
    <CheckPoint Sim_Time="898" NumVehicleInCity="380" />
    <CheckPoint Sim_Time="898.1" NumVehicleInCity="379" />
    <CheckPoint Sim_Time="900.2" NumVehicleInCity="380" />
    <CheckPoint Sim_Time="900.3" NumVehicleInCity="379" />
    <CheckPoint Sim_Time="900.6" NumVehicleInCity="378" />
    <CheckPoint Sim_Time="902.6" NumVehicleInCity="380" />
    <CheckPoint Sim_Time="904.6" NumVehicleInCity="379" />
    <CheckPoint Sim_Time="904.8" NumVehicleInCity="378" />
    <CheckPoint Sim_Time="905.8" NumVehicleInCity="377" />
    <CheckPoint Sim_Time="905.9" NumVehicleInCity="376" />
    <CheckPoint Sim_Time="906.4" NumVehicleInCity="376" />
    <CheckPoint Sim_Time="907.3" NumVehicleInCity="376" />
    <CheckPoint Sim_Time="910.8" NumVehicleInCity="375" />
    <CheckPoint Sim_Time="914" NumVehicleInCity="374" />
    <CheckPoint Sim_Time="914.1" NumVehicleInCity="373" />
    <CheckPoint Sim_Time="916.6" NumVehicleInCity="372" />
    <CheckPoint Sim_Time="917" NumVehicleInCity="371" />
    <CheckPoint Sim_Time="917.7" NumVehicleInCity="370" />
    <CheckPoint Sim_Time="920.7" NumVehicleInCity="369" />
    <CheckPoint Sim_Time="922.7" NumVehicleInCity="368" />
    <CheckPoint Sim_Time="924.8" NumVehicleInCity="367" />
    <CheckPoint Sim_Time="925" NumVehicleInCity="366" />
    <CheckPoint Sim_Time="927" NumVehicleInCity="365" />
    <CheckPoint Sim_Time="936.6" NumVehicleInCity="364" />
    <CheckPoint Sim_Time="937.3" NumVehicleInCity="363" />
    <CheckPoint Sim_Time="938.1" NumVehicleInCity="362" />
    <CheckPoint Sim_Time="938.4" NumVehicleInCity="361" />
    <CheckPoint Sim_Time="939.4" NumVehicleInCity="360" />
    <CheckPoint Sim_Time="939.5" NumVehicleInCity="359" />
    <CheckPoint Sim_Time="939.6" NumVehicleInCity="358" />
    <CheckPoint Sim_Time="940.1" NumVehicleInCity="357" />
    <CheckPoint Sim_Time="940.6" NumVehicleInCity="356" />
    <CheckPoint Sim_Time="941" NumVehicleInCity="355" />
    <CheckPoint Sim_Time="941.6" NumVehicleInCity="354" />
    <CheckPoint Sim_Time="945.9" NumVehicleInCity="353" />
    <CheckPoint Sim_Time="946.9" NumVehicleInCity="352" />
    <CheckPoint Sim_Time="947" NumVehicleInCity="351" />
    <CheckPoint Sim_Time="947.3" NumVehicleInCity="350" />
    <CheckPoint Sim_Time="948.7" NumVehicleInCity="349" />
    <CheckPoint Sim_Time="949.7" NumVehicleInCity="348" />
    <CheckPoint Sim_Time="950" NumVehicleInCity="347" />
    <CheckPoint Sim_Time="951.3" NumVehicleInCity="346" />
    <CheckPoint Sim_Time="951.7" NumVehicleInCity="345" />
    <CheckPoint Sim_Time="958.5" NumVehicleInCity="344" />
    <CheckPoint Sim_Time="960.3" NumVehicleInCity="343" />
    <CheckPoint Sim_Time="961.3" NumVehicleInCity="342" />
    <CheckPoint Sim_Time="962.1" NumVehicleInCity="341" />
    <CheckPoint Sim_Time="963.9" NumVehicleInCity="340" />
    <CheckPoint Sim_Time="964.5" NumVehicleInCity="339" />
    <CheckPoint Sim_Time="967.5" NumVehicleInCity="338" />
    <CheckPoint Sim_Time="968.9" NumVehicleInCity="337" />
    <CheckPoint Sim_Time="969.6" NumVehicleInCity="336" />
    <CheckPoint Sim_Time="970.3" NumVehicleInCity="335" />
    <CheckPoint Sim_Time="971.1" NumVehicleInCity="334" />
    <CheckPoint Sim_Time="971.5" NumVehicleInCity="333" />
    <CheckPoint Sim_Time="972.3" NumVehicleInCity="332" />
    <CheckPoint Sim_Time="973.6" NumVehicleInCity="331" />
    <CheckPoint Sim_Time="983.2" NumVehicleInCity="330" />
    <CheckPoint Sim_Time="983.4" NumVehicleInCity="329" />
    <CheckPoint Sim_Time="983.5" NumVehicleInCity="328" />
    <CheckPoint Sim_Time="984.2" NumVehicleInCity="327" />
    <CheckPoint Sim_Time="984.3" NumVehicleInCity="326" />
    <CheckPoint Sim_Time="984.4" NumVehicleInCity="325" />
    <CheckPoint Sim_Time="985.5" NumVehicleInCity="324" />
    <CheckPoint Sim_Time="985.7" NumVehicleInCity="323" />
    <CheckPoint Sim_Time="985.8" NumVehicleInCity="322" />
    <CheckPoint Sim_Time="986.3" NumVehicleInCity="321" />
    <CheckPoint Sim_Time="986.5" NumVehicleInCity="320" />
    <CheckPoint Sim_Time="987.6" NumVehicleInCity="319" />
    <CheckPoint Sim_Time="987.8" NumVehicleInCity="318" />
    <CheckPoint Sim_Time="988.8" NumVehicleInCity="317" />
    <CheckPoint Sim_Time="989.1" NumVehicleInCity="316" />
    <CheckPoint Sim_Time="989.1" NumVehicleInCity="315" />
    <CheckPoint Sim_Time="990" NumVehicleInCity="314" />
    <CheckPoint Sim_Time="990" NumVehicleInCity="313" />
    <CheckPoint Sim_Time="990.4" NumVehicleInCity="312" />
    <CheckPoint Sim_Time="991.3" NumVehicleInCity="311" />
    <CheckPoint Sim_Time="996.1" NumVehicleInCity="310" />
    <CheckPoint Sim_Time="996.1" NumVehicleInCity="309" />
    <CheckPoint Sim_Time="998.1" NumVehicleInCity="308" />
    <CheckPoint Sim_Time="999.8" NumVehicleInCity="307" />
    <CheckPoint Sim_Time="1001.4" NumVehicleInCity="306" />
    <CheckPoint Sim_Time="1002.8" NumVehicleInCity="305" />
    <CheckPoint Sim_Time="1002.9" NumVehicleInCity="304" />
    <CheckPoint Sim_Time="1003.9" NumVehicleInCity="303" />
    <CheckPoint Sim_Time="1007.1" NumVehicleInCity="302" />
    <CheckPoint Sim_Time="1007.3" NumVehicleInCity="301" />
    <CheckPoint Sim_Time="1007.4" NumVehicleInCity="300" />
    <CheckPoint Sim_Time="1011.6" NumVehicleInCity="299" />
    <CheckPoint Sim_Time="1012" NumVehicleInCity="298" />
    <CheckPoint Sim_Time="1012.2" NumVehicleInCity="297" />
    <CheckPoint Sim_Time="1013" NumVehicleInCity="296" />
    <CheckPoint Sim_Time="1013.8" NumVehicleInCity="295" />
    <CheckPoint Sim_Time="1015.1" NumVehicleInCity="294" />
    <CheckPoint Sim_Time="1015.1" NumVehicleInCity="293" />
    <CheckPoint Sim_Time="1015.8" NumVehicleInCity="292" />
    <CheckPoint Sim_Time="1027.5" NumVehicleInCity="291" />
    <CheckPoint Sim_Time="1027.5" NumVehicleInCity="290" />
    <CheckPoint Sim_Time="1028" NumVehicleInCity="289" />
    <CheckPoint Sim_Time="1028.1" NumVehicleInCity="288" />
    <CheckPoint Sim_Time="1028.1" NumVehicleInCity="287" />
    <CheckPoint Sim_Time="1029.5" NumVehicleInCity="286" />
    <CheckPoint Sim_Time="1029.7" NumVehicleInCity="285" />
    <CheckPoint Sim_Time="1030.1" NumVehicleInCity="284" />
    <CheckPoint Sim_Time="1030.3" NumVehicleInCity="283" />
    <CheckPoint Sim_Time="1031.2" NumVehicleInCity="282" />
    <CheckPoint Sim_Time="1031.9" NumVehicleInCity="281" />
    <CheckPoint Sim_Time="1033.1" NumVehicleInCity="280" />
    <CheckPoint Sim_Time="1036.5" NumVehicleInCity="279" />
    <CheckPoint Sim_Time="1036.6" NumVehicleInCity="278" />
    <CheckPoint Sim_Time="1037.3" NumVehicleInCity="277" />
    <CheckPoint Sim_Time="1037.8" NumVehicleInCity="276" />
    <CheckPoint Sim_Time="1038.2" NumVehicleInCity="275" />
    <CheckPoint Sim_Time="1038.4" NumVehicleInCity="274" />
    <CheckPoint Sim_Time="1039.2" NumVehicleInCity="273" />
    <CheckPoint Sim_Time="1039.6" NumVehicleInCity="272" />
    <CheckPoint Sim_Time="1040.7" NumVehicleInCity="271" />
    <CheckPoint Sim_Time="1040.7" NumVehicleInCity="270" />
    <CheckPoint Sim_Time="1041.3" NumVehicleInCity="269" />
    <CheckPoint Sim_Time="1041.6" NumVehicleInCity="268" />
    <CheckPoint Sim_Time="1042" NumVehicleInCity="267" />
    <CheckPoint Sim_Time="1042.7" NumVehicleInCity="266" />
    <CheckPoint Sim_Time="1042.9" NumVehicleInCity="265" />
    <CheckPoint Sim_Time="1044.6" NumVehicleInCity="264" />
    <CheckPoint Sim_Time="1044.6" NumVehicleInCity="263" />
    <CheckPoint Sim_Time="1044.7" NumVehicleInCity="262" />
    <CheckPoint Sim_Time="1045.2" NumVehicleInCity="261" />
    <CheckPoint Sim_Time="1046.1" NumVehicleInCity="260" />
    <CheckPoint Sim_Time="1047.1" NumVehicleInCity="259" />
    <CheckPoint Sim_Time="1049.2" NumVehicleInCity="258" />
    <CheckPoint Sim_Time="1054.8" NumVehicleInCity="257" />
    <CheckPoint Sim_Time="1055.1" NumVehicleInCity="256" />
    <CheckPoint Sim_Time="1057.7" NumVehicleInCity="255" />
    <CheckPoint Sim_Time="1058.5" NumVehicleInCity="254" />
    <CheckPoint Sim_Time="1059.9" NumVehicleInCity="253" />
    <CheckPoint Sim_Time="1060.1" NumVehicleInCity="252" />
    <CheckPoint Sim_Time="1072.5" NumVehicleInCity="251" />
    <CheckPoint Sim_Time="1073.3" NumVehicleInCity="250" />
    <CheckPoint Sim_Time="1073.4" NumVehicleInCity="249" />
    <CheckPoint Sim_Time="1073.5" NumVehicleInCity="248" />
    <CheckPoint Sim_Time="1073.6" NumVehicleInCity="247" />
    <CheckPoint Sim_Time="1074.2" NumVehicleInCity="246" />
    <CheckPoint Sim_Time="1074.4" NumVehicleInCity="245" />
    <CheckPoint Sim_Time="1075.2" NumVehicleInCity="244" />
    <CheckPoint Sim_Time="1075.7" NumVehicleInCity="243" />
    <CheckPoint Sim_Time="1075.7" NumVehicleInCity="242" />
    <CheckPoint Sim_Time="1075.9" NumVehicleInCity="241" />
    <CheckPoint Sim_Time="1076.1" NumVehicleInCity="240" />
    <CheckPoint Sim_Time="1076.3" NumVehicleInCity="239" />
    <CheckPoint Sim_Time="1077.8" NumVehicleInCity="238" />
    <CheckPoint Sim_Time="1077.9" NumVehicleInCity="237" />
    <CheckPoint Sim_Time="1079.1" NumVehicleInCity="236" />
    <CheckPoint Sim_Time="1079.3" NumVehicleInCity="235" />
    <CheckPoint Sim_Time="1079.7" NumVehicleInCity="234" />
    <CheckPoint Sim_Time="1079.7" NumVehicleInCity="233" />
    <CheckPoint Sim_Time="1080.2" NumVehicleInCity="232" />
    <CheckPoint Sim_Time="1080.3" NumVehicleInCity="231" />
    <CheckPoint Sim_Time="1080.3" NumVehicleInCity="230" />
    <CheckPoint Sim_Time="1081.6" NumVehicleInCity="229" />
    <CheckPoint Sim_Time="1082.4" NumVehicleInCity="228" />
    <CheckPoint Sim_Time="1083.4" NumVehicleInCity="227" />
    <CheckPoint Sim_Time="1085.3" NumVehicleInCity="226" />
    <CheckPoint Sim_Time="1085.6" NumVehicleInCity="225" />
    <CheckPoint Sim_Time="1085.7" NumVehicleInCity="224" />
    <CheckPoint Sim_Time="1087.6" NumVehicleInCity="223" />
    <CheckPoint Sim_Time="1087.8" NumVehicleInCity="222" />
    <CheckPoint Sim_Time="1088.3" NumVehicleInCity="221" />
    <CheckPoint Sim_Time="1088.6" NumVehicleInCity="220" />
    <CheckPoint Sim_Time="1090" NumVehicleInCity="219" />
    <CheckPoint Sim_Time="1090.1" NumVehicleInCity="218" />
    <CheckPoint Sim_Time="1091.1" NumVehicleInCity="217" />
    <CheckPoint Sim_Time="1091.5" NumVehicleInCity="216" />
    <CheckPoint Sim_Time="1092.2" NumVehicleInCity="215" />
    <CheckPoint Sim_Time="1092.4" NumVehicleInCity="214" />
    <CheckPoint Sim_Time="1092.6" NumVehicleInCity="213" />
    <CheckPoint Sim_Time="1095.8" NumVehicleInCity="212" />
    <CheckPoint Sim_Time="1099.4" NumVehicleInCity="211" />
    <CheckPoint Sim_Time="1100" NumVehicleInCity="210" />
    <CheckPoint Sim_Time="1102.4" NumVehicleInCity="209" />
    <CheckPoint Sim_Time="1102.7" NumVehicleInCity="208" />
    <CheckPoint Sim_Time="1104.7" NumVehicleInCity="207" />
    <CheckPoint Sim_Time="1106.9" NumVehicleInCity="206" />
    <CheckPoint Sim_Time="1117.7" NumVehicleInCity="205" />
    <CheckPoint Sim_Time="1118.3" NumVehicleInCity="204" />
    <CheckPoint Sim_Time="1118.5" NumVehicleInCity="203" />
    <CheckPoint Sim_Time="1119.3" NumVehicleInCity="202" />
    <CheckPoint Sim_Time="1120.3" NumVehicleInCity="201" />
    <CheckPoint Sim_Time="1120.4" NumVehicleInCity="200" />
    <CheckPoint Sim_Time="1121" NumVehicleInCity="199" />
    <CheckPoint Sim_Time="1122.7" NumVehicleInCity="198" />
    <CheckPoint Sim_Time="1123.3" NumVehicleInCity="197" />
    <CheckPoint Sim_Time="1126" NumVehicleInCity="196" />
    <CheckPoint Sim_Time="1127.1" NumVehicleInCity="195" />
    <CheckPoint Sim_Time="1129.2" NumVehicleInCity="194" />
    <CheckPoint Sim_Time="1130.6" NumVehicleInCity="193" />
    <CheckPoint Sim_Time="1130.9" NumVehicleInCity="192" />
    <CheckPoint Sim_Time="1131.5" NumVehicleInCity="191" />
    <CheckPoint Sim_Time="1132.2" NumVehicleInCity="190" />
    <CheckPoint Sim_Time="1132.6" NumVehicleInCity="189" />
    <CheckPoint Sim_Time="1134.6" NumVehicleInCity="188" />
    <CheckPoint Sim_Time="1135" NumVehicleInCity="187" />
    <CheckPoint Sim_Time="1136.7" NumVehicleInCity="186" />
    <CheckPoint Sim_Time="1137" NumVehicleInCity="185" />
    <CheckPoint Sim_Time="1138.4" NumVehicleInCity="184" />
    <CheckPoint Sim_Time="1139.4" NumVehicleInCity="183" />
    <CheckPoint Sim_Time="1139.5" NumVehicleInCity="182" />
    <CheckPoint Sim_Time="1141.4" NumVehicleInCity="181" />
    <CheckPoint Sim_Time="1146.9" NumVehicleInCity="180" />
    <CheckPoint Sim_Time="1149.1" NumVehicleInCity="179" />
    <CheckPoint Sim_Time="1149.3" NumVehicleInCity="178" />
    <CheckPoint Sim_Time="1150.5" NumVehicleInCity="177" />
    <CheckPoint Sim_Time="1152.4" NumVehicleInCity="176" />
    <CheckPoint Sim_Time="1152.8" NumVehicleInCity="175" />
    <CheckPoint Sim_Time="1153.6" NumVehicleInCity="174" />
    <CheckPoint Sim_Time="1162.3" NumVehicleInCity="173" />
    <CheckPoint Sim_Time="1163.1" NumVehicleInCity="172" />
    <CheckPoint Sim_Time="1163.2" NumVehicleInCity="171" />
    <CheckPoint Sim_Time="1163.7" NumVehicleInCity="170" />
    <CheckPoint Sim_Time="1164" NumVehicleInCity="169" />
    <CheckPoint Sim_Time="1164.3" NumVehicleInCity="168" />
    <CheckPoint Sim_Time="1164.4" NumVehicleInCity="167" />
    <CheckPoint Sim_Time="1165.7" NumVehicleInCity="166" />
    <CheckPoint Sim_Time="1165.8" NumVehicleInCity="165" />
    <CheckPoint Sim_Time="1166.2" NumVehicleInCity="164" />
    <CheckPoint Sim_Time="1166.4" NumVehicleInCity="163" />
    <CheckPoint Sim_Time="1166.5" NumVehicleInCity="162" />
    <CheckPoint Sim_Time="1166.7" NumVehicleInCity="161" />
    <CheckPoint Sim_Time="1167.8" NumVehicleInCity="160" />
    <CheckPoint Sim_Time="1168.1" NumVehicleInCity="159" />
    <CheckPoint Sim_Time="1168.4" NumVehicleInCity="158" />
    <CheckPoint Sim_Time="1169.4" NumVehicleInCity="157" />
    <CheckPoint Sim_Time="1170.2" NumVehicleInCity="156" />
    <CheckPoint Sim_Time="1172.2" NumVehicleInCity="155" />
    <CheckPoint Sim_Time="1175.7" NumVehicleInCity="154" />
    <CheckPoint Sim_Time="1176.5" NumVehicleInCity="153" />
    <CheckPoint Sim_Time="1183.7" NumVehicleInCity="152" />
    <CheckPoint Sim_Time="1190.3" NumVehicleInCity="151" />
    <CheckPoint Sim_Time="1190.5" NumVehicleInCity="150" />
    <CheckPoint Sim_Time="1208.3" NumVehicleInCity="149" />
    <CheckPoint Sim_Time="1208.4" NumVehicleInCity="148" />
    <CheckPoint Sim_Time="1208.7" NumVehicleInCity="147" />
    <CheckPoint Sim_Time="1209.2" NumVehicleInCity="146" />
    <CheckPoint Sim_Time="1209.3" NumVehicleInCity="145" />
    <CheckPoint Sim_Time="1209.5" NumVehicleInCity="144" />
    <CheckPoint Sim_Time="1210.5" NumVehicleInCity="143" />
    <CheckPoint Sim_Time="1210.9" NumVehicleInCity="142" />
    <CheckPoint Sim_Time="1210.9" NumVehicleInCity="141" />
    <CheckPoint Sim_Time="1211.4" NumVehicleInCity="140" />
    <CheckPoint Sim_Time="1212.9" NumVehicleInCity="139" />
    <CheckPoint Sim_Time="1213.9" NumVehicleInCity="138" />
    <CheckPoint Sim_Time="1215" NumVehicleInCity="137" />
    <CheckPoint Sim_Time="1216" NumVehicleInCity="136" />
    <CheckPoint Sim_Time="1216.3" NumVehicleInCity="135" />
    <CheckPoint Sim_Time="1217.7" NumVehicleInCity="134" />
    <CheckPoint Sim_Time="1219.4" NumVehicleInCity="133" />
    <CheckPoint Sim_Time="1219.4" NumVehicleInCity="132" />
    <CheckPoint Sim_Time="1221.2" NumVehicleInCity="131" />
    <CheckPoint Sim_Time="1221.4" NumVehicleInCity="130" />
    <CheckPoint Sim_Time="1221.5" NumVehicleInCity="129" />
    <CheckPoint Sim_Time="1222.6" NumVehicleInCity="128" />
    <CheckPoint Sim_Time="1228.1" NumVehicleInCity="127" />
    <CheckPoint Sim_Time="1230" NumVehicleInCity="126" />
    <CheckPoint Sim_Time="1231.1" NumVehicleInCity="125" />
    <CheckPoint Sim_Time="1232.5" NumVehicleInCity="124" />
    <CheckPoint Sim_Time="1232.7" NumVehicleInCity="123" />
    <CheckPoint Sim_Time="1235.1" NumVehicleInCity="122" />
    <CheckPoint Sim_Time="1236.3" NumVehicleInCity="121" />
    <CheckPoint Sim_Time="1240" NumVehicleInCity="120" />
    <CheckPoint Sim_Time="1242.1" NumVehicleInCity="119" />
    <CheckPoint Sim_Time="1253.6" NumVehicleInCity="118" />
    <CheckPoint Sim_Time="1253.9" NumVehicleInCity="117" />
    <CheckPoint Sim_Time="1254" NumVehicleInCity="116" />
    <CheckPoint Sim_Time="1254.5" NumVehicleInCity="115" />
    <CheckPoint Sim_Time="1256" NumVehicleInCity="114" />
    <CheckPoint Sim_Time="1256.7" NumVehicleInCity="113" />
    <CheckPoint Sim_Time="1263.3" NumVehicleInCity="112" />
    <CheckPoint Sim_Time="1280.7" NumVehicleInCity="111" />
    <CheckPoint Sim_Time="1283" NumVehicleInCity="110" />
    <CheckPoint Sim_Time="1283.1" NumVehicleInCity="109" />
    <CheckPoint Sim_Time="1298.3" NumVehicleInCity="108" />
    <CheckPoint Sim_Time="1298.4" NumVehicleInCity="107" />
    <CheckPoint Sim_Time="1298.6" NumVehicleInCity="106" />
    <CheckPoint Sim_Time="1298.8" NumVehicleInCity="105" />
    <CheckPoint Sim_Time="1299.2" NumVehicleInCity="104" />
    <CheckPoint Sim_Time="1300.3" NumVehicleInCity="103" />
    <CheckPoint Sim_Time="1301.5" NumVehicleInCity="102" />
    <CheckPoint Sim_Time="1301.7" NumVehicleInCity="101" />
    <CheckPoint Sim_Time="1303.4" NumVehicleInCity="100" />
    <CheckPoint Sim_Time="1303.8" NumVehicleInCity="99" />
    <CheckPoint Sim_Time="1304.8" NumVehicleInCity="98" />
    <CheckPoint Sim_Time="1307.4" NumVehicleInCity="97" />
    <CheckPoint Sim_Time="1308.1" NumVehicleInCity="96" />
    <CheckPoint Sim_Time="1309.5" NumVehicleInCity="95" />
    <CheckPoint Sim_Time="1309.6" NumVehicleInCity="94" />
    <CheckPoint Sim_Time="1309.7" NumVehicleInCity="93" />
    <CheckPoint Sim_Time="1312.2" NumVehicleInCity="92" />
    <CheckPoint Sim_Time="1312.8" NumVehicleInCity="91" />
    <CheckPoint Sim_Time="1316" NumVehicleInCity="90" />
    <CheckPoint Sim_Time="1316.6" NumVehicleInCity="89" />
    <CheckPoint Sim_Time="1317.7" NumVehicleInCity="88" />
    <CheckPoint Sim_Time="1319.2" NumVehicleInCity="87" />
    <CheckPoint Sim_Time="1319.3" NumVehicleInCity="86" />
    <CheckPoint Sim_Time="1322.7" NumVehicleInCity="85" />
    <CheckPoint Sim_Time="1323.1" NumVehicleInCity="84" />
    <CheckPoint Sim_Time="1326.8" NumVehicleInCity="83" />
    <CheckPoint Sim_Time="1327.9" NumVehicleInCity="82" />
    <CheckPoint Sim_Time="1328.4" NumVehicleInCity="81" />
    <CheckPoint Sim_Time="1329.3" NumVehicleInCity="80" />
    <CheckPoint Sim_Time="1329.4" NumVehicleInCity="79" />
    <CheckPoint Sim_Time="1330.9" NumVehicleInCity="78" />
    <CheckPoint Sim_Time="1331" NumVehicleInCity="77" />
    <CheckPoint Sim_Time="1333" NumVehicleInCity="76" />
    <CheckPoint Sim_Time="1343.7" NumVehicleInCity="75" />
    <CheckPoint Sim_Time="1344.1" NumVehicleInCity="74" />
    <CheckPoint Sim_Time="1344.3" NumVehicleInCity="73" />
    <CheckPoint Sim_Time="1344.6" NumVehicleInCity="72" />
    <CheckPoint Sim_Time="1346" NumVehicleInCity="71" />
    <CheckPoint Sim_Time="1346.8" NumVehicleInCity="70" />
    <CheckPoint Sim_Time="1354.2" NumVehicleInCity="69" />
    <CheckPoint Sim_Time="1357.2" NumVehicleInCity="68" />
    <CheckPoint Sim_Time="1361.4" NumVehicleInCity="67" />
    <CheckPoint Sim_Time="1388.4" NumVehicleInCity="66" />
    <CheckPoint Sim_Time="1389.3" NumVehicleInCity="65" />
    <CheckPoint Sim_Time="1389.4" NumVehicleInCity="64" />
    <CheckPoint Sim_Time="1390" NumVehicleInCity="63" />
    <CheckPoint Sim_Time="1390.6" NumVehicleInCity="62" />
    <CheckPoint Sim_Time="1391.4" NumVehicleInCity="61" />
    <CheckPoint Sim_Time="1391.5" NumVehicleInCity="60" />
    <CheckPoint Sim_Time="1395.7" NumVehicleInCity="59" />
    <CheckPoint Sim_Time="1396.1" NumVehicleInCity="58" />
    <CheckPoint Sim_Time="1396.3" NumVehicleInCity="57" />
    <CheckPoint Sim_Time="1397.3" NumVehicleInCity="56" />
    <CheckPoint Sim_Time="1397.6" NumVehicleInCity="55" />
    <CheckPoint Sim_Time="1398.4" NumVehicleInCity="54" />
    <CheckPoint Sim_Time="1402.5" NumVehicleInCity="53" />
    <CheckPoint Sim_Time="1404.7" NumVehicleInCity="52" />
    <CheckPoint Sim_Time="1405.2" NumVehicleInCity="51" />
    <CheckPoint Sim_Time="1405.9" NumVehicleInCity="50" />
    <CheckPoint Sim_Time="1407" NumVehicleInCity="49" />
    <CheckPoint Sim_Time="1410.8" NumVehicleInCity="48" />
    <CheckPoint Sim_Time="1411.6" NumVehicleInCity="47" />
    <CheckPoint Sim_Time="1433.1" NumVehicleInCity="46" />
    <CheckPoint Sim_Time="1433.5" NumVehicleInCity="45" />
    <CheckPoint Sim_Time="1434.2" NumVehicleInCity="44" />
    <CheckPoint Sim_Time="1434.2" NumVehicleInCity="43" />
    <CheckPoint Sim_Time="1435.7" NumVehicleInCity="42" />
    <CheckPoint Sim_Time="1476.9" NumVehicleInCity="41" />
    <CheckPoint Sim_Time="1479.1" NumVehicleInCity="40" />
    <CheckPoint Sim_Time="1479.2" NumVehicleInCity="39" />
    <CheckPoint Sim_Time="1479.3" NumVehicleInCity="38" />
    <CheckPoint Sim_Time="1483" NumVehicleInCity="37" />
    <CheckPoint Sim_Time="1486.5" NumVehicleInCity="36" />
    <CheckPoint Sim_Time="1487.8" NumVehicleInCity="35" />
    <CheckPoint Sim_Time="1488.7" NumVehicleInCity="34" />
    <CheckPoint Sim_Time="1494.3" NumVehicleInCity="33" />
    <CheckPoint Sim_Time="1495.1" NumVehicleInCity="32" />
    <CheckPoint Sim_Time="1497.6" NumVehicleInCity="31" />
    <CheckPoint Sim_Time="1505.6" NumVehicleInCity="30" />
    <CheckPoint Sim_Time="1524.2" NumVehicleInCity="29" />
    <CheckPoint Sim_Time="1524.5" NumVehicleInCity="28" />
    <CheckPoint Sim_Time="1535" NumVehicleInCity="27" />
    <CheckPoint Sim_Time="1569" NumVehicleInCity="26" />
    <CheckPoint Sim_Time="1569.3" NumVehicleInCity="25" />
    <CheckPoint Sim_Time="1569.4" NumVehicleInCity="24" />
    <CheckPoint Sim_Time="1571.3" NumVehicleInCity="23" />
    <CheckPoint Sim_Time="1574.8" NumVehicleInCity="22" />
    <CheckPoint Sim_Time="1584.9" NumVehicleInCity="21" />
    <CheckPoint Sim_Time="1612.4" NumVehicleInCity="20" />
    <CheckPoint Sim_Time="1613.2" NumVehicleInCity="19" />
    <CheckPoint Sim_Time="1614.9" NumVehicleInCity="18" />
    <CheckPoint Sim_Time="1615.5" NumVehicleInCity="17" />
    <CheckPoint Sim_Time="1622" NumVehicleInCity="16" />
    <CheckPoint Sim_Time="1640.6" NumVehicleInCity="15" />
    <CheckPoint Sim_Time="1659" NumVehicleInCity="14" />
    <CheckPoint Sim_Time="1659.2" NumVehicleInCity="13" />
    <CheckPoint Sim_Time="1661.5" NumVehicleInCity="12" />
    <CheckPoint Sim_Time="1702.7" NumVehicleInCity="11" />
    <CheckPoint Sim_Time="1704.4" NumVehicleInCity="10" />
    <CheckPoint Sim_Time="1705.3" NumVehicleInCity="9" />
    <CheckPoint Sim_Time="1711.7" NumVehicleInCity="8" />
    <CheckPoint Sim_Time="1730.5" NumVehicleInCity="7" />
    <CheckPoint Sim_Time="1748.4" NumVehicleInCity="6" />
    <CheckPoint Sim_Time="1748.4" NumVehicleInCity="5" />
    <CheckPoint Sim_Time="1794" NumVehicleInCity="4" />
    <CheckPoint Sim_Time="1838.1" NumVehicleInCity="3" />
    <CheckPoint Sim_Time="1839.3" NumVehicleInCity="2" />
    <CheckPoint Sim_Time="1974.1" NumVehicleInCity="1" />
    <CheckPoint Sim_Time="2018.1" NumVehicleInCity="0" />
</Protocol>
