<Protocol Name="ROVER">
    <The_Simulation_Start_at>2014-06-14,17:49:48</The_Simulation_Start_at>
    <The_Simulation_End_at>2014-06-14,21:44:48</The_Simulation_End_at>
    <Playground_X>1025</Playground_X>
    <Playground_Y>1025</Playground_Y>
    <Road_Length>184.095</Road_Length>
    <Road_Building_Density_Ratio>0.271598</Road_Building_Density_Ratio>
    <Number_of_CrossRoads>16</Number_of_CrossRoads>
    <Number_of_Polygons>1</Number_of_Polygons>
    <Vehicle_In_City>200</Vehicle_In_City>
    <The_Range_of_Transmission>300</The_Range_of_Transmission>
    <Network_Identification_Number ID="0">
        <Network_Created_by>5</Network_Created_by>
        <Network_Creating_Time>212.3</Network_Creating_Time>
        <Network_Time_to_live>0.215391</Network_Time_to_live>
        <The_Location_of_ZOR>626.17,262.012,0</The_Location_of_ZOR>
        <The_Shape_of_ZOR>1</The_Shape_of_ZOR>
        <The_Length_of_ZOR>840</The_Length_of_ZOR>
        <The_Width_of_ZOR>840</The_Width_of_ZOR>
        <The_Location_of_ZOF>626.17,262.012,0</The_Location_of_ZOF>
        <The_Shape_of_ZOF>1</The_Shape_of_ZOF>
        <The_Length_of_ZOF>840</The_Length_of_ZOF>
        <The_Width_of_ZOF>840</The_Width_of_ZOF>
        <The_Number_of_Received_Message_Nodes_ZOR>129</The_Number_of_Received_Message_Nodes_ZOR>
        <The_Number_of_Received_Message_Nodes_ZOF>129</The_Number_of_Received_Message_Nodes_ZOF>
        <The_Number_of_Nodes_Which_Passing_Through_ZOR>133</The_Number_of_Nodes_Which_Passing_Through_ZOR>
        <The_Number_of_Nodes_Which_Passing_Through_ZOF>133</The_Number_of_Nodes_Which_Passing_Through_ZOF>
        <The_Packet_Delivery_Ratio>0.969925</The_Packet_Delivery_Ratio>
        <The_Max_Hops>6</The_Max_Hops>
        <The_Max_Delay_Time>0.0269004</The_Max_Delay_Time>
        <Delay_Time_Per_Hop>
            <Delay_Time>0.00428568</Delay_Time>
            <Delay_Time>0.0011741</Delay_Time>
            <Delay_Time>0.00533901</Delay_Time>
            <Delay_Time>0.0085301</Delay_Time>
            <Delay_Time>0.00485523</Delay_Time>
            <Delay_Time>0.00271628</Delay_Time>
        </Delay_Time_Per_Hop>
    </Network_Identification_Number>
    <Network_Identification_Number ID="1">
        <Network_Created_by>70</Network_Created_by>
        <Network_Creating_Time>212.8</Network_Creating_Time>
        <Network_Time_to_live>0.258439</Network_Time_to_live>
        <The_Location_of_ZOR>423.82,477.846,0</The_Location_of_ZOR>
        <The_Shape_of_ZOR>1</The_Shape_of_ZOR>
        <The_Length_of_ZOR>840</The_Length_of_ZOR>
        <The_Width_of_ZOR>840</The_Width_of_ZOR>
        <The_Location_of_ZOF>423.82,477.846,0</The_Location_of_ZOF>
        <The_Shape_of_ZOF>1</The_Shape_of_ZOF>
        <The_Length_of_ZOF>840</The_Length_of_ZOF>
        <The_Width_of_ZOF>840</The_Width_of_ZOF>
        <The_Number_of_Received_Message_Nodes_ZOR>162</The_Number_of_Received_Message_Nodes_ZOR>
        <The_Number_of_Received_Message_Nodes_ZOF>162</The_Number_of_Received_Message_Nodes_ZOF>
        <The_Number_of_Nodes_Which_Passing_Through_ZOR>163</The_Number_of_Nodes_Which_Passing_Through_ZOR>
        <The_Number_of_Nodes_Which_Passing_Through_ZOF>163</The_Number_of_Nodes_Which_Passing_Through_ZOF>
        <The_Packet_Delivery_Ratio>0.993865</The_Packet_Delivery_Ratio>
        <The_Max_Hops>5</The_Max_Hops>
        <The_Max_Delay_Time>0.0833888</The_Max_Delay_Time>
        <Delay_Time_Per_Hop>
            <Delay_Time>0.0044445</Delay_Time>
            <Delay_Time>0.00950199</Delay_Time>
            <Delay_Time>0.00235027</Delay_Time>
            <Delay_Time>0.00927055</Delay_Time>
            <Delay_Time>0.0578215</Delay_Time>
        </Delay_Time_Per_Hop>
    </Network_Identification_Number>
    <Network_Identification_Number ID="2">
        <Network_Created_by>4</Network_Created_by>
        <Network_Creating_Time>213.3</Network_Creating_Time>
        <Network_Time_to_live>0.355568</Network_Time_to_live>
        <The_Location_of_ZOR>827.293,420.63,0</The_Location_of_ZOR>
        <The_Shape_of_ZOR>1</The_Shape_of_ZOR>
        <The_Length_of_ZOR>840</The_Length_of_ZOR>
        <The_Width_of_ZOR>840</The_Width_of_ZOR>
        <The_Location_of_ZOF>827.293,420.63,0</The_Location_of_ZOF>
        <The_Shape_of_ZOF>1</The_Shape_of_ZOF>
        <The_Length_of_ZOF>840</The_Length_of_ZOF>
        <The_Width_of_ZOF>840</The_Width_of_ZOF>
        <The_Number_of_Received_Message_Nodes_ZOR>134</The_Number_of_Received_Message_Nodes_ZOR>
        <The_Number_of_Received_Message_Nodes_ZOF>134</The_Number_of_Received_Message_Nodes_ZOF>
        <The_Number_of_Nodes_Which_Passing_Through_ZOR>135</The_Number_of_Nodes_Which_Passing_Through_ZOR>
        <The_Number_of_Nodes_Which_Passing_Through_ZOF>135</The_Number_of_Nodes_Which_Passing_Through_ZOF>
        <The_Packet_Delivery_Ratio>0.992593</The_Packet_Delivery_Ratio>
        <The_Max_Hops>8</The_Max_Hops>
        <The_Max_Delay_Time>0.0457467</The_Max_Delay_Time>
        <Delay_Time_Per_Hop>
            <Delay_Time>0.00435426</Delay_Time>
            <Delay_Time>0.00863285</Delay_Time>
            <Delay_Time>0.00333759</Delay_Time>
            <Delay_Time>0.00387547</Delay_Time>
            <Delay_Time>0.00956726</Delay_Time>
            <Delay_Time>0.00338548</Delay_Time>
            <Delay_Time>0.0078395</Delay_Time>
            <Delay_Time>0.00475428</Delay_Time>
        </Delay_Time_Per_Hop>
    </Network_Identification_Number>
    <Network_Identification_Number ID="3">
        <Network_Created_by>49</Network_Created_by>
        <Network_Creating_Time>213.9</Network_Creating_Time>
        <Network_Time_to_live>0.458415</Network_Time_to_live>
        <The_Location_of_ZOR>614.37,426.17,0</The_Location_of_ZOR>
        <The_Shape_of_ZOR>1</The_Shape_of_ZOR>
        <The_Length_of_ZOR>840</The_Length_of_ZOR>
        <The_Width_of_ZOR>840</The_Width_of_ZOR>
        <The_Location_of_ZOF>614.37,426.17,0</The_Location_of_ZOF>
        <The_Shape_of_ZOF>1</The_Shape_of_ZOF>
        <The_Length_of_ZOF>840</The_Length_of_ZOF>
        <The_Width_of_ZOF>840</The_Width_of_ZOF>
        <The_Number_of_Received_Message_Nodes_ZOR>177</The_Number_of_Received_Message_Nodes_ZOR>
        <The_Number_of_Received_Message_Nodes_ZOF>177</The_Number_of_Received_Message_Nodes_ZOF>
        <The_Number_of_Nodes_Which_Passing_Through_ZOR>178</The_Number_of_Nodes_Which_Passing_Through_ZOR>
        <The_Number_of_Nodes_Which_Passing_Through_ZOF>178</The_Number_of_Nodes_Which_Passing_Through_ZOF>
        <The_Packet_Delivery_Ratio>0.994382</The_Packet_Delivery_Ratio>
        <The_Max_Hops>7</The_Max_Hops>
        <The_Max_Delay_Time>0.0306677</The_Max_Delay_Time>
        <Delay_Time_Per_Hop>
            <Delay_Time>0.00443357</Delay_Time>
            <Delay_Time>0.00706988</Delay_Time>
            <Delay_Time>0.00316897</Delay_Time>
            <Delay_Time>0.00817459</Delay_Time>
            <Delay_Time>0.00103528</Delay_Time>
            <Delay_Time>0.00512565</Delay_Time>
            <Delay_Time>0.00165976</Delay_Time>
        </Delay_Time_Per_Hop>
    </Network_Identification_Number>
    <Network_Identification_Number ID="4">
        <Network_Created_by>56</Network_Created_by>
        <Network_Creating_Time>214.6</Network_Creating_Time>
        <Network_Time_to_live>0.456622</Network_Time_to_live>
        <The_Location_of_ZOR>226.18,691.968,0</The_Location_of_ZOR>
        <The_Shape_of_ZOR>1</The_Shape_of_ZOR>
        <The_Length_of_ZOR>840</The_Length_of_ZOR>
        <The_Width_of_ZOR>840</The_Width_of_ZOR>
        <The_Location_of_ZOF>226.18,691.968,0</The_Location_of_ZOF>
        <The_Shape_of_ZOF>1</The_Shape_of_ZOF>
        <The_Length_of_ZOF>840</The_Length_of_ZOF>
        <The_Width_of_ZOF>840</The_Width_of_ZOF>
        <The_Number_of_Received_Message_Nodes_ZOR>93</The_Number_of_Received_Message_Nodes_ZOR>
        <The_Number_of_Received_Message_Nodes_ZOF>93</The_Number_of_Received_Message_Nodes_ZOF>
        <The_Number_of_Nodes_Which_Passing_Through_ZOR>94</The_Number_of_Nodes_Which_Passing_Through_ZOR>
        <The_Number_of_Nodes_Which_Passing_Through_ZOF>94</The_Number_of_Nodes_Which_Passing_Through_ZOF>
        <The_Packet_Delivery_Ratio>0.989362</The_Packet_Delivery_Ratio>
        <The_Max_Hops>5</The_Max_Hops>
        <The_Max_Delay_Time>0.0235777</The_Max_Delay_Time>
        <Delay_Time_Per_Hop>
            <Delay_Time>0.0044721</Delay_Time>
            <Delay_Time>0.00927049</Delay_Time>
            <Delay_Time>0.00673464</Delay_Time>
            <Delay_Time>0.00136595</Delay_Time>
            <Delay_Time>0.0017345</Delay_Time>
        </Delay_Time_Per_Hop>
    </Network_Identification_Number>
    <Network_Identification_Number ID="5">
        <Network_Created_by>77</Network_Created_by>
        <Network_Creating_Time>215.3</Network_Creating_Time>
        <Network_Time_to_live>0.279679</Network_Time_to_live>
        <The_Location_of_ZOR>635.629,623.82,0</The_Location_of_ZOR>
        <The_Shape_of_ZOR>1</The_Shape_of_ZOR>
        <The_Length_of_ZOR>840</The_Length_of_ZOR>
        <The_Width_of_ZOR>840</The_Width_of_ZOR>
        <The_Location_of_ZOF>635.629,623.82,0</The_Location_of_ZOF>
        <The_Shape_of_ZOF>1</The_Shape_of_ZOF>
        <The_Length_of_ZOF>840</The_Length_of_ZOF>
        <The_Width_of_ZOF>840</The_Width_of_ZOF>
        <The_Number_of_Received_Message_Nodes_ZOR>161</The_Number_of_Received_Message_Nodes_ZOR>
        <The_Number_of_Received_Message_Nodes_ZOF>161</The_Number_of_Received_Message_Nodes_ZOF>
        <The_Number_of_Nodes_Which_Passing_Through_ZOR>162</The_Number_of_Nodes_Which_Passing_Through_ZOR>
        <The_Number_of_Nodes_Which_Passing_Through_ZOF>162</The_Number_of_Nodes_Which_Passing_Through_ZOF>
        <The_Packet_Delivery_Ratio>0.993827</The_Packet_Delivery_Ratio>
        <The_Max_Hops>5</The_Max_Hops>
        <The_Max_Delay_Time>0.0224497</The_Max_Delay_Time>
        <Delay_Time_Per_Hop>
            <Delay_Time>0.00455728</Delay_Time>
            <Delay_Time>0.0039607</Delay_Time>
            <Delay_Time>0.00586396</Delay_Time>
            <Delay_Time>0.00251884</Delay_Time>
            <Delay_Time>0.00554895</Delay_Time>
        </Delay_Time_Per_Hop>
    </Network_Identification_Number>
    <Network_Identification_Number ID="6">
        <Network_Created_by>88</Network_Created_by>
        <Network_Creating_Time>215.8</Network_Creating_Time>
        <Network_Time_to_live>0.406809</Network_Time_to_live>
        <The_Location_of_ZOR>470.463,823.82,0</The_Location_of_ZOR>
        <The_Shape_of_ZOR>1</The_Shape_of_ZOR>
        <The_Length_of_ZOR>840</The_Length_of_ZOR>
        <The_Width_of_ZOR>840</The_Width_of_ZOR>
        <The_Location_of_ZOF>470.463,823.82,0</The_Location_of_ZOF>
        <The_Shape_of_ZOF>1</The_Shape_of_ZOF>
        <The_Length_of_ZOF>840</The_Length_of_ZOF>
        <The_Width_of_ZOF>840</The_Width_of_ZOF>
        <The_Number_of_Received_Message_Nodes_ZOR>124</The_Number_of_Received_Message_Nodes_ZOR>
        <The_Number_of_Received_Message_Nodes_ZOF>124</The_Number_of_Received_Message_Nodes_ZOF>
        <The_Number_of_Nodes_Which_Passing_Through_ZOR>126</The_Number_of_Nodes_Which_Passing_Through_ZOR>
        <The_Number_of_Nodes_Which_Passing_Through_ZOF>126</The_Number_of_Nodes_Which_Passing_Through_ZOF>
        <The_Packet_Delivery_Ratio>0.984127</The_Packet_Delivery_Ratio>
        <The_Max_Hops>6</The_Max_Hops>
        <The_Max_Delay_Time>0.0929733</The_Max_Delay_Time>
        <Delay_Time_Per_Hop>
            <Delay_Time>0.00449515</Delay_Time>
            <Delay_Time>0.00913394</Delay_Time>
            <Delay_Time>0.00646685</Delay_Time>
            <Delay_Time>0.0101474</Delay_Time>
            <Delay_Time>0.056514</Delay_Time>
            <Delay_Time>0.00621603</Delay_Time>
        </Delay_Time_Per_Hop>
    </Network_Identification_Number>
    <Network_Identification_Number ID="7">
        <Network_Created_by>2</Network_Created_by>
        <Network_Creating_Time>216.5</Network_Creating_Time>
        <Network_Time_to_live>0.264728</Network_Time_to_live>
        <The_Location_of_ZOR>614.37,826.18,0</The_Location_of_ZOR>
        <The_Shape_of_ZOR>1</The_Shape_of_ZOR>
        <The_Length_of_ZOR>840</The_Length_of_ZOR>
        <The_Width_of_ZOR>840</The_Width_of_ZOR>
        <The_Location_of_ZOF>614.37,826.18,0</The_Location_of_ZOF>
        <The_Shape_of_ZOF>1</The_Shape_of_ZOF>
        <The_Length_of_ZOF>840</The_Length_of_ZOF>
        <The_Width_of_ZOF>840</The_Width_of_ZOF>
        <The_Number_of_Received_Message_Nodes_ZOR>124</The_Number_of_Received_Message_Nodes_ZOR>
        <The_Number_of_Received_Message_Nodes_ZOF>124</The_Number_of_Received_Message_Nodes_ZOF>
        <The_Number_of_Nodes_Which_Passing_Through_ZOR>125</The_Number_of_Nodes_Which_Passing_Through_ZOR>
        <The_Number_of_Nodes_Which_Passing_Through_ZOF>125</The_Number_of_Nodes_Which_Passing_Through_ZOF>
        <The_Packet_Delivery_Ratio>0.992</The_Packet_Delivery_Ratio>
        <The_Max_Hops>4</The_Max_Hops>
        <The_Max_Delay_Time>0.0190576</The_Max_Delay_Time>
        <Delay_Time_Per_Hop>
            <Delay_Time>0.00438013</Delay_Time>
            <Delay_Time>0.0071513</Delay_Time>
            <Delay_Time>0.00364142</Delay_Time>
            <Delay_Time>0.00388475</Delay_Time>
        </Delay_Time_Per_Hop>
    </Network_Identification_Number>
    <Network_Identification_Number ID="8">
        <Network_Created_by>31</Network_Created_by>
        <Network_Creating_Time>217</Network_Creating_Time>
        <Network_Time_to_live>0.370176</Network_Time_to_live>
        <The_Location_of_ZOR>814.371,825.53,0</The_Location_of_ZOR>
        <The_Shape_of_ZOR>1</The_Shape_of_ZOR>
        <The_Length_of_ZOR>840</The_Length_of_ZOR>
        <The_Width_of_ZOR>840</The_Width_of_ZOR>
        <The_Location_of_ZOF>814.371,825.53,0</The_Location_of_ZOF>
        <The_Shape_of_ZOF>1</The_Shape_of_ZOF>
        <The_Length_of_ZOF>840</The_Length_of_ZOF>
        <The_Width_of_ZOF>840</The_Width_of_ZOF>
        <The_Number_of_Received_Message_Nodes_ZOR>95</The_Number_of_Received_Message_Nodes_ZOR>
        <The_Number_of_Received_Message_Nodes_ZOF>95</The_Number_of_Received_Message_Nodes_ZOF>
        <The_Number_of_Nodes_Which_Passing_Through_ZOR>96</The_Number_of_Nodes_Which_Passing_Through_ZOR>
        <The_Number_of_Nodes_Which_Passing_Through_ZOF>96</The_Number_of_Nodes_Which_Passing_Through_ZOF>
        <The_Packet_Delivery_Ratio>0.989583</The_Packet_Delivery_Ratio>
        <The_Max_Hops>4</The_Max_Hops>
        <The_Max_Delay_Time>0.0689169</The_Max_Delay_Time>
        <Delay_Time_Per_Hop>
            <Delay_Time>0.00442095</Delay_Time>
            <Delay_Time>0.00143035</Delay_Time>
            <Delay_Time>0.0582858</Delay_Time>
            <Delay_Time>0.00477982</Delay_Time>
        </Delay_Time_Per_Hop>
    </Network_Identification_Number>
    <Network_Identification_Number ID="9">
        <Network_Created_by>105</Network_Created_by>
        <Network_Creating_Time>217.6</Network_Creating_Time>
        <Network_Time_to_live>0.372022</Network_Time_to_live>
        <The_Location_of_ZOR>445.14,623.82,0</The_Location_of_ZOR>
        <The_Shape_of_ZOR>1</The_Shape_of_ZOR>
        <The_Length_of_ZOR>840</The_Length_of_ZOR>
        <The_Width_of_ZOR>840</The_Width_of_ZOR>
        <The_Location_of_ZOF>445.14,623.82,0</The_Location_of_ZOF>
        <The_Shape_of_ZOF>1</The_Shape_of_ZOF>
        <The_Length_of_ZOF>840</The_Length_of_ZOF>
        <The_Width_of_ZOF>840</The_Width_of_ZOF>
        <The_Number_of_Received_Message_Nodes_ZOR>166</The_Number_of_Received_Message_Nodes_ZOR>
        <The_Number_of_Received_Message_Nodes_ZOF>166</The_Number_of_Received_Message_Nodes_ZOF>
        <The_Number_of_Nodes_Which_Passing_Through_ZOR>167</The_Number_of_Nodes_Which_Passing_Through_ZOR>
        <The_Number_of_Nodes_Which_Passing_Through_ZOF>167</The_Number_of_Nodes_Which_Passing_Through_ZOF>
        <The_Packet_Delivery_Ratio>0.994012</The_Packet_Delivery_Ratio>
        <The_Max_Hops>5</The_Max_Hops>
        <The_Max_Delay_Time>0.0243652</The_Max_Delay_Time>
        <Delay_Time_Per_Hop>
            <Delay_Time>0.00443741</Delay_Time>
            <Delay_Time>0.00354843</Delay_Time>
            <Delay_Time>0.00903542</Delay_Time>
            <Delay_Time>0.00374163</Delay_Time>
            <Delay_Time>0.00360233</Delay_Time>
        </Delay_Time_Per_Hop>
    </Network_Identification_Number>
    <Network_Identification_Number ID="10">
        <Network_Created_by>161</Network_Created_by>
        <Network_Creating_Time>218.2</Network_Creating_Time>
        <Network_Time_to_live>0.273315</Network_Time_to_live>
        <The_Location_of_ZOR>826.17,244.668,0</The_Location_of_ZOR>
        <The_Shape_of_ZOR>1</The_Shape_of_ZOR>
        <The_Length_of_ZOR>840</The_Length_of_ZOR>
        <The_Width_of_ZOR>840</The_Width_of_ZOR>
        <The_Location_of_ZOF>826.17,244.668,0</The_Location_of_ZOF>
        <The_Shape_of_ZOF>1</The_Shape_of_ZOF>
        <The_Length_of_ZOF>840</The_Length_of_ZOF>
        <The_Width_of_ZOF>840</The_Width_of_ZOF>
        <The_Number_of_Received_Message_Nodes_ZOR>104</The_Number_of_Received_Message_Nodes_ZOR>
        <The_Number_of_Received_Message_Nodes_ZOF>104</The_Number_of_Received_Message_Nodes_ZOF>
        <The_Number_of_Nodes_Which_Passing_Through_ZOR>105</The_Number_of_Nodes_Which_Passing_Through_ZOR>
        <The_Number_of_Nodes_Which_Passing_Through_ZOF>105</The_Number_of_Nodes_Which_Passing_Through_ZOF>
        <The_Packet_Delivery_Ratio>0.990476</The_Packet_Delivery_Ratio>
        <The_Max_Hops>6</The_Max_Hops>
        <The_Max_Delay_Time>0.0861813</The_Max_Delay_Time>
        <Delay_Time_Per_Hop>
            <Delay_Time>0.00455801</Delay_Time>
            <Delay_Time>0.00744803</Delay_Time>
            <Delay_Time>0.0105146</Delay_Time>
            <Delay_Time>0.00167257</Delay_Time>
            <Delay_Time>0.00183706</Delay_Time>
            <Delay_Time>0.0601511</Delay_Time>
        </Delay_Time_Per_Hop>
    </Network_Identification_Number>
    <Network_Identification_Number ID="11">
        <Network_Created_by>46</Network_Created_by>
        <Network_Creating_Time>218.7</Network_Creating_Time>
        <Network_Time_to_live>0.486166</Network_Time_to_live>
        <The_Location_of_ZOR>625.52,255.47,0</The_Location_of_ZOR>
        <The_Shape_of_ZOR>1</The_Shape_of_ZOR>
        <The_Length_of_ZOR>840</The_Length_of_ZOR>
        <The_Width_of_ZOR>840</The_Width_of_ZOR>
        <The_Location_of_ZOF>625.52,255.47,0</The_Location_of_ZOF>
        <The_Shape_of_ZOF>1</The_Shape_of_ZOF>
        <The_Length_of_ZOF>840</The_Length_of_ZOF>
        <The_Width_of_ZOF>840</The_Width_of_ZOF>
        <The_Number_of_Received_Message_Nodes_ZOR>132</The_Number_of_Received_Message_Nodes_ZOR>
        <The_Number_of_Received_Message_Nodes_ZOF>132</The_Number_of_Received_Message_Nodes_ZOF>
        <The_Number_of_Nodes_Which_Passing_Through_ZOR>133</The_Number_of_Nodes_Which_Passing_Through_ZOR>
        <The_Number_of_Nodes_Which_Passing_Through_ZOF>133</The_Number_of_Nodes_Which_Passing_Through_ZOF>
        <The_Packet_Delivery_Ratio>0.992481</The_Packet_Delivery_Ratio>
        <The_Max_Hops>7</The_Max_Hops>
        <The_Max_Delay_Time>0.0767267</The_Max_Delay_Time>
        <Delay_Time_Per_Hop>
            <Delay_Time>0.00457228</Delay_Time>
            <Delay_Time>0.00793443</Delay_Time>
            <Delay_Time>0.00563001</Delay_Time>
            <Delay_Time>0.0522163</Delay_Time>
            <Delay_Time>0.00228399</Delay_Time>
            <Delay_Time>0.000566229</Delay_Time>
            <Delay_Time>0.00352355</Delay_Time>
        </Delay_Time_Per_Hop>
    </Network_Identification_Number>
    <Network_Identification_Number ID="12">
        <Network_Created_by>153</Network_Created_by>
        <Network_Creating_Time>219.4</Network_Creating_Time>
        <Network_Time_to_live>0.192213</Network_Time_to_live>
        <The_Location_of_ZOR>645.784,423.83,0</The_Location_of_ZOR>
        <The_Shape_of_ZOR>1</The_Shape_of_ZOR>
        <The_Length_of_ZOR>840</The_Length_of_ZOR>
        <The_Width_of_ZOR>840</The_Width_of_ZOR>
        <The_Location_of_ZOF>645.784,423.83,0</The_Location_of_ZOF>
        <The_Shape_of_ZOF>1</The_Shape_of_ZOF>
        <The_Length_of_ZOF>840</The_Length_of_ZOF>
        <The_Width_of_ZOF>840</The_Width_of_ZOF>
        <The_Number_of_Received_Message_Nodes_ZOR>160</The_Number_of_Received_Message_Nodes_ZOR>
        <The_Number_of_Received_Message_Nodes_ZOF>160</The_Number_of_Received_Message_Nodes_ZOF>
        <The_Number_of_Nodes_Which_Passing_Through_ZOR>162</The_Number_of_Nodes_Which_Passing_Through_ZOR>
        <The_Number_of_Nodes_Which_Passing_Through_ZOF>162</The_Number_of_Nodes_Which_Passing_Through_ZOF>
        <The_Packet_Delivery_Ratio>0.987654</The_Packet_Delivery_Ratio>
        <The_Max_Hops>6</The_Max_Hops>
        <The_Max_Delay_Time>0.0909321</The_Max_Delay_Time>
        <Delay_Time_Per_Hop>
            <Delay_Time>0.00440538</Delay_Time>
            <Delay_Time>0.00784207</Delay_Time>
            <Delay_Time>0.00147185</Delay_Time>
            <Delay_Time>0.00701454</Delay_Time>
            <Delay_Time>0.0601578</Delay_Time>
            <Delay_Time>0.0100404</Delay_Time>
        </Delay_Time_Per_Hop>
    </Network_Identification_Number>
    <Network_Identification_Number ID="13">
        <Network_Created_by>86</Network_Created_by>
        <Network_Creating_Time>219.8</Network_Creating_Time>
        <Network_Time_to_live>0.288053</Network_Time_to_live>
        <The_Location_of_ZOR>625.064,614.018,0</The_Location_of_ZOR>
        <The_Shape_of_ZOR>1</The_Shape_of_ZOR>
        <The_Length_of_ZOR>840</The_Length_of_ZOR>
        <The_Width_of_ZOR>840</The_Width_of_ZOR>
        <The_Location_of_ZOF>625.064,614.018,0</The_Location_of_ZOF>
        <The_Shape_of_ZOF>1</The_Shape_of_ZOF>
        <The_Length_of_ZOF>840</The_Length_of_ZOF>
        <The_Width_of_ZOF>840</The_Width_of_ZOF>
        <The_Number_of_Received_Message_Nodes_ZOR>169</The_Number_of_Received_Message_Nodes_ZOR>
        <The_Number_of_Received_Message_Nodes_ZOF>169</The_Number_of_Received_Message_Nodes_ZOF>
        <The_Number_of_Nodes_Which_Passing_Through_ZOR>170</The_Number_of_Nodes_Which_Passing_Through_ZOR>
        <The_Number_of_Nodes_Which_Passing_Through_ZOF>170</The_Number_of_Nodes_Which_Passing_Through_ZOF>
        <The_Packet_Delivery_Ratio>0.994118</The_Packet_Delivery_Ratio>
        <The_Max_Hops>5</The_Max_Hops>
        <The_Max_Delay_Time>0.0734298</The_Max_Delay_Time>
        <Delay_Time_Per_Hop>
            <Delay_Time>0.00447378</Delay_Time>
            <Delay_Time>0.0059881</Delay_Time>
            <Delay_Time>0.003785</Delay_Time>
            <Delay_Time>0.0580003</Delay_Time>
            <Delay_Time>0.00118263</Delay_Time>
        </Delay_Time_Per_Hop>
    </Network_Identification_Number>
    <Network_Identification_Number ID="14">
        <Network_Created_by>167</Network_Created_by>
        <Network_Creating_Time>220.3</Network_Creating_Time>
        <Network_Time_to_live>0.253385</Network_Time_to_live>
        <The_Location_of_ZOR>456.697,823.82,0</The_Location_of_ZOR>
        <The_Shape_of_ZOR>1</The_Shape_of_ZOR>
        <The_Length_of_ZOR>840</The_Length_of_ZOR>
        <The_Width_of_ZOR>840</The_Width_of_ZOR>
        <The_Location_of_ZOF>456.697,823.82,0</The_Location_of_ZOF>
        <The_Shape_of_ZOF>1</The_Shape_of_ZOF>
        <The_Length_of_ZOF>840</The_Length_of_ZOF>
        <The_Width_of_ZOF>840</The_Width_of_ZOF>
        <The_Number_of_Received_Message_Nodes_ZOR>111</The_Number_of_Received_Message_Nodes_ZOR>
        <The_Number_of_Received_Message_Nodes_ZOF>111</The_Number_of_Received_Message_Nodes_ZOF>
        <The_Number_of_Nodes_Which_Passing_Through_ZOR>125</The_Number_of_Nodes_Which_Passing_Through_ZOR>
        <The_Number_of_Nodes_Which_Passing_Through_ZOF>125</The_Number_of_Nodes_Which_Passing_Through_ZOF>
        <The_Packet_Delivery_Ratio>0.888</The_Packet_Delivery_Ratio>
        <The_Max_Hops>7</The_Max_Hops>
        <The_Max_Delay_Time>0.0427987</The_Max_Delay_Time>
        <Delay_Time_Per_Hop>
            <Delay_Time>0.00449281</Delay_Time>
            <Delay_Time>0.00798918</Delay_Time>
            <Delay_Time>0.00215133</Delay_Time>
            <Delay_Time>0.00590185</Delay_Time>
            <Delay_Time>0.00899794</Delay_Time>
            <Delay_Time>0.0050092</Delay_Time>
            <Delay_Time>0.00825641</Delay_Time>
        </Delay_Time_Per_Hop>
    </Network_Identification_Number>
    <Network_Identification_Number ID="15">
        <Network_Created_by>171</Network_Created_by>
        <Network_Creating_Time>220.8</Network_Creating_Time>
        <Network_Time_to_live>0.146481</Network_Time_to_live>
        <The_Location_of_ZOR>235.63,823.82,0</The_Location_of_ZOR>
        <The_Shape_of_ZOR>1</The_Shape_of_ZOR>
        <The_Length_of_ZOR>840</The_Length_of_ZOR>
        <The_Width_of_ZOR>840</The_Width_of_ZOR>
        <The_Location_of_ZOF>235.63,823.82,0</The_Location_of_ZOF>
        <The_Shape_of_ZOF>1</The_Shape_of_ZOF>
        <The_Length_of_ZOF>840</The_Length_of_ZOF>
        <The_Width_of_ZOF>840</The_Width_of_ZOF>
        <The_Number_of_Received_Message_Nodes_ZOR>56</The_Number_of_Received_Message_Nodes_ZOR>
        <The_Number_of_Received_Message_Nodes_ZOF>56</The_Number_of_Received_Message_Nodes_ZOF>
        <The_Number_of_Nodes_Which_Passing_Through_ZOR>93</The_Number_of_Nodes_Which_Passing_Through_ZOR>
        <The_Number_of_Nodes_Which_Passing_Through_ZOF>93</The_Number_of_Nodes_Which_Passing_Through_ZOF>
        <The_Packet_Delivery_Ratio>0.602151</The_Packet_Delivery_Ratio>
        <The_Max_Hops>3</The_Max_Hops>
        <The_Max_Delay_Time>0.0163771</The_Max_Delay_Time>
        <Delay_Time_Per_Hop>
            <Delay_Time>0.00444882</Delay_Time>
            <Delay_Time>0.00248197</Delay_Time>
            <Delay_Time>0.00944628</Delay_Time>
        </Delay_Time_Per_Hop>
    </Network_Identification_Number>
    <Network_Identification_Number ID="16">
        <Network_Created_by>193</Network_Created_by>
        <Network_Creating_Time>221.2</Network_Creating_Time>
        <Network_Time_to_live>0.335386</Network_Time_to_live>
        <The_Location_of_ZOR>813.871,226.17,0</The_Location_of_ZOR>
        <The_Shape_of_ZOR>1</The_Shape_of_ZOR>
        <The_Length_of_ZOR>840</The_Length_of_ZOR>
        <The_Width_of_ZOR>840</The_Width_of_ZOR>
        <The_Location_of_ZOF>813.871,226.17,0</The_Location_of_ZOF>
        <The_Shape_of_ZOF>1</The_Shape_of_ZOF>
        <The_Length_of_ZOF>840</The_Length_of_ZOF>
        <The_Width_of_ZOF>840</The_Width_of_ZOF>
        <The_Number_of_Received_Message_Nodes_ZOR>109</The_Number_of_Received_Message_Nodes_ZOR>
        <The_Number_of_Received_Message_Nodes_ZOF>109</The_Number_of_Received_Message_Nodes_ZOF>
        <The_Number_of_Nodes_Which_Passing_Through_ZOR>110</The_Number_of_Nodes_Which_Passing_Through_ZOR>
        <The_Number_of_Nodes_Which_Passing_Through_ZOF>110</The_Number_of_Nodes_Which_Passing_Through_ZOF>
        <The_Packet_Delivery_Ratio>0.990909</The_Packet_Delivery_Ratio>
        <The_Max_Hops>4</The_Max_Hops>
        <The_Max_Delay_Time>0.0288379</The_Max_Delay_Time>
        <Delay_Time_Per_Hop>
            <Delay_Time>0.00446647</Delay_Time>
            <Delay_Time>0.00509056</Delay_Time>
            <Delay_Time>0.0088837</Delay_Time>
            <Delay_Time>0.0103972</Delay_Time>
        </Delay_Time_Per_Hop>
    </Network_Identification_Number>
    <Network_Identification_Number ID="17">
        <Network_Created_by>210</Network_Created_by>
        <Network_Creating_Time>221.8</Network_Creating_Time>
        <Network_Time_to_live>0.402443</Network_Time_to_live>
        <The_Location_of_ZOR>214.371,426.17,0</The_Location_of_ZOR>
        <The_Shape_of_ZOR>1</The_Shape_of_ZOR>
        <The_Length_of_ZOR>840</The_Length_of_ZOR>
        <The_Width_of_ZOR>840</The_Width_of_ZOR>
        <The_Location_of_ZOF>214.371,426.17,0</The_Location_of_ZOF>
        <The_Shape_of_ZOF>1</The_Shape_of_ZOF>
        <The_Length_of_ZOF>840</The_Length_of_ZOF>
        <The_Width_of_ZOF>840</The_Width_of_ZOF>
        <The_Number_of_Received_Message_Nodes_ZOR>117</The_Number_of_Received_Message_Nodes_ZOR>
        <The_Number_of_Received_Message_Nodes_ZOF>117</The_Number_of_Received_Message_Nodes_ZOF>
        <The_Number_of_Nodes_Which_Passing_Through_ZOR>118</The_Number_of_Nodes_Which_Passing_Through_ZOR>
        <The_Number_of_Nodes_Which_Passing_Through_ZOF>118</The_Number_of_Nodes_Which_Passing_Through_ZOF>
        <The_Packet_Delivery_Ratio>0.991525</The_Packet_Delivery_Ratio>
        <The_Max_Hops>5</The_Max_Hops>
        <The_Max_Delay_Time>0.0691058</The_Max_Delay_Time>
        <Delay_Time_Per_Hop>
            <Delay_Time>0.00452339</Delay_Time>
            <Delay_Time>0.00789898</Delay_Time>
            <Delay_Time>0.00338359</Delay_Time>
            <Delay_Time>0.0498804</Delay_Time>
            <Delay_Time>0.00341946</Delay_Time>
        </Delay_Time_Per_Hop>
    </Network_Identification_Number>
    <Network_Identification_Number ID="18">
        <Network_Created_by>219</Network_Created_by>
        <Network_Creating_Time>222.5</Network_Creating_Time>
        <Network_Time_to_live>0.215196</Network_Time_to_live>
        <The_Location_of_ZOR>213.87,826.18,0</The_Location_of_ZOR>
        <The_Shape_of_ZOR>1</The_Shape_of_ZOR>
        <The_Length_of_ZOR>840</The_Length_of_ZOR>
        <The_Width_of_ZOR>840</The_Width_of_ZOR>
        <The_Location_of_ZOF>213.87,826.18,0</The_Location_of_ZOF>
        <The_Shape_of_ZOF>1</The_Shape_of_ZOF>
        <The_Length_of_ZOF>840</The_Length_of_ZOF>
        <The_Width_of_ZOF>840</The_Width_of_ZOF>
        <The_Number_of_Received_Message_Nodes_ZOR>86</The_Number_of_Received_Message_Nodes_ZOR>
        <The_Number_of_Received_Message_Nodes_ZOF>86</The_Number_of_Received_Message_Nodes_ZOF>
        <The_Number_of_Nodes_Which_Passing_Through_ZOR>87</The_Number_of_Nodes_Which_Passing_Through_ZOR>
        <The_Number_of_Nodes_Which_Passing_Through_ZOF>87</The_Number_of_Nodes_Which_Passing_Through_ZOF>
        <The_Packet_Delivery_Ratio>0.988506</The_Packet_Delivery_Ratio>
        <The_Max_Hops>5</The_Max_Hops>
        <The_Max_Delay_Time>0.0219973</The_Max_Delay_Time>
        <Delay_Time_Per_Hop>
            <Delay_Time>0.00446944</Delay_Time>
            <Delay_Time>0.00289908</Delay_Time>
            <Delay_Time>0.00609866</Delay_Time>
            <Delay_Time>0.00578375</Delay_Time>
            <Delay_Time>0.00274642</Delay_Time>
        </Delay_Time_Per_Hop>
    </Network_Identification_Number>
    <Network_Identification_Number ID="19">
        <Network_Created_by>220</Network_Created_by>
        <Network_Creating_Time>223</Network_Creating_Time>
        <Network_Time_to_live>0.347523</Network_Time_to_live>
        <The_Location_of_ZOR>214.37,626.18,0</The_Location_of_ZOR>
        <The_Shape_of_ZOR>1</The_Shape_of_ZOR>
        <The_Length_of_ZOR>840</The_Length_of_ZOR>
        <The_Width_of_ZOR>840</The_Width_of_ZOR>
        <The_Location_of_ZOF>214.37,626.18,0</The_Location_of_ZOF>
        <The_Shape_of_ZOF>1</The_Shape_of_ZOF>
        <The_Length_of_ZOF>840</The_Length_of_ZOF>
        <The_Width_of_ZOF>840</The_Width_of_ZOF>
        <The_Number_of_Received_Message_Nodes_ZOR>116</The_Number_of_Received_Message_Nodes_ZOR>
        <The_Number_of_Received_Message_Nodes_ZOF>116</The_Number_of_Received_Message_Nodes_ZOF>
        <The_Number_of_Nodes_Which_Passing_Through_ZOR>117</The_Number_of_Nodes_Which_Passing_Through_ZOR>
        <The_Number_of_Nodes_Which_Passing_Through_ZOF>117</The_Number_of_Nodes_Which_Passing_Through_ZOF>
        <The_Packet_Delivery_Ratio>0.991453</The_Packet_Delivery_Ratio>
        <The_Max_Hops>5</The_Max_Hops>
        <The_Max_Delay_Time>0.0694469</The_Max_Delay_Time>
        <Delay_Time_Per_Hop>
            <Delay_Time>0.00457769</Delay_Time>
            <Delay_Time>0.00146833</Delay_Time>
            <Delay_Time>0.00245953</Delay_Time>
            <Delay_Time>0.0566195</Delay_Time>
            <Delay_Time>0.00432187</Delay_Time>
        </Delay_Time_Per_Hop>
    </Network_Identification_Number>
    <Network_Identification_Number ID="20">
        <Network_Created_by>143</Network_Created_by>
        <Network_Creating_Time>223.6</Network_Creating_Time>
        <Network_Time_to_live>0.289947</Network_Time_to_live>
        <The_Location_of_ZOR>413.87,625.52,0</The_Location_of_ZOR>
        <The_Shape_of_ZOR>1</The_Shape_of_ZOR>
        <The_Length_of_ZOR>840</The_Length_of_ZOR>
        <The_Width_of_ZOR>840</The_Width_of_ZOR>
        <The_Location_of_ZOF>413.87,625.52,0</The_Location_of_ZOF>
        <The_Shape_of_ZOF>1</The_Shape_of_ZOF>
        <The_Length_of_ZOF>840</The_Length_of_ZOF>
        <The_Width_of_ZOF>840</The_Width_of_ZOF>
        <The_Number_of_Received_Message_Nodes_ZOR>150</The_Number_of_Received_Message_Nodes_ZOR>
        <The_Number_of_Received_Message_Nodes_ZOF>150</The_Number_of_Received_Message_Nodes_ZOF>
        <The_Number_of_Nodes_Which_Passing_Through_ZOR>151</The_Number_of_Nodes_Which_Passing_Through_ZOR>
        <The_Number_of_Nodes_Which_Passing_Through_ZOF>151</The_Number_of_Nodes_Which_Passing_Through_ZOF>
        <The_Packet_Delivery_Ratio>0.993377</The_Packet_Delivery_Ratio>
        <The_Max_Hops>6</The_Max_Hops>
        <The_Max_Delay_Time>0.0214631</The_Max_Delay_Time>
        <Delay_Time_Per_Hop>
            <Delay_Time>0.00435344</Delay_Time>
            <Delay_Time>0.000948638</Delay_Time>
            <Delay_Time>0.00654632</Delay_Time>
            <Delay_Time>0.00456318</Delay_Time>
            <Delay_Time>0.00306849</Delay_Time>
            <Delay_Time>0.00198298</Delay_Time>
        </Delay_Time_Per_Hop>
    </Network_Identification_Number>
    <Network_Identification_Number ID="21">
        <Network_Created_by>224</Network_Created_by>
        <Network_Creating_Time>224.1</Network_Creating_Time>
        <Network_Time_to_live>0.363867</Network_Time_to_live>
        <The_Location_of_ZOR>204.861,426.17,0</The_Location_of_ZOR>
        <The_Shape_of_ZOR>1</The_Shape_of_ZOR>
        <The_Length_of_ZOR>840</The_Length_of_ZOR>
        <The_Width_of_ZOR>840</The_Width_of_ZOR>
        <The_Location_of_ZOF>204.861,426.17,0</The_Location_of_ZOF>
        <The_Shape_of_ZOF>1</The_Shape_of_ZOF>
        <The_Length_of_ZOF>840</The_Length_of_ZOF>
        <The_Width_of_ZOF>840</The_Width_of_ZOF>
        <The_Number_of_Received_Message_Nodes_ZOR>110</The_Number_of_Received_Message_Nodes_ZOR>
        <The_Number_of_Received_Message_Nodes_ZOF>110</The_Number_of_Received_Message_Nodes_ZOF>
        <The_Number_of_Nodes_Which_Passing_Through_ZOR>111</The_Number_of_Nodes_Which_Passing_Through_ZOR>
        <The_Number_of_Nodes_Which_Passing_Through_ZOF>111</The_Number_of_Nodes_Which_Passing_Through_ZOF>
        <The_Packet_Delivery_Ratio>0.990991</The_Packet_Delivery_Ratio>
        <The_Max_Hops>5</The_Max_Hops>
        <The_Max_Delay_Time>0.0267527</The_Max_Delay_Time>
        <Delay_Time_Per_Hop>
            <Delay_Time>0.0044889</Delay_Time>
            <Delay_Time>0.00417284</Delay_Time>
            <Delay_Time>0.0068664</Delay_Time>
            <Delay_Time>0.0102376</Delay_Time>
            <Delay_Time>0.000986929</Delay_Time>
        </Delay_Time_Per_Hop>
    </Network_Identification_Number>
    <Network_Identification_Number ID="22">
        <Network_Created_by>97</Network_Created_by>
        <Network_Creating_Time>224.7</Network_Creating_Time>
        <Network_Time_to_live>0.313283</Network_Time_to_live>
        <The_Location_of_ZOR>385.841,426.17,0</The_Location_of_ZOR>
        <The_Shape_of_ZOR>1</The_Shape_of_ZOR>
        <The_Length_of_ZOR>840</The_Length_of_ZOR>
        <The_Width_of_ZOR>840</The_Width_of_ZOR>
        <The_Location_of_ZOF>385.841,426.17,0</The_Location_of_ZOF>
        <The_Shape_of_ZOF>1</The_Shape_of_ZOF>
        <The_Length_of_ZOF>840</The_Length_of_ZOF>
        <The_Width_of_ZOF>840</The_Width_of_ZOF>
        <The_Number_of_Received_Message_Nodes_ZOR>137</The_Number_of_Received_Message_Nodes_ZOR>
        <The_Number_of_Received_Message_Nodes_ZOF>137</The_Number_of_Received_Message_Nodes_ZOF>
        <The_Number_of_Nodes_Which_Passing_Through_ZOR>138</The_Number_of_Nodes_Which_Passing_Through_ZOR>
        <The_Number_of_Nodes_Which_Passing_Through_ZOF>138</The_Number_of_Nodes_Which_Passing_Through_ZOF>
        <The_Packet_Delivery_Ratio>0.992754</The_Packet_Delivery_Ratio>
        <The_Max_Hops>6</The_Max_Hops>
        <The_Max_Delay_Time>0.0872671</The_Max_Delay_Time>
        <Delay_Time_Per_Hop>
            <Delay_Time>0.00455954</Delay_Time>
            <Delay_Time>0.00240062</Delay_Time>
            <Delay_Time>0.00317598</Delay_Time>
            <Delay_Time>0.0055823</Delay_Time>
            <Delay_Time>0.00991942</Delay_Time>
            <Delay_Time>0.0616292</Delay_Time>
        </Delay_Time_Per_Hop>
    </Network_Identification_Number>
    <Network_Identification_Number ID="23">
        <Network_Created_by>234</Network_Created_by>
        <Network_Creating_Time>225.3</Network_Creating_Time>
        <Network_Time_to_live>0.327847</Network_Time_to_live>
        <The_Location_of_ZOR>213.871,226.17,0</The_Location_of_ZOR>
        <The_Shape_of_ZOR>1</The_Shape_of_ZOR>
        <The_Length_of_ZOR>840</The_Length_of_ZOR>
        <The_Width_of_ZOR>840</The_Width_of_ZOR>
        <The_Location_of_ZOF>213.871,226.17,0</The_Location_of_ZOF>
        <The_Shape_of_ZOF>1</The_Shape_of_ZOF>
        <The_Length_of_ZOF>840</The_Length_of_ZOF>
        <The_Width_of_ZOF>840</The_Width_of_ZOF>
        <The_Number_of_Received_Message_Nodes_ZOR>84</The_Number_of_Received_Message_Nodes_ZOR>
        <The_Number_of_Received_Message_Nodes_ZOF>84</The_Number_of_Received_Message_Nodes_ZOF>
        <The_Number_of_Nodes_Which_Passing_Through_ZOR>85</The_Number_of_Nodes_Which_Passing_Through_ZOR>
        <The_Number_of_Nodes_Which_Passing_Through_ZOF>85</The_Number_of_Nodes_Which_Passing_Through_ZOF>
        <The_Packet_Delivery_Ratio>0.988235</The_Packet_Delivery_Ratio>
        <The_Max_Hops>4</The_Max_Hops>
        <The_Max_Delay_Time>0.0787869</The_Max_Delay_Time>
        <Delay_Time_Per_Hop>
            <Delay_Time>0.00434382</Delay_Time>
            <Delay_Time>0.00964662</Delay_Time>
            <Delay_Time>0.00873293</Delay_Time>
            <Delay_Time>0.0560635</Delay_Time>
        </Delay_Time_Per_Hop>
    </Network_Identification_Number>
    <Network_Identification_Number ID="24">
        <Network_Created_by>205</Network_Created_by>
        <Network_Creating_Time>225.9</Network_Creating_Time>
        <Network_Time_to_live>0.381495</Network_Time_to_live>
        <The_Location_of_ZOR>401.359,226.17,0</The_Location_of_ZOR>
        <The_Shape_of_ZOR>1</The_Shape_of_ZOR>
        <The_Length_of_ZOR>840</The_Length_of_ZOR>
        <The_Width_of_ZOR>840</The_Width_of_ZOR>
        <The_Location_of_ZOF>401.359,226.17,0</The_Location_of_ZOF>
        <The_Shape_of_ZOF>1</The_Shape_of_ZOF>
        <The_Length_of_ZOF>840</The_Length_of_ZOF>
        <The_Width_of_ZOF>840</The_Width_of_ZOF>
        <The_Number_of_Received_Message_Nodes_ZOR>106</The_Number_of_Received_Message_Nodes_ZOR>
        <The_Number_of_Received_Message_Nodes_ZOF>106</The_Number_of_Received_Message_Nodes_ZOF>
        <The_Number_of_Nodes_Which_Passing_Through_ZOR>107</The_Number_of_Nodes_Which_Passing_Through_ZOR>
        <The_Number_of_Nodes_Which_Passing_Through_ZOF>107</The_Number_of_Nodes_Which_Passing_Through_ZOF>
        <The_Packet_Delivery_Ratio>0.990654</The_Packet_Delivery_Ratio>
        <The_Max_Hops>6</The_Max_Hops>
        <The_Max_Delay_Time>0.0314098</The_Max_Delay_Time>
        <Delay_Time_Per_Hop>
            <Delay_Time>0.00454495</Delay_Time>
            <Delay_Time>0.00760025</Delay_Time>
            <Delay_Time>0.010032</Delay_Time>
            <Delay_Time>0.000705694</Delay_Time>
            <Delay_Time>0.00451805</Delay_Time>
            <Delay_Time>0.00400884</Delay_Time>
        </Delay_Time_Per_Hop>
    </Network_Identification_Number>
    <Network_Identification_Number ID="25">
        <Network_Created_by>239</Network_Created_by>
        <Network_Creating_Time>226.5</Network_Creating_Time>
        <Network_Time_to_live>0.225287</Network_Time_to_live>
        <The_Location_of_ZOR>436.145,224.48,0</The_Location_of_ZOR>
        <The_Shape_of_ZOR>1</The_Shape_of_ZOR>
        <The_Length_of_ZOR>840</The_Length_of_ZOR>
        <The_Width_of_ZOR>840</The_Width_of_ZOR>
        <The_Location_of_ZOF>436.145,224.48,0</The_Location_of_ZOF>
        <The_Shape_of_ZOF>1</The_Shape_of_ZOF>
        <The_Length_of_ZOF>840</The_Length_of_ZOF>
        <The_Width_of_ZOF>840</The_Width_of_ZOF>
        <The_Number_of_Received_Message_Nodes_ZOR>121</The_Number_of_Received_Message_Nodes_ZOR>
        <The_Number_of_Received_Message_Nodes_ZOF>121</The_Number_of_Received_Message_Nodes_ZOF>
        <The_Number_of_Nodes_Which_Passing_Through_ZOR>124</The_Number_of_Nodes_Which_Passing_Through_ZOR>
        <The_Number_of_Nodes_Which_Passing_Through_ZOF>124</The_Number_of_Nodes_Which_Passing_Through_ZOF>
        <The_Packet_Delivery_Ratio>0.975806</The_Packet_Delivery_Ratio>
        <The_Max_Hops>4</The_Max_Hops>
        <The_Max_Delay_Time>0.0254875</The_Max_Delay_Time>
        <Delay_Time_Per_Hop>
            <Delay_Time>0.00439094</Delay_Time>
            <Delay_Time>0.00367568</Delay_Time>
            <Delay_Time>0.0160751</Delay_Time>
            <Delay_Time>0.00134577</Delay_Time>
        </Delay_Time_Per_Hop>
    </Network_Identification_Number>
    <Network_Identification_Number ID="26">
        <Network_Created_by>240</Network_Created_by>
        <Network_Creating_Time>227</Network_Creating_Time>
        <Network_Time_to_live>0.257948</Network_Time_to_live>
        <The_Location_of_ZOR>835.63,424.48,0</The_Location_of_ZOR>
        <The_Shape_of_ZOR>1</The_Shape_of_ZOR>
        <The_Length_of_ZOR>840</The_Length_of_ZOR>
        <The_Width_of_ZOR>840</The_Width_of_ZOR>
        <The_Location_of_ZOF>835.63,424.48,0</The_Location_of_ZOF>
        <The_Shape_of_ZOF>1</The_Shape_of_ZOF>
        <The_Length_of_ZOF>840</The_Length_of_ZOF>
        <The_Width_of_ZOF>840</The_Width_of_ZOF>
        <The_Number_of_Received_Message_Nodes_ZOR>112</The_Number_of_Received_Message_Nodes_ZOR>
        <The_Number_of_Received_Message_Nodes_ZOF>112</The_Number_of_Received_Message_Nodes_ZOF>
        <The_Number_of_Nodes_Which_Passing_Through_ZOR>129</The_Number_of_Nodes_Which_Passing_Through_ZOR>
        <The_Number_of_Nodes_Which_Passing_Through_ZOF>129</The_Number_of_Nodes_Which_Passing_Through_ZOF>
        <The_Packet_Delivery_Ratio>0.868217</The_Packet_Delivery_Ratio>
        <The_Max_Hops>4</The_Max_Hops>
        <The_Max_Delay_Time>0.0729316</The_Max_Delay_Time>
        <Delay_Time_Per_Hop>
            <Delay_Time>0.00421413</Delay_Time>
            <Delay_Time>0.00549491</Delay_Time>
            <Delay_Time>0.00551877</Delay_Time>
            <Delay_Time>0.0577038</Delay_Time>
        </Delay_Time_Per_Hop>
    </Network_Identification_Number>
    <Network_Identification_Number ID="27">
        <Network_Created_by>284</Network_Created_by>
        <Network_Creating_Time>227.5</Network_Creating_Time>
        <Network_Time_to_live>0.199919</Network_Time_to_live>
        <The_Location_of_ZOR>198.404,226.17,0</The_Location_of_ZOR>
        <The_Shape_of_ZOR>1</The_Shape_of_ZOR>
        <The_Length_of_ZOR>840</The_Length_of_ZOR>
        <The_Width_of_ZOR>840</The_Width_of_ZOR>
        <The_Location_of_ZOF>198.404,226.17,0</The_Location_of_ZOF>
        <The_Shape_of_ZOF>1</The_Shape_of_ZOF>
        <The_Length_of_ZOF>840</The_Length_of_ZOF>
        <The_Width_of_ZOF>840</The_Width_of_ZOF>
        <The_Number_of_Received_Message_Nodes_ZOR>74</The_Number_of_Received_Message_Nodes_ZOR>
        <The_Number_of_Received_Message_Nodes_ZOF>74</The_Number_of_Received_Message_Nodes_ZOF>
        <The_Number_of_Nodes_Which_Passing_Through_ZOR>75</The_Number_of_Nodes_Which_Passing_Through_ZOR>
        <The_Number_of_Nodes_Which_Passing_Through_ZOF>75</The_Number_of_Nodes_Which_Passing_Through_ZOF>
        <The_Packet_Delivery_Ratio>0.986667</The_Packet_Delivery_Ratio>
        <The_Max_Hops>4</The_Max_Hops>
        <The_Max_Delay_Time>0.0647442</The_Max_Delay_Time>
        <Delay_Time_Per_Hop>
            <Delay_Time>0.00439013</Delay_Time>
            <Delay_Time>0.0039227</Delay_Time>
            <Delay_Time>0.00364487</Delay_Time>
            <Delay_Time>0.0527865</Delay_Time>
        </Delay_Time_Per_Hop>
    </Network_Identification_Number>
    <Network_Identification_Number ID="28">
        <Network_Created_by>123</Network_Created_by>
        <Network_Creating_Time>233.5</Network_Creating_Time>
        <Network_Time_to_live>0.491428</Network_Time_to_live>
        <The_Location_of_ZOR>824.48,592.752,0</The_Location_of_ZOR>
        <The_Shape_of_ZOR>1</The_Shape_of_ZOR>
        <The_Length_of_ZOR>840</The_Length_of_ZOR>
        <The_Width_of_ZOR>840</The_Width_of_ZOR>
        <The_Location_of_ZOF>824.48,592.752,0</The_Location_of_ZOF>
        <The_Shape_of_ZOF>1</The_Shape_of_ZOF>
        <The_Length_of_ZOF>840</The_Length_of_ZOF>
        <The_Width_of_ZOF>840</The_Width_of_ZOF>
        <The_Number_of_Received_Message_Nodes_ZOR>143</The_Number_of_Received_Message_Nodes_ZOR>
        <The_Number_of_Received_Message_Nodes_ZOF>143</The_Number_of_Received_Message_Nodes_ZOF>
        <The_Number_of_Nodes_Which_Passing_Through_ZOR>144</The_Number_of_Nodes_Which_Passing_Through_ZOR>
        <The_Number_of_Nodes_Which_Passing_Through_ZOF>144</The_Number_of_Nodes_Which_Passing_Through_ZOF>
        <The_Packet_Delivery_Ratio>0.993056</The_Packet_Delivery_Ratio>
        <The_Max_Hops>6</The_Max_Hops>
        <The_Max_Delay_Time>0.0811201</The_Max_Delay_Time>
        <Delay_Time_Per_Hop>
            <Delay_Time>0.00443501</Delay_Time>
            <Delay_Time>0.00376569</Delay_Time>
            <Delay_Time>0.0451854</Delay_Time>
            <Delay_Time>0.00992274</Delay_Time>
            <Delay_Time>0.00828416</Delay_Time>
            <Delay_Time>0.00952706</Delay_Time>
        </Delay_Time_Per_Hop>
    </Network_Identification_Number>
    <Network_Identification_Number ID="29">
        <Network_Created_by>298</Network_Created_by>
        <Network_Creating_Time>234.2</Network_Creating_Time>
        <Network_Time_to_live>0.38643</Network_Time_to_live>
        <The_Location_of_ZOR>826.17,611.183,0</The_Location_of_ZOR>
        <The_Shape_of_ZOR>1</The_Shape_of_ZOR>
        <The_Length_of_ZOR>840</The_Length_of_ZOR>
        <The_Width_of_ZOR>840</The_Width_of_ZOR>
        <The_Location_of_ZOF>826.17,611.183,0</The_Location_of_ZOF>
        <The_Shape_of_ZOF>1</The_Shape_of_ZOF>
        <The_Length_of_ZOF>840</The_Length_of_ZOF>
        <The_Width_of_ZOF>840</The_Width_of_ZOF>
        <The_Number_of_Received_Message_Nodes_ZOR>140</The_Number_of_Received_Message_Nodes_ZOR>
        <The_Number_of_Received_Message_Nodes_ZOF>140</The_Number_of_Received_Message_Nodes_ZOF>
        <The_Number_of_Nodes_Which_Passing_Through_ZOR>141</The_Number_of_Nodes_Which_Passing_Through_ZOR>
        <The_Number_of_Nodes_Which_Passing_Through_ZOF>141</The_Number_of_Nodes_Which_Passing_Through_ZOF>
        <The_Packet_Delivery_Ratio>0.992908</The_Packet_Delivery_Ratio>
        <The_Max_Hops>5</The_Max_Hops>
        <The_Max_Delay_Time>0.0310239</The_Max_Delay_Time>
        <Delay_Time_Per_Hop>
            <Delay_Time>0.00454722</Delay_Time>
            <Delay_Time>0.00611417</Delay_Time>
            <Delay_Time>0.00269145</Delay_Time>
            <Delay_Time>0.014327</Delay_Time>
            <Delay_Time>0.00334405</Delay_Time>
        </Delay_Time_Per_Hop>
    </Network_Identification_Number>
</Protocol>
